Workbook

Sheet Index
B2: PIKETTY-ZUCMAN WEALTH-INCOME DATA SET
B3: This database supports our paper "Capital is Back: Wealth-Income Ratios in Rich Countries, 1700-2010"
B6: Germany, 1870-2010
B7: Last update: June 4, 2013
B9: Summary Macro Variables
B10: =TableDE1!A3 -> Table DE.1: National income and private wealth in Germany, 1870-2011 (annual series)
B11: =TableDE2!A3 -> Table DE.2: National income and private wealth in Germany, 1870-2010 (decennial averages)
B12: =TableDE3!A3 -> Table DE.3: Economic growth, population growth and price deflators in Germany (changing boundaries), 1870-2010
B13: =TableDE3b!A3 -> Table DE.3b: Economic and population growth in Germany, 1870-2011: Corrections for frontier changes
B14: =TableDE3c!A3 -> Table DE.3c: Economic growth, population growth and price deflators in Germany (fixed boundaries), 1870-2010
B15: =TableDE3d!A3 -> Table DE.3d: Summary macro variables, 1870-2011 (annual series)
B16: =TableDE3e!A3 -> Table DE.3e: Summary macro variables, 1870-2010 (decennial averages)
B17: Wealth Accumulation
B18: =TableDE4a!A3 -> Table DE.4a: Sources of private wealth accumulation in Germany, 1870-2010 - Additive decomposition
B19: =Table_DE_4b__Sources_of_private_wealth_accumulation_in_Germany__1870_2010___Multiplicative_decomposition -> Table DE.4b: Sources of private wealth accumulation in Germany, 1870-2010 - Multiplicative decomposition
B20: =TableDE4c!A3 -> Table DE.4c: Sources of market value national wealth accumulation in Germany, 1870-2010
B21: =TableDE4e!A3 -> Table DE.4e: Sources of government wealth accumulation in Germany, 1870-2010
B22: =TableDE4f!A3 -> Table DE.4f: Sources of foreign wealth accumulation in Germany, 1870-2010
B23: =TableDE4g!A3 -> Table DE.4g: Sources of book value national wealth accumulation in Germany, 1970-2010
B24: =TableDE5a!A3 -> Table DE.5a: Accumulation equation for private wealth in Germany, 1870-2010 (annual series)
B25: =TableDE5b!A3 -> Table DE.5b: Accumulation equation for national wealth in Germany, 1870-2010 (annual series)
B26: =TableDE5c!A3 -> Table DE.5c: Accumulation equation for government wealth in Germany, 1870-2010 (annual series)
B27: Structure of National Wealth
B28: =TableDE6a!A3 -> Table DE.6a: Structure of national wealth in Germany, 1870-2011: private wealth vs government wealth
B29: =TableDE6b!A3 -> Table DE.6b: Structure of national wealth in Germany, 1870-2011: corporate wealth and net foreign asset position
B30: =TableDE6c!A3 -> Table DE.6c: Composition of private wealth in Germany, 1950-2011, % of national income
B31: =TableDE6d!A3 -> Table DE.6d: Composition of private wealth in Germany, 1950-2011, % of private wealth
B32: =TableDE6e!A3 -> Table DE.6e: The structure of national wealth in Germany, 1870-2010 (decenial averages)
B33: =TableDE6f!A3 -> Table DE.6f: The changing nature of national wealth in Germany, 1870-2010
B34: =TableDE6g!A3 -> Table DE.6g: Assets and liabilities in Eastern Germany as of 1991 and 1998
B35: Structure of National Income
B36: =TableDE8!A3 -> Table DE.8: Structure of national income in Germany, 1950-2011: national income vs gross domestic product
B37: =TableDE9!A3 -> Table DE.9: Structure of national income in Germany, 1950-2011: decomposition by production sectors
B38: =TableDE10!A3 -> Table DE.10: Structure of national income in Germany, 1980-2011: profits & wages in the corporate sector
B39: =TableDE11a!A3 -> Table DE.11a: Structure of national income in Germany, 1950-2010: capital & labor shares in national income
B40: =TableDE11b!A3 -> Table DE.11b: Structure of national income in Germany, 1950-2011: capital & labor shares in factor-price national income
B41: =TableDE12!A4 -> Table DE.12: Structure of national income in Germany, 1950-2010: disposable income & savings
B42: =TableDE12b!A3 -> Table DE12b: Structure of national income in Germany, 1870-2010: savings, investment and external balance
B43: =TableDE12c!A3 -> Table DE12c: Structure of national income in Germany, 1870-2010: private vs government saving, investment, and depreciation
B44: =TableDE13!A3 -> Table DE.13: Structure of national income in Germany, 1950-2010: taxes & transfers
B45: Prices & Returns
B46: =TableDE15a!A3 -> Table DE.15a: Price indices in Germany, 1870-2011 (annual series)

Sheet TableDE1
B1: Back to index
A3: Table DE.1: National income and private wealth in Germany, 1870-2011 (annual series)
B5: [1] | C5: [2] | D5: [3] | E5: [4] | F5: [5] | G5: [6] | H5: [7] | I5: [8] | J5: [9] | K5: [10] | L5: [11] | M5: [12] | N5: [13] | O5: [14] | P5: [15] | Q5: [16] | R5: [17] | S5: [18] | T5: [19] | U5: [20]
B6: Boundaries: 1870-1944: German Empire (including Alsace-Lorraine from 1871 on, excluding territories lost in the wake of World War 1 from 1919-1923 on, including Saarland from 1935 on, and including annexed territories in 1938-1944); 1945-1949: territory occupied by the Allied powers and USSR; 1950-1990: West Germany (including Saarland & West Berlin); 1991-onwards: reunified Germany.
B7: (1850-1949: current bn marks; 1950-onwards: current bn euros) | D7: (2010 billions euros) | F7: (1850-1949: current bn marks; 1950-onwards: current bn euros) | J7: (2010 euros) | N7: Ratio (private wealth)/ (national income) βt = Wt/Yt | O7: memo: Ratio (dispos. income)/ (national income) | P7: memo: Per adult dispos. income (2010 €) | Q7: memo: Ratio (private wealth)/ (dispos. income) | R7: Population (thousands, mid-year) | S7: Adult population (20-yr+) | T7: Employed population | U7: Land area (1000 km2)
D8: National income Yt | E8: Private wealth Wt | F8: Per capita national income | G8: Per capita private wealth | H8: Per adult national income yt | I8: Per adult private wealth wt | J8: Per capita national income | K8: Per capita private wealth | L8: Per adult national income yt | M8: Per adult private wealth wt
B9: National income Yt | C9: Private wealth Wt | R9: Nt | S9: Nt20+ | T9: Lt
A10: 1870 | B10: =DataDE1c!B33 -> 12.876 | C10: =N10*B10 -> 90.610518 | D10: =B10*(TableDE15a!C$149/TableDE15a!C9)/1.95583 -> 94.828634 | E10: =D10*N10 -> 667.32461 | F10: =1000000*B10/R10 -> 328.20983 | G10: =1000000*C10/R10 -> 2309.6663 | H10: =1000000*B10/S10 -> 580.7513 | I10: =1000000*C10/S10 -> 4086.8419 | J10: =1000000*D10/R10 -> 2417.1863 | K10: =1000000*E10/R10 -> 17010.135 | L10: =1000000*D10/S10 -> 4277.0932 | M10: =1000000*E10/S10 -> 30098.605 | N10: =TableDE5a!F10 -> 7.0371635 | O10: =DataDE1c!AW33/DataDE1c!B33 -> 0.95588692 | P10: =O10*L10 -> 4088.4175 | Q10: =M10/P10 -> 7.3619205 | R10: =DataDE1c!BK33 -> 39231 | S10: =R10*(1-DataDE1c!BN33) -> 22171.281 | T10: =DataDE1c!BO33 -> 17045.5 | U10: 533.1
A11: 1871 | B11: =DataDE1c!B34 -> 14.013 | C11: =N11*B11 -> 96.64773 | D11: =B11*(TableDE15a!C$149/TableDE15a!C10)/1.95583 -> 98.720872 | E11: =D11*N11 -> 680.87834 | F11: =1000000*B11/R11 -> 341.82217 | G11: =1000000*C11/R11 -> 2357.5492 | H11: =1000000*B11/S11 -> 604.83767 | I11: =1000000*C11/S11 -> 4171.5684 | J11: =1000000*D11/R11 -> 2408.1198 | K11: =1000000*E11/R11 -> 16608.814 | L11: =1000000*D11/S11 -> 4261.0506 | M11: =1000000*E11/S11 -> 29388.487 | N11: =TableDE5a!F11 -> 6.8970049 | O11: =DataDE1c!AW34/DataDE1c!B34 -> 0.95703989 | P11: =O11*L11 -> 4077.9954 | Q11: =M11/P11 -> 7.2066013 | R11: =DataDE1c!BK34 -> 40995 | S11: =R11*(1-DataDE1c!BN34) -> 23168.2 | T11: =DataDE1c!BO34 -> 17337 | U11: 540.6
A12: 1872 | B12: =DataDE1c!B35 -> 16.627 | C12: =N12*B12 -> 104.67993 | D12: =B12*(TableDE15a!C$149/TableDE15a!C11)/1.95583 -> 109.14672 | E12: =D12*N12 -> 687.16372 | F12: =1000000*B12/R12 -> 403.71494 | G12: =1000000*C12/R12 -> 2541.7004 | H12: =1000000*B12/S12 -> 712.21541 | I12: =1000000*C12/S12 -> 4483.9514 | J12: =1000000*D12/R12 -> 2650.1571 | K12: =1000000*E12/R12 -> 16684.806 | L12: =1000000*D12/S12 -> 4675.2858 | M12: =1000000*E12/S12 -> 29434.57 | N12: =TableDE5a!F12 -> 6.2957798 | O12: =DataDE1c!AW35/DataDE1c!B35 -> 0.96313225 | P12: =O12*L12 -> 4502.9186 | Q12: =M12/P12 -> 6.536776 | R12: =DataDE1c!BK35 -> 41185 | S12: =R12*(1-DataDE1c!BN35) -> 23345.465 | T12: =DataDE1c!BO35 -> 17663.5 | U12: 540.6
A13: 1873 | B13: =DataDE1c!B36 -> 17.95 | C13: =N13*B13 -> 113.64915 | D13: =B13*(TableDE15a!C$149/TableDE15a!C12)/1.95583 -> 111.759 | E13: =D13*N13 -> 707.59421 | F13: =1000000*B13/R13 -> 432.19686 | G13: =1000000*C13/R13 -> 2736.4238 | H13: =1000000*B13/S13 -> 760.1862 | I13: =1000000*C13/S13 -> 4813.065 | J13: =1000000*D13/R13 -> 2690.9131 | K13: =1000000*E13/R13 -> 17037.326 | L13: =1000000*D13/S13 -> 4733.0168 | M13: =1000000*E13/S13 -> 29966.76 | N13: =TableDE5a!F13 -> 6.3314291 | O13: =DataDE1c!AW36/DataDE1c!B36 -> 0.95749304 | P13: =O13*L13 -> 4531.8306 | Q13: =M13/P13 -> 6.6125067 | R13: =DataDE1c!BK36 -> 41532 | S13: =R13*(1-DataDE1c!BN36) -> 23612.636 | T13: =DataDE1c!BO36 -> 17990 | U13: 540.6
A14: 1874 | B14: =DataDE1c!B37 -> 19.544 | C14: =N14*B14 -> 117.51057 | D14: =B14*(TableDE15a!C$149/TableDE15a!C13)/1.95583 -> 121.01996 | E14: =D14*N14 -> 727.64661 | F14: =1000000*B14/R14 -> 465.52176 | G14: =1000000*C14/R14 -> 2799.0037 | H14: =1000000*B14/S14 -> 816.3644 | I14: =1000000*C14/S14 -> 4908.4859 | J14: =1000000*D14/R14 -> 2882.5945 | K14: =1000000*E14/R14 -> 17331.935 | L14: =1000000*D14/S14 -> 5055.0753 | M14: =1000000*E14/S14 -> 30394.228 | N14: =TableDE5a!F14 -> 6.0126163 | O14: =DataDE1c!AW37/DataDE1c!B37 -> 0.96162505 | P14: =O14*L14 -> 4861.087 | Q14: =M14/P14 -> 6.2525579 | R14: =DataDE1c!BK37 -> 41983 | S14: =R14*(1-DataDE1c!BN37) -> 23940.289 | T14: =DataDE1c!BO37 -> 18316.5 | U14: 540.6
A15: 1875 | B15: =DataDE1c!B38 -> 18.242 | C15: =N15*B15 -> 116.48561 | D15: =B15*(TableDE15a!C$149/TableDE15a!C14)/1.95583 -> 119.47203 | E15: =D15*N15 -> 762.89729 | F15: =1000000*B15/R15 -> 429.12256 | G15: =1000000*C15/R15 -> 2740.1931 | H15: =1000000*B15/S15 -> 750.30004 | I15: =1000000*C15/S15 -> 4791.095 | J15: =1000000*D15/R15 -> 2810.4454 | K15: =1000000*E15/R15 -> 17946.302 | L15: =1000000*D15/S15 -> 4913.9278 | M15: =1000000*E15/S15 -> 31378.241 | N15: =TableDE5a!F15 -> 6.3855721 | O15: =DataDE1c!AW38/DataDE1c!B38 -> 0.95943427 | P15: =O15*L15 -> 4714.5908 | Q15: =M15/P15 -> 6.6555598 | R15: =DataDE1c!BK38 -> 42510 | S15: =R15*(1-DataDE1c!BN38) -> 24312.94 | T15: =DataDE1c!BO38 -> 18643 | U15: 540.6
A16: 1876 | B16: =DataDE1c!B39 -> 17.912 | C16: =N16*B16 -> 114.16671 | D16: =B16*(TableDE15a!C$149/TableDE15a!C15)/1.95583 -> 118.26563 | E16: =D16*N16 -> 753.79617 | F16: =1000000*B16/R16 -> 416.00669 | G16: =1000000*C16/R16 -> 2651.5249 | H16: =1000000*B16/S16 -> 725.21588 | I16: =1000000*C16/S16 -> 4622.3487 | J16: =1000000*D16/R16 -> 2746.7224 | K16: =1000000*E16/R16 -> 17506.937 | L16: =1000000*D16/S16 -> 4788.3045 | M16: =1000000*E16/S16 -> 30519.482 | N16: =TableDE5a!F16 -> 6.3737554 | O16: =DataDE1c!AW39/DataDE1c!B39 -> 0.95801697 | P16: =O16*L16 -> 4587.277 | Q16: =M16/P16 -> 6.6530715 | R16: =DataDE1c!BK39 -> 43057 | S16: =R16*(1-DataDE1c!BN39) -> 24698.852 | T16: =DataDE1c!BO39 -> 18891 | U16: 540.6
A17: 1877 | B17: =DataDE1c!B40 -> 17.414 | C17: =N17*B17 -> 111.59336 | D17: =B17*(TableDE15a!C$149/TableDE15a!C16)/1.95583 -> 117.57512 | E17: =D17*N17 -> 753.45143 | F17: =1000000*B17/R17 -> 399.3304 | G17: =1000000*C17/R17 -> 2559.0112 | H17: =1000000*B17/S17 -> 694.09119 | I17: =1000000*C17/S17 -> 4447.9136 | J17: =1000000*D17/R17 -> 2696.1825 | K17: =1000000*E17/R17 -> 17277.826 | L17: =1000000*D17/S17 -> 4686.3362 | M17: =1000000*E17/S17 -> 30031.239 | N17: =TableDE5a!F17 -> 6.4082554 | O17: =DataDE1c!AW40/DataDE1c!B40 -> 0.95716091 | P17: =O17*L17 -> 4485.5778 | Q17: =M17/P17 -> 6.695066 | R17: =DataDE1c!BK40 -> 43608 | S17: =R17*(1-DataDE1c!BN40) -> 25088.922 | T17: =DataDE1c!BO40 -> 19108 | U17: 540.6
A18: 1878 | B18: =DataDE1c!B41 -> 17.874 | C18: =N18*B18 -> 109.90173 | D18: =B18*(TableDE15a!C$149/TableDE15a!C17)/1.95583 -> 123.77154 | E18: =D18*N18 -> 761.03319 | F18: =1000000*B18/R18 -> 405.05813 | G18: =1000000*C18/R18 -> 2490.578 | H18: =1000000*B18/S18 -> 701.97632 | I18: =1000000*C18/S18 -> 4316.2367 | J18: =1000000*D18/R18 -> 2804.8937 | K18: =1000000*E18/R18 -> 17246.429 | L18: =1000000*D18/S18 -> 4860.954 | M18: =1000000*E18/S18 -> 29888.513 | N18: =TableDE5a!F18 -> 6.1486927 | O18: =DataDE1c!AW41/DataDE1c!B41 -> 0.95703256 | P18: =O18*L18 -> 4652.0913 | Q18: =M18/P18 -> 6.4247477 | R18: =DataDE1c!BK41 -> 44127 | S18: =R18*(1-DataDE1c!BN41) -> 25462.397 | T18: =DataDE1c!BO41 -> 19277 | U18: 540.6
A19: 1879 | B19: =DataDE1c!B42 -> 16.678 | C19: =N19*B19 -> 108.40044 | D19: =B19*(TableDE15a!C$149/TableDE15a!C18)/1.95583 -> 120.33228 | E19: =D19*N19 -> 782.11246 | F19: =1000000*B19/R19 -> 373.61948 | G19: =1000000*C19/R19 -> 2428.3796 | H19: =1000000*B19/S19 -> 645.59377 | I19: =1000000*C19/S19 -> 4196.1054 | J19: =1000000*D19/R19 -> 2695.676 | K19: =1000000*E19/R19 -> 17520.833 | L19: =1000000*D19/S19 -> 4657.9787 | M19: =1000000*E19/S19 -> 30275.029 | N19: =TableDE5a!F19 -> 6.4996065 | O19: =DataDE1c!AW42/DataDE1c!B42 -> 0.95041372 | P19: =O19*L19 -> 4427.0069 | Q19: =M19/P19 -> 6.8387128 | R19: =DataDE1c!BK42 -> 44639 | S19: =R19*(1-DataDE1c!BN42) -> 25833.583 | T19: =DataDE1c!BO42 -> 19554 | U19: 540.6
A20: 1880 | B20: =DataDE1c!B43 -> 16.914 | C20: =N20*B20 -> 109.26095 | D20: =B20*(TableDE15a!C$149/TableDE15a!C19)/1.95583 -> 116.83889 | E20: =D20*N20 -> 754.75507 | F20: =1000000*B20/R20 -> 375.09148 | G20: =1000000*C20/R20 -> 2423.0134 | H20: =1000000*B20/S20 -> 646.2424 | I20: =1000000*C20/S20 -> 4174.5924 | J20: =1000000*D20/R20 -> 2591.0649 | K20: =1000000*E20/R20 -> 16737.744 | L20: =1000000*D20/S20 -> 4464.127 | M20: =1000000*E20/S20 -> 28837.338 | N20: =TableDE5a!F20 -> 6.4597934 | O20: =DataDE1c!AW43/DataDE1c!B43 -> 0.94992314 | P20: =O20*L20 -> 4240.5775 | Q20: =M20/P20 -> 6.8003327 | R20: =DataDE1c!BK43 -> 45093 | S20: =R20*(1-DataDE1c!BN43) -> 26172.841 | T20: =DataDE1c!BO43 -> 19638 | U20: 540.6
A21: 1881 | B21: =DataDE1c!B44 -> 17.368 | C21: =N21*B21 -> 111.42746 | D21: =B21*(TableDE15a!C$149/TableDE15a!C20)/1.95583 -> 121.75245 | E21: =D21*N21 -> 781.12427 | F21: =1000000*B21/R21 -> 382.33611 | G21: =1000000*C21/R21 -> 2452.9446 | H21: =1000000*B21/S21 -> 658.88773 | I21: =1000000*C21/S21 -> 4227.2103 | J21: =1000000*D21/R21 -> 2680.237 | K21: =1000000*E21/R21 -> 17195.533 | L21: =1000000*D21/S21 -> 4618.9079 | M21: =1000000*E21/S21 -> 29633.417 | N21: =TableDE5a!F21 -> 6.4156762 | O21: =DataDE1c!AW44/DataDE1c!B44 -> 0.94864118 | P21: =O21*L21 -> 4381.6862 | Q21: =M21/P21 -> 6.7630167 | R21: =DataDE1c!BK44 -> 45426 | S21: =R21*(1-DataDE1c!BN44) -> 26359.574 | T21: =DataDE1c!BO44 -> 19745 | U21: 540.6
... A53: 1913 | B53: =DataDE1c!B76 -> 52.105 | C53: =N53*B53 -> 324.696 | D53: =B53*(TableDE15a!C$149/TableDE15a!C52)/1.95583 -> 295.86412 | E53: =D53*N53 -> 1843.6982 | F53: =1000000*B53/R53 -> 777.94201 | G53: =1000000*C53/R53 -> 4847.8008 | H53: =1000000*B53/S53 -> 1369.2563 | I53: =1000000*C53/S53 -> 8532.6176 | J53: =1000000*D53/R53 -> 4417.3329 | K53: =1000000*E53/R53 -> 27526.923 | L53: =1000000*D53/S53 -> 7774.9508 | M53: =1000000*E53/S53 -> 48450.157 | N53: =TableDE5a!F53 -> 6.2315709 | O53: =DataDE1c!AW76/DataDE1c!B76 -> 0.92745418 | P53: =O53*L53 -> 7210.9106 | Q53: =M53/P53 -> 6.7190067 | R53: =DataDE1c!BK76 -> 66978 | S53: =R53*(1-DataDE1c!BN76) -> 38053.504 | T53: =DataDE1c!BO76 -> 30968 | U53: 540.9
A54: 1914 | B54: =D54*1.95583*TableDE15a!C53/TableDE15a!C$149 -> 49.586625 | C54: =N54*B54 -> 295.81497 | D54: =D53*DataDE1c!C77/DataDE1c!C76 -> 273.16926 | E54: =D54*N54 -> 1629.624 | F54: =1000000*B54/R54 -> 731.47404 | G54: =1000000*C54/R54 -> 4363.6963 | H54: =1000000*B54/S54 -> 1274.6848 | I54: =1000000*C54/S54 -> 7604.2855 | J54: =1000000*D54/R54 -> 4029.6394 | K54: =1000000*E54/R54 -> 24039.298 | L54: =1000000*D54/S54 -> 7022.1498 | M54: =1000000*E54/S54 -> 41891.478 | N54: =TableDE5a!F54 -> 5.9656201 | R54: =DataDE1c!BK77 -> 67790 | S54: =R54*(1-DataDE1c!BN77) -> 38901.087 | U54: 540.9
A55: 1915 | B55: =D55*1.95583*TableDE15a!C54/TableDE15a!C$149 -> 57.042835 | C55: =N55*B55 -> 325.26924 | D55: =D54*DataDE1c!C78/DataDE1c!C77 -> 250.9447 | E55: =D55*N55 -> 1430.935 | F55: =1000000*B55/R55 -> 840.31104 | G55: =1000000*C55/R55 -> 4791.6155 | H55: =1000000*B55/S55 -> 1449.9505 | I55: =1000000*C55/S55 -> 8267.8971 | J55: =1000000*D55/R55 -> 3696.7237 | K55: =1000000*E55/R55 -> 21079.431 | L55: =1000000*D55/S55 -> 6378.6695 | M55: =1000000*E55/S55 -> 36372.403 | N55: =TableDE5a!F55 -> 5.7021927 | R55: =DataDE1c!BK78 -> 67883 | S55: =R55*(1-DataDE1c!BN78) -> 39341.229 | U55: 540.9
A56: 1916 | B56: =D56*1.95583*TableDE15a!C55/TableDE15a!C$149 -> 70.888421 | C56: =N56*B56 -> 381.55366 | D56: =D55*DataDE1c!C79/DataDE1c!C78 -> 239.31769 | E56: =D56*N56 -> 1288.1165 | F56: =1000000*B56/R56 -> 1046.8644 | G56: =1000000*C56/R56 -> 5634.6993 | H56: =1000000*B56/S56 -> 1788.7708 | I56: =1000000*C56/S56 -> 9627.9766 | J56: =1000000*D56/R56 -> 3534.1903 | K56: =1000000*E56/R56 -> 19022.617 | L56: =1000000*D56/S56 -> 6038.8495 | M56: =1000000*E56/S56 -> 32503.83 | N56: =TableDE5a!F56 -> 5.382454 | R56: =DataDE1c!BK79 -> 67715 | S56: =R56*(1-DataDE1c!BN79) -> 39629.683 | U56: 540.9
A57: 1917 | B57: =D57*1.95583*TableDE15a!C56/TableDE15a!C$149 -> 103.07864 | C57: =N57*B57 -> 521.30756 | D57: =D56*DataDE1c!C80/DataDE1c!C79 -> 233.57474 | E57: =D57*N57 -> 1181.2756 | F57: =1000000*B57/R57 -> 1530.0831 | G57: =1000000*C57/R57 -> 7738.2074 | H57: =1000000*B57/S57 -> 2589.236 | I57: =1000000*C57/S57 -> 13094.743 | J57: =1000000*D57/R57 -> 3467.1467 | K57: =1000000*E57/R57 -> 17534.669 | L57: =1000000*D57/S57 -> 5867.1723 | M57: =1000000*E57/S57 -> 29672.503 | N57: =TableDE5a!F57 -> 5.0573772 | R57: =DataDE1c!BK80 -> 67368 | S57: =R57*(1-DataDE1c!BN80) -> 39810.445 | U57: 540.9
A58: 1918 | B58: =D58*1.95583*TableDE15a!C57/TableDE15a!C$149 -> 120.25965 | C58: =N58*B58 -> 569.75132 | D58: =D57*DataDE1c!C81/DataDE1c!C80 -> 227.3249 | E58: =D58*N58 -> 1076.9919 | F58: =1000000*B58/R58 -> 1799.9977 | G58: =1000000*C58/R58 -> 8527.8071 | H58: =1000000*B58/S58 -> 3016.9026 | I58: =1000000*C58/S58 -> 14293.109 | J58: =1000000*D58/R58 -> 3402.507 | K58: =1000000*E58/R58 -> 16119.978 | L58: =1000000*D58/S58 -> 5702.803 | M58: =1000000*E58/S58 -> 27018.037 | N58: =TableDE5a!F58 -> 4.7376766 | R58: =DataDE1c!BK81 -> 66811 | S58: =R58*(1-DataDE1c!BN81) -> 39861.958 | U58: 540.9
A59: 1919 | B59: =D59*1.95583*TableDE15a!C58/TableDE15a!C$149 -> 146.67191 | C59: =N59*B59 -> 647.71188 | D59: =D58*DataDE1c!C82/DataDE1c!C81 -> 202.16877 | E59: =D59*N59 -> 892.7893 | F59: =1000000*B59/R59 -> 2331.9381 | G59: =1000000*C59/R59 -> 10297.977 | H59: =1000000*B59/S59 -> 3871.4948 | I59: =1000000*C59/S59 -> 17096.751 | J59: =1000000*D59/R59 -> 3214.2831 | K59: =1000000*E59/R59 -> 14194.466 | L59: =1000000*D59/S59 -> 5336.3683 | M59: =1000000*E59/S59 -> 23565.72 | N59: =TableDE5a!F59 -> 4.4160595 | R59: =DataDE1c!BK82 -> 62897 | S59: =R59*(1-DataDE1c!BN82) -> 37885.085
A60: 1920 | B60: =D60*1.95583*TableDE15a!C59/TableDE15a!C$149 -> 402.74688 | C60: =N60*B60 -> 1343.9315 | D60: =D59*DataDE1c!C83/DataDE1c!C82 -> 226.21707 | E60: =D60*N60 -> 754.8668 | F60: =1000000*B60/R60 -> 6592.681 | G60: =1000000*C60/R60 -> 21999.207 | H60: =1000000*B60/S60 -> 10842.637 | I60: =1000000*C60/S60 -> 36180.942 | J60: =1000000*D60/R60 -> 3703.013 | K60: =1000000*E60/R60 -> 12356.635 | L60: =1000000*D60/S60 -> 6090.1515 | M60: =1000000*E60/S60 -> 20322.309 | N60: =TableDE5a!F60 -> 3.3369136 | R60: =DataDE1c!BK83 -> 61090 | S60: =R60*(1-DataDE1c!BN83) -> 37144.736
A61: 1921 | B61: =D61*1.95583*TableDE15a!C60/TableDE15a!C$149 -> 561.34928 | C61: =N61*B61 -> 1602.5567 | D61: =D60*DataDE1c!C84/DataDE1c!C83 -> 239.8089 | E61: =D61*N61 -> 684.61362 | F61: =1000000*B61/R61 -> 9089.6461 | G61: =1000000*C61/R61 -> 25949.393 | H61: =1000000*B61/S61 -> 14810.481 | I61: =1000000*C61/S61 -> 42281.403 | J61: =1000000*D61/R61 -> 3883.1048 | K61: =1000000*E61/R61 -> 11085.604 | L61: =1000000*D61/S61 -> 6327.0503 | M61: =1000000*E61/S61 -> 18062.652 | N61: =TableDE5a!F61 -> 2.8548299 | R61: =DataDE1c!BK84 -> 61757 | S61: =R61*(1-DataDE1c!BN84) -> 37902.165
A62: 1922 | B62: =D62*1.95583*TableDE15a!C61/TableDE15a!C$149 -> 10728.3 | C62: =N62*B62 -> 25382.025 | D62: =D61*DataDE1c!C85/DataDE1c!C84 -> 254.13233 | E62: =D62*N62 -> 601.25025 | F62: =1000000*B62/R62 -> 174975.94 | G62: =1000000*C62/R62 -> 413974.61 | H62: =1000000*B62/S62 -> 282479.72 | I62: =1000000*C62/S62 -> 668317.2 | J62: =1000000*D62/R62 -> 4144.8359 | K62: =1000000*E62/R62 -> 9806.2442 | L62: =1000000*D62/S62 -> 6691.389 | M62: =1000000*E62/S62 -> 15831.12 | N62: =TableDE5a!F62 -> 2.3658944 | R62: =DataDE1c!BK85 -> 61313 | S62: =R62*(1-DataDE1c!BN85) -> 37979.009
A63: 1923 | B63: =D63*1.95583*TableDE15a!C62/TableDE15a!C$149 -> 2.6454682e+12 | C63: =N63*B63 -> 6.358065e+12 | D63: =D62*DataDE1c!C86/DataDE1c!C85 -> 221.01235 | E63: =D63*N63 -> 531.17662 | F63: =1000000*B63/R63 -> 4.2863804e+13 | G63: =1000000*C63/R63 -> 103018001680797 | H63: =1000000*B63/S63 -> 6.8568262e+13 | I63: =1000000*C63/S63 -> 164795578968036 | J63: =1000000*D63/R63 -> 3581.0031 | K63: =1000000*E63/R63 -> 8606.5107 | L63: =1000000*D63/S63 -> 5728.4501 | M63: =1000000*E63/S63 -> 13767.641 | N63: =TableDE5a!F63 -> 2.4033798 | R63: =DataDE1c!BK86 -> 61718 | S63: =R63*(1-DataDE1c!BN86) -> 38581.527 | U63: 468.7
A64: 1924 | B64: =D64*1.95583*TableDE15a!C63/TableDE15a!C$149 -> 55.065401 | C64: =N64*B64 -> 121.86527 | D64: =D63*DataDE1c!C87/DataDE1c!C86 -> 246.24687 | E64: =D64*N64 -> 544.96905 | F64: =1000000*B64/R64 -> 886.6215 | G64: =1000000*C64/R64 -> 1962.1824 | H64: =1000000*B64/S64 -> 1405.4981 | I64: =1000000*C64/S64 -> 3110.5086 | J64: =1000000*D64/R64 -> 3964.881 | K64: =1000000*E64/R64 -> 8774.68 | L64: =1000000*D64/S64 -> 6285.2445 | M64: =1000000*E64/S64 -> 13909.878 | N64: =TableDE5a!F64 -> 2.2131005 | R64: =DataDE1c!BK87 -> 62107 | S64: =R64*(1-DataDE1c!BN87) -> 39178.566 | U64: 468.7
A65: 1925 | B65: =DataDE1c!B88 -> 65.5139 | C65: =N65*B65 -> 150.7519 | D65: =B65*(TableDE15a!C$149/TableDE15a!C64)/1.95583 -> 267.86259 | E65: =D65*N65 -> 616.36988 | F65: =1000000*B65/R65 -> 1049.734 | G65: =1000000*C65/R65 -> 2415.5088 | H65: =1000000*B65/S65 -> 1649.1733 | I65: =1000000*C65/S65 -> 3794.8591 | J65: =1000000*D65/R65 -> 4291.9818 | K65: =1000000*E65/R65 -> 9876.1398 | L65: =1000000*D65/S65 -> 6742.8718 | M65: =1000000*E65/S65 -> 15515.803 | N65: =TableDE5a!F65 -> 2.3010675 | O65: =DataDE1c!AW88/DataDE1c!B88 -> 0.87316737 | P65: =O65*L65 -> 5887.6557 | Q65: =M65/P65 -> 2.6353109 | R65: =DataDE1c!BK88 -> 62410 | S65: =R65*(1-DataDE1c!BN88) -> 39725.297 | T65: =DataDE1c!BO88 -> 31033 | U65: 468.7
A66: 1926 | B66: =DataDE1c!B89 -> 67.777915 | C66: =N66*B66 -> 181.08441 | D66: =B66*(TableDE15a!C$149/TableDE15a!C65)/1.95583 -> 269.78427 | E66: =D66*N66 -> 720.79121 | F66: =1000000*B66/R66 -> 1078.116 | G66: =1000000*C66/R66 -> 2880.4366 | H66: =1000000*B66/S66 -> 1675.7925 | I66: =1000000*C66/S66 -> 4477.2681 | J66: =1000000*D66/R66 -> 4291.3495 | K66: =1000000*E66/R66 -> 11465.335 | L66: =1000000*D66/S66 -> 6670.3506 | M66: =1000000*E66/S66 -> 17821.388 | N66: =TableDE5a!F66 -> 2.6717318 | O66: =DataDE1c!AW89/DataDE1c!B89 -> 0.8999185 | P66: =O66*L66 -> 6002.7719 | Q66: =M66/P66 -> 2.9688597 | R66: =DataDE1c!BK89 -> 62867 | S66: =R66*(1-DataDE1c!BN89) -> 40445.291 | T66: =DataDE1c!BO89 -> 29852 | U66: 468.7
A67: 1927 | B67: =DataDE1c!B90 -> 76.393524 | C67: =N67*B67 -> 209.892 | D67: =B67*(TableDE15a!C$149/TableDE15a!C66)/1.95583 -> 297.20867 | E67: =D67*N67 -> 816.58392 | F67: =1000000*B67/R67 -> 1207.7455 | G67: =1000000*C67/R67 -> 3318.2932 | H67: =1000000*B67/S67 -> 1857.577 | I67: =1000000*C67/S67 -> 5103.712 | J67: =1000000*D67/R67 -> 4698.7285 | K67: =1000000*E67/R67 -> 12909.805 | L67: =1000000*D67/S67 -> 7226.8952 | M67: =1000000*E67/S67 -> 19855.97 | N67: =TableDE5a!F67 -> 2.7475104 | O67: =DataDE1c!AW90/DataDE1c!B90 -> 0.87169693 | P67: =O67*L67 -> 6299.6624 | Q67: =M67/P67 -> 3.1519101 | R67: =DataDE1c!BK90 -> 63253 | S67: =R67*(1-DataDE1c!BN90) -> 41125.361 | T67: =DataDE1c!BO90 -> 31963 | U67: 468.7
A68: 1928 | B68: =DataDE1c!B91 -> 81.783623 | C68: =N68*B68 -> 228.94747 | D68: =B68*(TableDE15a!C$149/TableDE15a!C67)/1.95583 -> 307.09538 | E68: =D68*N68 -> 859.69179 | F68: =1000000*B68/R68 -> 1285.5422 | G68: =1000000*C68/R68 -> 3598.7844 | H68: =1000000*B68/S68 -> 1956.6909 | I68: =1000000*C68/S68 -> 5477.6179 | J68: =1000000*D68/R68 -> 4827.1775 | K68: =1000000*E68/R68 -> 13513.342 | L68: =1000000*D68/S68 -> 7347.3236 | M68: =1000000*E68/S68 -> 20568.313 | N68: =TableDE5a!F68 -> 2.7994293 | O68: =DataDE1c!AW91/DataDE1c!B91 -> 0.8742117 | P68: =O68*L68 -> 6423.1163 | Q68: =M68/P68 -> 3.2022327 | R68: =DataDE1c!BK91 -> 63618 | S68: =R68*(1-DataDE1c!BN91) -> 41796.904 | T68: =DataDE1c!BO91 -> 32531 | U68: 468.7
A69: 1929 | B69: =DataDE1c!B92 -> 81.509642 | C69: =N69*B69 -> 248.2871 | D69: =B69*(TableDE15a!C$149/TableDE15a!C68)/1.95583 -> 300.76233 | E69: =D69*N69 -> 916.15429 | F69: =1000000*B69/R69 -> 1274.4245 | G69: =1000000*C69/R69 -> 3882.0336 | H69: =1000000*B69/S69 -> 1919.8239 | I69: =1000000*C69/S69 -> 5847.9892 | J69: =1000000*D69/R69 -> 4702.4975 | K69: =1000000*E69/R69 -> 14324.311 | L69: =1000000*D69/S69 -> 7083.9559 | M69: =1000000*E69/S69 -> 21578.489 | N69: =TableDE5a!F69 -> 3.0461071 | O69: =DataDE1c!AW92/DataDE1c!B92 -> 0.88159877 | P69: =O69*L69 -> 6245.2068 | Q69: =M69/P69 -> 3.455208 | R69: =DataDE1c!BK92 -> 63958 | S69: =R69*(1-DataDE1c!BN92) -> 42456.833 | T69: =DataDE1c!BO92 -> 32266 | U69: 468.7
A70: 1930 | B70: =DataDE1c!B93 -> 75.05359 | C70: =N70*B70 -> 240.56338 | D70: =B70*(TableDE15a!C$149/TableDE15a!C69)/1.95583 -> 277.65082 | E70: =D70*N70 -> 889.93235 | F70: =1000000*B70/R70 -> 1167.3317 | G70: =1000000*C70/R70 -> 3741.5565 | H70: =1000000*B70/S70 -> 1740.5994 | I70: =1000000*C70/S70 -> 5579.0067 | J70: =1000000*D70/R70 -> 4318.3889 | K70: =1000000*E70/R70 -> 13841.393 | L70: =1000000*D70/S70 -> 6439.1171 | M70: =1000000*E70/S70 -> 20638.796 | N70: =TableDE5a!F70 -> 3.2052214 | O70: =DataDE1c!AW93/DataDE1c!B93 -> 0.88651455 | P70: =O70*L70 -> 5708.371 | Q70: =M70/P70 -> 3.6155317 | R70: =DataDE1c!BK93 -> 64295 | S70: =R70*(1-DataDE1c!BN93) -> 43119.392 | T70: =DataDE1c!BO93 -> 30483 | U70: 468.7
A71: 1931 | B71: =DataDE1c!B94 -> 61.589965 | C71: =N71*B71 -> 207.32547 | D71: =B71*(TableDE15a!C$149/TableDE15a!C70)/1.95583 -> 241.18709 | E71: =D71*N71 -> 811.8892 | F71: =1000000*B71/R71 -> 952.94773 | G71: =1000000*C71/R71 -> 3207.8332 | H71: =1000000*B71/S71 -> 1406.6172 | I71: =1000000*C71/S71 -> 4734.9852 | J71: =1000000*D71/R71 -> 3731.7556 | K71: =1000000*E71/R71 -> 12561.916 | L71: =1000000*D71/S71 -> 5508.3311 | M71: =1000000*E71/S71 -> 18542.263 | N71: =TableDE5a!F71 -> 3.3662216 | O71: =DataDE1c!AW94/DataDE1c!B94 -> 0.9018742 | P71: =O71*L71 -> 4967.8217 | Q71: =M71/P71 -> 3.7324735 | R71: =DataDE1c!BK94 -> 64631 | S71: =R71*(1-DataDE1c!BN94) -> 43785.875 | T71: =DataDE1c!BO94 -> 28115 | U71: 468.7
A72: 1932 | B72: =DataDE1c!B95 -> 49.716754 | C72: =N72*B72 -> 173.31363 | D72: =B72*(TableDE15a!C$149/TableDE15a!C71)/1.95583 -> 220.04563 | E72: =D72*N72 -> 767.0836 | F72: =1000000*B72/R72 -> 765.91007 | G72: =1000000*C72/R72 -> 2669.9783 | H72: =1000000*B72/S72 -> 1119.26 | I72: =1000000*C72/S72 -> 3901.7635 | J72: =1000000*D72/R72 -> 3389.9069 | K72: =1000000*E72/R72 -> 11817.285 | L72: =1000000*D72/S72 -> 4953.8286 | M72: =1000000*E72/S72 -> 17269.148 | N72: =TableDE5a!F72 -> 3.4860206 | O72: =DataDE1c!AW95/DataDE1c!B95 -> 0.91340838 | P72: =O72*L72 -> 4524.8685 | Q72: =M72/P72 -> 3.8164973 | R72: =DataDE1c!BK95 -> 64912 | S72: =R72*(1-DataDE1c!BN95) -> 44419.307 | T72: =DataDE1c!BO95 -> 26113 | U72: 468.7
A73: 1933 | B73: =DataDE1c!B96 -> 51.2088 | C73: =N73*B73 -> 169.63802 | D73: =B73*(TableDE15a!C$149/TableDE15a!C72)/1.95583 -> 237.16199 | E73: =D73*N73 -> 785.64018 | F73: =1000000*B73/R73 -> 785.11 | G73: =1000000*C73/R73 -> 2600.8129 | H73: =1000000*B73/S73 -> 1135.9868 | I73: =1000000*C73/S73 -> 3763.1532 | J73: =1000000*D73/R73 -> 3636.0597 | K73: =1000000*E73/R73 -> 12045.077 | L73: =1000000*D73/S73 -> 5261.0665 | M73: =1000000*E73/S73 -> 17428.194 | N73: =TableDE5a!F73 -> 3.3126732 | O73: =DataDE1c!AW96/DataDE1c!B96 -> 0.89933761 | P73: =O73*L73 -> 4731.475 | Q73: =M73/P73 -> 3.683459 | R73: =DataDE1c!BK96 -> 65225 | S73: =R73*(1-DataDE1c!BN96) -> 45078.691 | T73: =DataDE1c!BO96 -> 26687 | U73: 468.8
A74: 1934 | B74: =DataDE1c!B97 -> 57.926061 | C74: =N74*B74 -> 176.60291 | D74: =B74*(TableDE15a!C$149/TableDE15a!C73)/1.95583 -> 267.54848 | E74: =D74*N74 -> 815.69225 | F74: =1000000*B74/R74 -> 887.85097 | G74: =1000000*C74/R74 -> 2706.8483 | H74: =1000000*B74/S74 -> 1284.4398 | I74: =1000000*C74/S74 -> 3915.9543 | J74: =1000000*D74/R74 -> 4100.7997 | K74: =1000000*E74/R74 -> 12502.372 | L74: =1000000*D74/S74 -> 5932.5616 | M74: =1000000*E74/S74 -> 18086.982 | N74: =TableDE5a!F74 -> 3.0487643 | O74: =DataDE1c!AW97/DataDE1c!B97 -> 0.87947289 | P74: =O74*L74 -> 5217.5271 | Q74: =M74/P74 -> 3.4665813 | R74: =DataDE1c!BK97 -> 65243 | S74: =R74*(1-DataDE1c!BN97) -> 45098.306 | T74: =DataDE1c!BO97 -> 28811 | U74: 468.8
A75: 1935 | B75: =DataDE1c!B98 -> 64.797104 | C75: =N75*B75 -> 188.23312 | D75: =B75*(TableDE15a!C$149/TableDE15a!C74)/1.95583 -> 300.59803 | E75: =D75*N75 -> 873.22585 | F75: =1000000*B75/R75 -> 968.98662 | G75: =1000000*C75/R75 -> 2814.8693 | H75: =1000000*B75/S75 -> 1401.5945 | I75: =1000000*C75/S75 -> 4071.5787 | J75: =1000000*D75/R75 -> 4495.1927 | K75: =1000000*E75/R75 -> 13058.364 | L75: =1000000*D75/S75 -> 6502.0892 | M75: =1000000*E75/S75 -> 18888.322 | N75: =TableDE5a!F75 -> 2.904962 | O75: =DataDE1c!AW98/DataDE1c!B98 -> 0.86774403 | P75: =O75*L75 -> 5642.1491 | Q75: =M75/P75 -> 3.3477176 | R75: =DataDE1c!BK98 -> 66871 | S75: =R75*(1-DataDE1c!BN98) -> 46230.992 | T75: =DataDE1c!BO98 -> 30086 | U75: 470.4
A76: 1936 | B76: =DataDE1c!B99 -> 72.171255 | C76: =N76*B76 -> 200.05577 | D76: =B76*(TableDE15a!C$149/TableDE15a!C75)/1.95583 -> 336.29448 | E76: =D76*N76 -> 932.19457 | F76: =1000000*B76/R76 -> 1071.601 | G76: =1000000*C76/R76 -> 2970.4342 | H76: =1000000*B76/S76 -> 1549.7749 | I76: =1000000*C76/S76 -> 4295.913 | J76: =1000000*D76/R76 -> 4993.3106 | K76: =1000000*E76/R76 -> 13841.253 | L76: =1000000*D76/S76 -> 7221.4451 | M76: =1000000*E76/S76 -> 20017.551 | N76: =TableDE5a!F76 -> 2.7719592 | O76: =DataDE1c!AW99/DataDE1c!B99 -> 0.84749808 | P76: =O76*L76 -> 6120.1609 | Q76: =M76/P76 -> 3.2707557 | R76: =DataDE1c!BK99 -> 67349 | S76: =R76*(1-DataDE1c!BN99) -> 46568.861 | T76: =DataDE1c!BO99 -> 31409 | U76: 470.714
A77: 1937 | B77: =DataDE1c!B100 -> 81.217882 | C77: =N77*B77 -> 216.89678 | D77: =B77*(TableDE15a!C$149/TableDE15a!C76)/1.95583 -> 375.47649 | E77: =D77*N77 -> 1002.7304 | F77: =1000000*B77/R77 -> 1197.3564 | G77: =1000000*C77/R77 -> 3197.6055 | H77: =1000000*B77/S77 -> 1731.3701 | I77: =1000000*C77/S77 -> 4623.7182 | J77: =1000000*D77/R77 -> 5535.4704 | K77: =1000000*E77/R77 -> 14782.775 | L77: =1000000*D77/S77 -> 8004.2565 | M77: =1000000*E77/S77 -> 21375.803 | N77: =TableDE5a!F77 -> 2.6705545 | O77: =DataDE1c!AW100/DataDE1c!B100 -> 0.8224999 | P77: =O77*L77 -> 6583.5002 | Q77: =M77/P77 -> 3.2468752 | R77: =DataDE1c!BK100 -> 67831 | S77: =R77*(1-DataDE1c!BN100) -> 46909.602 | T77: =DataDE1c!BO100 -> 32739 | U77: 470.714
A78: 1938 | B78: =DataDE1c!B101 -> 90.919916 | C78: =N78*B78 -> 240.74413 | D78: =B78*(TableDE15a!C$149/TableDE15a!C77)/1.95583*DataDE1c!BK101/DataDE1c!BI101 -> 450.45718 | E78: =D78*N78 -> 1192.7521 | F78: =1000000*B78/R78 -> 1205.8984 | G78: =1000000*C78/R78 -> 3193.0623 | H78: =1000000*B78/S78 -> 1743.4445 | I78: =1000000*C78/S78 -> 4616.4147 | J78: =1000000*D78/R78 -> 5974.5501 | K78: =1000000*E78/R78 -> 15819.833 | L78: =1000000*D78/S78 -> 8637.7897 | M78: =1000000*E78/S78 -> 22871.745 | N78: =TableDE5a!F78 -> 2.6478701 | O78: =DataDE1c!AW101/DataDE1c!B101 -> 0.80421324 | P78: =O78*L78 -> 6946.6248 | Q78: =M78/P78 -> 3.2924976 | R78: =DataDE1c!BK101 -> 75396 | S78: =R78*(1-DataDE1c!BN101) -> 52149.589 | U78: 583.279
A79: 1939 | B79: =DataDE1c!B102 -> 109.81684 | C79: =N79*B79 -> 309.27336 | D79: =D78*DataDE1c!C102/DataDE1c!C101 -> 535.54471 | E79: =D79*N79 -> 1508.2361 | F79: =1000000*B79/R79 -> 1263.5696 | G79: =1000000*C79/R79 -> 3558.5475 | H79: =1000000*B79/S79 -> 1826.5331 | I79: =1000000*C79/S79 -> 5144.0022 | J79: =1000000*D79/R79 -> 6162.0608 | K79: =1000000*E79/R79 -> 17353.999 | L79: =1000000*D79/S79 -> 8907.4698 | M79: =1000000*E79/S79 -> 25085.799 | N79: =TableDE5a!F79 -> 2.8162654 | O79: =DataDE1c!AW102/DataDE1c!B102 -> 0.80421324 | P79: =O79*L79 -> 7163.5051 | Q79: =M79/P79 -> 3.5018889 | R79: =DataDE1c!BK102 -> 86910 | S79: =R79*(1-DataDE1c!BN102) -> 60123.101 | U79: 680.747
A80: 1940 | B80: =D80*1.95583*TableDE15a!C79/TableDE15a!C$149 -> 135.55496 | C80: =N80*B80 -> 389.38008 | D80: =D79*DataDE1c!C103/DataDE1c!C102 -> 621.8537 | E80: =D80*N80 -> 1786.2677 | F80: =1000000*B80/R80 -> 1380.7764 | G80: =1000000*C80/R80 -> 3966.2645 | H80: =1000000*B80/S80 -> 1995.6423 | I80: =1000000*C80/S80 -> 5732.4597 | J80: =1000000*D80/R80 -> 6334.264 | K80: =1000000*E80/R80 -> 18195.101 | L80: =1000000*D80/S80 -> 9154.94 | M80: =1000000*E80/S80 -> 26297.461 | N80: =TableDE5a!F80 -> 2.8724887 | R80: =DataDE1c!BK103 -> 98173 | S80: =R80*(1-DataDE1c!BN103) -> 67925.48 | U80: 729.773
A81: 1941 | B81: =D81*1.95583*TableDE15a!C80/TableDE15a!C$149 -> 147.84406 | C81: =N81*B81 -> 389.10766 | D81: =D80*DataDE1c!C104/DataDE1c!C103 -> 710.4186 | E81: =D81*N81 -> 1869.7357 | F81: =1000000*B81/R81 -> 1496.5337 | G81: =1000000*C81/R81 -> 3938.6954 | H81: =1000000*B81/S81 -> 2162.6031 | I81: =1000000*C81/S81 -> 5691.7095 | J81: =1000000*D81/R81 -> 7191.1267 | K81: =1000000*E81/R81 -> 18926.175 | L81: =1000000*D81/S81 -> 10391.716 | M81: =1000000*E81/S81 -> 27349.738 | N81: =TableDE5a!F81 -> 2.6318789 | R81: =DataDE1c!BK104 -> 98791 | S81: =R81*(1-DataDE1c!BN104) -> 68363.936 | U81: =U80 -> 729.773
A82: 1942 | B82: =D82*1.95583*TableDE15a!C81/TableDE15a!C$149 -> 153.98753 | C82: =N82*B82 -> 415.21186 | D82: =D81*DataDE1c!C105/DataDE1c!C104 -> 750.56326 | E82: =D82*N82 -> 2023.8182 | F82: =1000000*B82/R82 -> 1555.4296 | G82: =1000000*C82/R82 -> 4194.0592 | H82: =1000000*B82/S82 -> 2247.355 | I82: =1000000*C82/S82 -> 6059.7663 | J82: =1000000*D82/R82 -> 7581.4471 | K82: =1000000*E82/R82 -> 20442.608 | L82: =1000000*D82/S82 -> 10954.017 | M82: =1000000*E82/S82 -> 29536.404 | N82: =TableDE5a!F82 -> 2.6963993 | R82: =DataDE1c!BK105 -> 99000 | S82: =R82*(1-DataDE1c!BN105) -> 68519.451 | U82: =U81 -> 729.773
A83: 1943 | B83: =D83*1.95583*TableDE15a!C82/TableDE15a!C$149 -> 166.31257 | C83: =N83*B83 -> 463.52826 | D83: =D82*DataDE1c!C106/DataDE1c!C105 -> 798.49842 | E83: =D83*N83 -> 2225.4877 | F83: =1000000*B83/R83 -> 1679.9249 | G83: =1000000*C83/R83 -> 4682.1036 | H83: =1000000*B83/S83 -> 2426.8459 | I83: =1000000*C83/S83 -> 6763.8403 | J83: =1000000*D83/R83 -> 8065.6406 | K83: =1000000*E83/R83 -> 22479.674 | L83: =1000000*D83/S83 -> 11651.751 | M83: =1000000*E83/S83 -> 32474.489 | N83: =TableDE5a!F83 -> 2.787091 | R83: =DataDE1c!BK106 -> 99000 | S83: =R83*(1-DataDE1c!BN106) -> 68530.338 | U83: =U82 -> 729.773
A84: 1944 | B84: =D84*1.95583*TableDE15a!C83/TableDE15a!C$149 -> 160.17165 | C84: =N84*B84 -> 474.4385 | D84: =D83*DataDE1c!C107/DataDE1c!C106 -> 730.71594 | E84: =D84*N84 -> 2164.4266 | F84: =1000000*B84/R84 -> 1617.8955 | G84: =1000000*C84/R84 -> 4792.3081 | H84: =1000000*B84/S84 -> 2336.8659 | I84: =1000000*C84/S84 -> 6921.9437 | J84: =1000000*D84/R84 -> 7380.9691 | K84: =1000000*E84/R84 -> 21862.895 | L84: =1000000*D84/S84 -> 10660.97 | M84: =1000000*E84/S84 -> 31578.463 | N84: =TableDE5a!F84 -> 2.9620629 | R84: =DataDE1c!BK107 -> 99000 | S84: =R84*(1-DataDE1c!BN107) -> 68541.225 | U84: =U83 -> 729.773
A85: 1945 | B85: =D85*1.95583*TableDE15a!C84/TableDE15a!C$149 -> 50.903761 | C85: =N85*B85 -> 132.5968 | D85: =D84*DataDE1c!C108/DataDE1c!C107 -> 204.07587 | E85: =D85*N85 -> 531.58757 | F85: =1000000*B85/R85 -> 805.54248 | G85: =1000000*C85/R85 -> 2098.3195 | H85: =1000000*B85/S85 -> 1163.3297 | I85: =1000000*C85/S85 -> 3030.3024 | J85: =1000000*D85/R85 -> 3229.4624 | K85: =1000000*E85/R85 -> 8412.2738 | L85: =1000000*D85/S85 -> 4663.8502 | M85: =1000000*E85/S85 -> 12148.643 | N85: =TableDE5a!F85 -> 2.6048527 | R85: =DataDE1c!BK108+DataDE1c!BL108 -> 63191.901 | S85: =R85*(1-DataDE1c!BN108) -> 43756.952 | U85: =U$150 -> 357
A86: 1946 | B86: =D86*1.95583*TableDE15a!C85/TableDE15a!C$149 -> 49.327519 | C86: =N86*B86 -> 115.9799 | D86: =D85*DataDE1c!C109/DataDE1c!C108 -> 176.37588 | E86: =D86*N86 -> 414.69868 | F86: =1000000*B86/R86 -> 760.48806 | G86: =1000000*C86/R86 -> 1788.0756 | H86: =1000000*B86/S86 -> 1098.0896 | I86: =1000000*C86/S86 -> 2581.8515 | J86: =1000000*D86/R86 -> 2719.2074 | K86: =1000000*E86/R86 -> 6393.4576 | L86: =1000000*D86/S86 -> 3926.3383 | M86: =1000000*E86/S86 -> 9231.6893 | N86: =TableDE5a!F86 -> 2.3512211 | R86: =DataDE1c!BK109+DataDE1c!BL109 -> 64862.976 | S86: =R86*(1-DataDE1c!BN109) -> 44921.213 | U86: =U$150 -> 357
A87: 1947 | B87: =D87*1.95583*TableDE15a!C86/TableDE15a!C$149 -> 62.098314 | C87: =N87*B87 -> 133.17142 | D87: =D86*DataDE1c!C110/DataDE1c!C109 -> 208.8411 | E87: =D87*N87 -> 447.86507 | F87: =1000000*B87/R87 -> 938.37205 | G87: =1000000*C87/R87 -> 2012.3628 | H87: =1000000*B87/S87 -> 1354.7261 | I87: =1000000*C87/S87 -> 2905.2447 | J87: =1000000*D87/R87 -> 3155.8128 | K87: =1000000*E87/R87 -> 6767.7209 | L87: =1000000*D87/S87 -> 4556.0415 | M87: =1000000*E87/S87 -> 9770.5471 | N87: =TableDE5a!F87 -> 2.1445255 | R87: =DataDE1c!BK110+DataDE1c!BL110 -> 66176.645 | S87: =R87*(1-DataDE1c!BN110) -> 45838.28 | U87: =U$150 -> 357
A88: 1948 | B88: =D88*1.95583*TableDE15a!C87/TableDE15a!C$149 -> 85.33944 | C88: =N88*B88 -> 169.66176 | D88: =D87*DataDE1c!C111/DataDE1c!C110 -> 248.10912 | E88: =D88*N88 -> 493.26116 | F88: =1000000*B88/R88 -> 1255.9017 | G88: =1000000*C88/R88 -> 2496.8349 | H88: =1000000*B88/S88 -> 1812.8553 | I88: =1000000*C88/S88 -> 3604.1041 | J88: =1000000*D88/R88 -> 3651.309 | K88: =1000000*E88/R88 -> 7259.0998 | L88: =1000000*D88/S88 -> 5270.5518 | M88: =1000000*E88/S88 -> 10478.286 | N88: =TableDE5a!F88 -> 1.9880815 | R88: =DataDE1c!BK111+DataDE1c!BL111 -> 67950.733 | S88: =R88*(1-DataDE1c!BN111) -> 47074.601 | U88: =U$150 -> 357
A89: 1949 | B89: =D89*1.95583*TableDE15a!C88/TableDE15a!C$149 -> 109.29513 | C89: =N89*B89 -> 200.10272 | D89: =D88*DataDE1c!C112/DataDE1c!C111 -> 298.08395 | E89: =D89*N89 -> 545.74629 | F89: =1000000*B89/R89 -> 1590.5994 | G89: =1000000*C89/R89 -> 2912.1452 | H89: =1000000*B89/S89 -> 2295.6167 | I89: =1000000*C89/S89 -> 4202.9245 | J89: =1000000*D89/R89 -> 4338.0905 | K89: =1000000*E89/R89 -> 7942.3828 | L89: =1000000*D89/S89 -> 6260.9059 | M89: =1000000*E89/S89 -> 11462.765 | N89: =TableDE5a!F89 -> 1.8308476 | R89: =DataDE1c!BK112+DataDE1c!BL112 -> 68713.169 | S89: =R89*(1-DataDE1c!BN112) -> 47610.354 | U89: =U$150 -> 357
A90: 1950 | B90: =TableDE8!B8 -> 50.750383 | C90: =N90*B90 -> 91.907163 | D90: =B90*(TableDE15a!$C$149/TableDE15a!$C89) -> 279.70094 | E90: =D90*N90 -> 506.52859 | F90: =1000000*B90/R90 -> 1000.0554 | G90: =1000000*C90/R90 -> 1811.0653 | H90: =1000000*B90/S90 -> 1438.9287 | I90: =1000000*C90/S90 -> 2605.8493 | J90: =1000000*D90/R90 -> 5511.6125 | K90: =1000000*E90/R90 -> 9981.3368 | L90: =1000000*D90/S90 -> 7930.3777 | M90: =K90/(1-DataDE1!GL11) -> 14361.636 | N90: =TableDE5a!F90 -> 1.8109649 | O90: =TableDE12!F10 -> 0.83667349 | P90: =L90*O90 -> 6635.1367 | Q90: =N90/O90 -> 2.1644823 | R90: =DataDE1!GH11 -> 50747.57 | S90: =R90*(1-DataDE1!GL11) -> 35269.561 | T90: =DataDE1!GI11 -> 20726.759 | U90: 248.6
A91: =A90+1 -> 1951 | B91: =TableDE8!B9 -> 62.195926 | C91: =N91*B91 -> 107.34937 | D91: =B91*(TableDE15a!$C$149/TableDE15a!$C90) -> 307.00212 | E91: =D91*N91 -> 529.8817 | F91: =1000000*B91/R91 -> 1214.8484 | G91: =1000000*C91/R91 -> 2096.8127 | H91: =1000000*B91/S91 -> 1742.7176 | I91: =1000000*C91/S91 -> 3007.908 | J91: =1000000*D91/R91 -> 5996.551 | K91: =1000000*E91/R91 -> 10349.97 | L91: =1000000*D91/S91 -> 8602.1388 | M91: =K91/(1-DataDE1!GL12) -> 14847.181 | N91: =TableDE5a!F91 -> 1.7259871 | O91: =TableDE12!F11 -> 0.80987661 | P91: =L91*O91 -> 6966.671 | Q91: =N91/O91 -> 2.1311729 | R91: =DataDE1!GH12 -> 51196.45 | S91: =R91*(1-DataDE1!GL12) -> 35689.045 | T91: =DataDE1!GI12 -> 21278.555 | U91: 248.6
A92: =A91+1 -> 1952 | B92: =TableDE8!B10 -> 71.06132 | C92: =N92*B92 -> 120.29633 | D92: =B92*(TableDE15a!$C$149/TableDE15a!$C91) -> 335.18751 | E92: =D92*N92 -> 567.42299 | F92: =1000000*B92/R92 -> 1375.8428 | G92: =1000000*C92/R92 -> 2329.0989 | H92: =1000000*B92/S92 -> 1967.7386 | I92: =1000000*C92/S92 -> 3331.0911 | J92: =1000000*D92/R92 -> 6489.6816 | K92: =1000000*E92/R92 -> 10986.073 | L92: =1000000*D92/S92 -> 9281.5813 | M92: =K92/(1-DataDE1!GL13) -> 15712.347 | N92: =TableDE5a!F92 -> 1.6928524 | O92: =TableDE12!F12 -> 0.80142599 | P92: =L92*O92 -> 7438.5005 | Q92: =N92/O92 -> 2.1123004 | R92: =DataDE1!GH13 -> 51649.3 | S92: =R92*(1-DataDE1!GL13) -> 36113.191 | T92: =DataDE1!GI13 -> 21735.03 | U92: 248.6
A93: =A92+1 -> 1953 | B93: =TableDE8!B11 -> 76.415437 | C93: =N93*B93 -> 128.45634 | D93: =B93*(TableDE15a!$C$149/TableDE15a!$C92) -> 365.60976 | E93: =D93*N93 -> 614.59953 | F93: =1000000*B93/R93 -> 1465.0536 | G93: =1000000*C93/R93 -> 2462.7932 | H93: =1000000*B93/S93 -> 2089.054 | I93: =1000000*C93/S93 -> 3511.7542 | J93: =1000000*D93/R93 -> 7009.5509 | K93: =1000000*E93/R93 -> 11783.238 | L93: =1000000*D93/S93 -> 9995.0819 | M93: =K93/(1-DataDE1!GL14) -> 16801.993 | N93: =TableDE5a!F93 -> 1.681026 | O93: =TableDE12!F13 -> 0.79833512 | P93: =L93*O93 -> 7979.4249 | Q93: =N93/O93 -> 2.1056646 | R93: =DataDE1!GH14 -> 52158.8 | S93: =R93*(1-DataDE1!GL14) -> 36578.966 | T93: =DataDE1!GI14 -> 22319.659 | U93: 248.6
A94: =A93+1 -> 1954 | B94: =TableDE8!B12 -> 81.849926 | C94: =N94*B94 -> 139.31832 | D94: =B94*(TableDE15a!$C$149/TableDE15a!$C93) -> 392.79135 | E94: =D94*N94 -> 668.57765 | F94: =1000000*B94/R94 -> 1553.1723 | G94: =1000000*C94/R94 -> 2643.6842 | H94: =1000000*B94/S94 -> 2208.0925 | I94: =1000000*C94/S94 -> 3758.4364 | J94: =1000000*D94/R94 -> 7453.5514 | K94: =1000000*E94/R94 -> 12686.832 | L94: =1000000*D94/S94 -> 10596.462 | M94: =K94/(1-DataDE1!GL15) -> 18036.44 | N94: =TableDE5a!F94 -> 1.7021191 | O94: =TableDE12!F14 -> 0.79708305 | P94: =L94*O94 -> 8446.2602 | Q94: =N94/O94 -> 2.1354351 | R94: =DataDE1!GH15 -> 52698.55 | S94: =R94*(1-DataDE1!GL15) -> 37068.16 | T94: =DataDE1!GI15 -> 22951.946 | U94: 248.6
A95: =A94+1 -> 1955 | B95: =TableDE8!B13 -> 93.701857 | C95: =N95*B95 -> 150.10891 | D95: =B95*(TableDE15a!$C$149/TableDE15a!$C94) -> 440.99693 | E95: =D95*N95 -> 706.47019 | F95: =1000000*B95/R95 -> 1760.3039 | G95: =1000000*C95/R95 -> 2819.9793 | H95: =1000000*B95/S95 -> 2495.1154 | I95: =1000000*C95/S95 -> 3997.1358 | J95: =1000000*D95/R95 -> 8284.6664 | K95: =1000000*E95/R95 -> 13271.906 | L95: =1000000*D95/S95 -> 11742.971 | M95: =K95/(1-DataDE1!GL16) -> 18812.057 | N95: =TableDE5a!F95 -> 1.6019844 | O95: =TableDE12!F15 -> 0.80652233 | P95: =L95*O95 -> 9470.9687 | Q95: =N95/O95 -> 1.9862864 | R95: =DataDE1!GH16 -> 53230.5 | S95: =R95*(1-DataDE1!GL16) -> 37554.118 | T95: =DataDE1!GI16 -> 23829.948 | U95: 248.6
A96: =A95+1 -> 1956 | B96: =TableDE8!B14 -> 103.4376 | C96: =N96*B96 -> 159.43543 | D96: =B96*(TableDE15a!$C$149/TableDE15a!$C95) -> 473.84914 | E96: =D96*N96 -> 730.37601 | F96: =1000000*B96/R96 -> 1935.995 | G96: =1000000*C96/R96 -> 2984.0812 | H96: =1000000*B96/S96 -> 2736.002 | I96: =1000000*C96/S96 -> 4217.1866 | J96: =1000000*D96/R96 -> 8868.8211 | K96: =1000000*E96/R96 -> 13670.119 | L96: =1000000*D96/S96 -> 12533.665 | M96: =K96/(1-DataDE1!GL17) -> 19318.993 | N96: =TableDE5a!F96 -> 1.5413682 | O96: =TableDE12!F16 -> 0.80492078 | P96: =L96*O96 -> 10088.607 | Q96: =N96/O96 -> 1.9149316 | R96: =DataDE1!GH17 -> 53428.65 | S96: =R96*(1-DataDE1!GL17) -> 37806.113 | T96: =DataDE1!GI17 -> 24522.605 | U96: 248.6
A97: =A96+1 -> 1957 | B97: =TableDE8!B15 -> 112.53719 | C97: =N97*B97 -> 173.1028 | D97: =B97*(TableDE15a!$C$149/TableDE15a!$C96) -> 500.61439 | E97: =D97*N97 -> 770.03656 | F97: =1000000*B97/R97 -> 2095.5866 | G97: =1000000*C97/R97 -> 3223.3958 | H97: =1000000*B97/S97 -> 2952.7781 | I97: =1000000*C97/S97 -> 4541.9132 | J97: =1000000*D97/R97 -> 9322.0809 | K97: =1000000*E97/R97 -> 14339.067 | L97: =1000000*D97/S97 -> 13135.242 | M97: =K97/(1-DataDE1!GL18) -> 20204.406 | N97: =TableDE5a!F97 -> 1.538183 | O97: =TableDE12!F17 -> 0.8138263 | P97: =L97*O97 -> 10689.805 | Q97: =N97/O97 -> 1.8900631 | R97: =DataDE1!GH18 -> 53702 | S97: =R97*(1-DataDE1!GL18) -> 38112.309 | T97: =DataDE1!GI18 -> 25082.873 | U97: 248.6
A98: =A97+1 -> 1958 | B98: =TableDE8!B16 -> 120.43312 | C98: =N98*B98 -> 194.09611 | D98: =B98*(TableDE15a!$C$149/TableDE15a!$C97) -> 520.19881 | E98: =D98*N98 -> 838.37874 | F98: =1000000*B98/R98 -> 2214.1778 | G98: =1000000*C98/R98 -> 3568.481 | H98: =1000000*B98/S98 -> 3110.6741 | I98: =1000000*C98/S98 -> 5013.3198 | J98: =1000000*D98/R98 -> 9563.9197 | K98: =1000000*E98/R98 -> 15413.697 | L98: =1000000*D98/S98 -> 13436.246 | M98: =K98/(1-DataDE1!GL19) -> 21654.534 | N98: =TableDE5a!F98 -> 1.6116506 | O98: =TableDE12!F18 -> 0.82103785 | P98: =L98*O98 -> 11031.666 | Q98: =N98/O98 -> 1.9629431 | R98: =DataDE1!GH19 -> 54391.8 | S98: =R98*(1-DataDE1!GL19) -> 38716.083 | T98: =DataDE1!GI19 -> 25307.404 | U98: 248.6
A99: =A98+1 -> 1959 | B99: =TableDE8!B17 -> 131.63558 | C99: =N99*B99 -> 218.41166 | D99: =B99*(TableDE15a!$C$149/TableDE15a!$C98) -> 559.77791 | E99: =D99*N99 -> 928.7916 | F99: =1000000*B99/R99 -> 2393.89 | G99: =1000000*C99/R99 -> 3971.9769 | H99: =1000000*B99/S99 -> 3353.2568 | I99: =1000000*C99/S99 -> 5563.7721 | J99: =1000000*D99/R99 -> 10179.974 | K99: =1000000*E99/R99 -> 16890.759 | L99: =1000000*D99/S99 -> 14259.663 | M99: =K99/(1-DataDE1!GL20) -> 23659.839 | N99: =TableDE5a!F99 -> 1.6592144 | O99: =TableDE12!F19 -> 0.80869351 | P99: =L99*O99 -> 11531.697 | Q99: =N99/O99 -> 2.0517222 | R99: =DataDE1!GH20 -> 54988.15 | S99: =R99*(1-DataDE1!GL20) -> 39256.04 | T99: =DataDE1!GI20 -> 25599.718 | U99: 248.6
A100: =A99+1 -> 1960 | B100: =TableDE8!B18 -> 147.63695 | C100: =N100*B100 -> 254.36528 | D100: =B100*(TableDE15a!$C$149/TableDE15a!$C99) -> 608.43168 | E100: =D100*N100 -> 1048.2734 | F100: =1000000*B100/R100 -> 2654.9732 | G100: =1000000*C100/R100 -> 4574.2816 | H100: =1000000*B100/S100 -> 3708.0632 | I100: =1000000*C100/S100 -> 6388.6615 | J100: =1000000*D100/R100 -> 10941.501 | K100: =1000000*E100/R100 -> 18851.228 | L100: =1000000*D100/S100 -> 15281.425 | M100: =K100/(1-DataDE1!GL21) -> 26328.53 | N100: =TableDE5a!F100 -> 1.7229106 | O100: =TableDE12!F20 -> 0.79627917 | P100: =L100*O100 -> 12168.281 | Q100: =N100/O100 -> 2.1637018 | R100: =DataDE1!GH21 -> 55607.7 | S100: =R100*(1-DataDE1!GL21) -> 39815.113 | T100: =DataDE1!GI21 -> 26053.017 | U100: 248.6
A101: =A100+1 -> 1961 | B101: =TableDE8!B19 -> 160.78098 | C101: =N101*B101 -> 297.59429 | D101: =B101*(TableDE15a!$C$149/TableDE15a!$C100) -> 632.69787 | E101: =D101*N101 -> 1171.0793 | F101: =1000000*B101/R101 -> 2857.1235 | G101: =1000000*C101/R101 -> 5288.3347 | H101: =1000000*B101/S101 -> 3997.6543 | I101: =1000000*C101/S101 -> 7399.377 | J101: =1000000*D101/R101 -> 11243.22 | K101: =1000000*E101/R101 -> 20810.41 | L101: =1000000*D101/S101 -> 15731.384 | M101: =K101/(1-DataDE1!GL22) -> 29117.686 | N101: =TableDE5a!F101 -> 1.8509297 | O101: =TableDE12!F21 -> 0.78184377 | P101: =L101*O101 -> 12299.485 | Q101: =N101/O101 -> 2.3673907 | R101: =DataDE1!GH22 -> 56273.724 | S101: =R101*(1-DataDE1!GL22) -> 40218.831 | T101: =DataDE1!GI22 -> 26420.825 | U101: 248.6
A102: =A101+1 -> 1962 | B102: =TableDE8!B20 -> 173.97224 | C102: =N102*B102 -> 334.82429 | D102: =B102*(TableDE15a!$C$149/TableDE15a!$C101) -> 658.51537 | E102: =D102*N102 -> 1267.3685 | F102: =1000000*B102/R102 -> 3056.5312 | G102: =1000000*C102/R102 -> 5882.5527 | H102: =1000000*B102/S102 -> 4284.4564 | I102: =1000000*C102/S102 -> 8245.7985 | J102: =1000000*D102/R102 -> 11569.505 | K102: =1000000*E102/R102 -> 22266.491 | L102: =1000000*D102/S102 -> 16217.417 | M102: =K102/(1-DataDE1!GL23) -> 31211.79 | N102: =TableDE5a!F102 -> 1.9245845 | O102: =TableDE12!F22 -> 0.77730358 | P102: =L102*O102 -> 12605.856 | Q102: =N102/O102 -> 2.4759754 | R102: =DataDE1!GH23 -> 56918.197 | S102: =R102*(1-DataDE1!GL23) -> 40605.442 | T102: =DataDE1!GI23 -> 26518.01 | U102: 248.6
... A110: =A109+1 -> 1970 | B110: =TableDE8!B28 -> 321.12 | C110: =N110*B110 -> 722.61092 | D110: =B110*(TableDE15a!$C$149/TableDE15a!$C109) -> 914.31941 | E110: =D110*N110 -> 2057.4775 | F110: =1000000*B110/R110 -> 5255.8291 | G110: =1000000*C110/R110 -> 11827.103 | H110: =1000000*B110/S110 -> 7476.286 | I110: =1000000*C110/S110 -> 16823.76 | J110: =1000000*D110/R110 -> 14964.831 | K110: =1000000*E110/R110 -> 33675.106 | L110: =1000000*D110/S110 -> 21287.1 | M110: =K110/(1-DataDE1!GL31) -> 47902.001 | N110: =TableDE5a!F110 -> 2.2502831 | O110: =TableDE12!F30 -> 0.76354635 | P110: =L110*O110 -> 16253.687 | Q110: =N110/O110 -> 2.9471467 | R110: =DataDE1!GH31 -> 61097.878 | S110: =R110*(1-DataDE1!GL31) -> 42951.808 | T110: =DataDE1!GI31 -> 26589 | U110: 248.6
A111: 1971 | B111: =TableDE8!B29 -> 354.54 | C111: =N111*B111 -> 779.97867 | D111: =B111*(TableDE15a!$C$149/TableDE15a!$C110) -> 938.00741 | E111: =D111*N111 -> 2063.5916 | F111: =1000000*B111/R111 -> 5788.2349 | G111: =1000000*C111/R111 -> 12733.964 | H111: =1000000*B111/S111 -> 8195.1506 | I111: =1000000*C111/S111 -> 18029.116 | J111: =1000000*D111/R111 -> 15313.948 | K111: =1000000*E111/R111 -> 33690.283 | L111: =1000000*D111/S111 -> 21681.932 | M111: =K111/(1-DataDE1!GL32) -> 47699.679 | N111: =TableDE5a!F111 -> 2.1999737 | O111: =TableDE12!F31 -> 0.7600835 | P111: =L111*O111 -> 16480.079 | Q111: =N111/O111 -> 2.8943842 | R111: =DataDE1!GH32 -> 61251.834 | S111: =R111*(1-DataDE1!GL32) -> 43262.17 | T111: =DataDE1!GI32 -> 26710 | U111: 248.6
A112: 1972 | B112: =TableDE8!B30 -> 385.44 | C112: =N112*B112 -> 854.84401 | D112: =B112*(TableDE15a!$C$149/TableDE15a!$C111) -> 975.50709 | E112: =D112*N112 -> 2163.518 | F112: =1000000*B112/R112 -> 6251.4657 | G112: =1000000*C112/R112 -> 13864.747 | H112: =1000000*B112/S112 -> 8809.8446 | I112: =1000000*C112/S112 -> 19538.82 | J112: =1000000*D112/R112 -> 15821.786 | K112: =1000000*E112/R112 -> 35090.18 | L112: =1000000*D112/S112 -> 22296.767 | M112: =K112/(1-DataDE1!GL33) -> 49450.648 | N112: =TableDE5a!F112 -> 2.2178394 | O112: =TableDE12!F32 -> 0.76696763 | P112: =L112*O112 -> 17100.899 | Q112: =N112/O112 -> 2.8916988 | R112: =DataDE1!GH33 -> 61655.94 | S112: =R112*(1-DataDE1!GL33) -> 43751.055 | T112: =DataDE1!GI33 -> 26857 | U112: 248.6
A113: 1973 | B113: =TableDE8!B31 -> 429.54 | C113: =N113*B113 -> 938.45861 | D113: =B113*(TableDE15a!$C$149/TableDE15a!$C112) -> 1022.7141 | E113: =D113*N113 -> 2234.4249 | F113: =1000000*B113/R113 -> 6933.0548 | G113: =1000000*C113/R113 -> 15147.332 | H113: =1000000*B113/S113 -> 9725.1435 | I113: =1000000*C113/S113 -> 21247.485 | J113: =1000000*D113/R113 -> 16507.271 | K113: =1000000*E113/R113 -> 36065.071 | L113: =1000000*D113/S113 -> 23155.1 | M113: =K113/(1-DataDE1!GL34) -> 50589.242 | N113: =TableDE5a!F113 -> 2.1847991 | O113: =TableDE12!F33 -> 0.74663595 | P113: =L113*O113 -> 17288.43 | Q113: =N113/O113 -> 2.9261906 | R113: =DataDE1!GH34 -> 61955.374 | S113: =R113*(1-DataDE1!GL34) -> 44167.986 | T113: =DataDE1!GI34 -> 27181 | U113: 248.6
A114: 1974 | B114: =TableDE8!B32 -> 462.37 | C114: =N114*B114 -> 1017.7998 | D114: =B114*(TableDE15a!$C$149/TableDE15a!$C113) -> 1026.22 | E114: =D114*N114 -> 2258.9842 | F114: =1000000*B114/R114 -> 7452.001 | G114: =1000000*C114/R114 -> 16403.844 | H114: =1000000*B114/S114 -> 10404.916 | I114: =1000000*C114/S114 -> 22903.999 | J114: =1000000*D114/R114 -> 16539.552 | K114: =1000000*E114/R114 -> 36407.969 | L114: =1000000*D114/S114 -> 23093.482 | M114: =K114/(1-DataDE1!GL35) -> 50834.92 | N114: =TableDE5a!F114 -> 2.201267 | O114: =TableDE12!F34 -> 0.7550663 | P114: =L114*O114 -> 17437.11 | Q114: =N114/O114 -> 2.9153294 | R114: =DataDE1!GH35 -> 62046.422 | S114: =R114*(1-DataDE1!GL35) -> 44437.647 | T114: =DataDE1!GI35 -> 26924 | U114: 248.6
A115: 1975 | B115: =TableDE8!B33 -> 482.61 | C115: =N115*B115 -> 1107.4231 | D115: =B115*(TableDE15a!$C$149/TableDE15a!$C114) -> 1013.7296 | E115: =D115*N115 -> 2326.1591 | F115: =1000000*B115/R115 -> 7806.9432 | G115: =1000000*C115/R115 -> 17914.236 | H115: =1000000*B115/S115 -> 10850.512 | I115: =1000000*C115/S115 -> 24898.174 | J115: =1000000*D115/R115 -> 16398.603 | K115: =1000000*E115/R115 -> 37629.124 | L115: =1000000*D115/S115 -> 22791.665 | M115: =K115/(1-DataDE1!GL36) -> 52298.992 | N115: =TableDE5a!F115 -> 2.2946543 | O115: =TableDE12!F35 -> 0.79184021 | P115: =L115*O115 -> 18047.357 | Q115: =N115/O115 -> 2.8978755 | R115: =DataDE1!GH36 -> 61818.05 | S115: =R115*(1-DataDE1!GL36) -> 44478.087 | T115: =DataDE1!GI36 -> 26248 | U115: 248.6
A116: 1976 | B116: =TableDE8!B34 -> 524.83 | C116: =N116*B116 -> 1200.1649 | D116: =B116*(TableDE15a!$C$149/TableDE15a!$C115) -> 1067.1389 | E116: =D116*N116 -> 2440.3 | F116: =1000000*B116/R116 -> 8527.8156 | G116: =1000000*C116/R116 -> 19501.143 | H116: =1000000*B116/S116 -> 11798.306 | I116: =1000000*C116/S116 -> 26979.999 | J116: =1000000*D116/R116 -> 17339.641 | K116: =1000000*E116/R116 -> 39651.751 | L116: =1000000*D116/S116 -> 23989.542 | M116: =K116/(1-DataDE1!GL37) -> 54858.538 | N116: =TableDE5a!F116 -> 2.2867689 | O116: =TableDE12!F36 -> 0.77575597 | P116: =L116*O116 -> 18610.03 | Q116: =N116/O116 -> 2.9477941 | R116: =DataDE1!GH37 -> 61543.31 | S116: =R116*(1-DataDE1!GL37) -> 44483.504 | T116: =DataDE1!GI37 -> 26139 | U116: 248.6
A117: 1977 | B117: =TableDE8!B35 -> 558.19 | C117: =N117*B117 -> 1319.8401 | D117: =B117*(TableDE15a!$C$149/TableDE15a!$C116) -> 1100.7446 | E117: =D117*N117 -> 2602.7104 | F117: =1000000*B117/R117 -> 9091.4317 | G117: =1000000*C117/R117 -> 21496.688 | H117: =1000000*B117/S117 -> 12520.909 | I117: =1000000*C117/S117 -> 29605.684 | J117: =1000000*D117/R117 -> 17928.205 | K117: =1000000*E117/R117 -> 42391.235 | L117: =1000000*D117/S117 -> 24691.096 | M117: =K117/(1-DataDE1!GL38) -> 58382.09 | N117: =TableDE5a!F117 -> 2.3644997 | O117: =TableDE12!F37 -> 0.76583243 | P117: =L117*O117 -> 18909.242 | Q117: =N117/O117 -> 3.0874896 | R117: =DataDE1!GH38 -> 61397.37 | S117: =R117*(1-DataDE1!GL38) -> 44580.631 | T117: =DataDE1!GI38 -> 26198 | U117: 248.6
A118: 1978 | B118: =TableDE8!B36 -> 596.72 | C118: =N118*B118 -> 1466.4499 | D118: =B118*(TableDE15a!$C$149/TableDE15a!$C117) -> 1136.43 | E118: =D118*N118 -> 2792.7968 | F118: =1000000*B118/R118 -> 9728.5165 | G118: =1000000*C118/R118 -> 23908.001 | H118: =1000000*B118/S118 -> 13337.697 | I118: =1000000*C118/S118 -> 32777.627 | J118: =1000000*D118/R118 -> 18527.581 | K118: =1000000*E118/R118 -> 45531.856 | L118: =1000000*D118/S118 -> 25401.125 | M118: =K118/(1-DataDE1!GL39) -> 62423.713 | N118: =TableDE5a!F118 -> 2.4575176 | O118: =TableDE12!F38 -> 0.76808219 | P118: =L118*O118 -> 19510.152 | Q118: =N118/O118 -> 3.1995503 | R118: =DataDE1!GH39 -> 61337.204 | S118: =R118*(1-DataDE1!GL39) -> 44739.357 | T118: =DataDE1!GI39 -> 26457 | U118: 248.6
A119: 1979 | B119: =TableDE8!B37 -> 645.02 | C119: =N119*B119 -> 1603.5423 | D119: =B119*(TableDE15a!$C$149/TableDE15a!$C118) -> 1177.9993 | E119: =D119*N119 -> 2928.5475 | F119: =1000000*B119/R119 -> 10508.549 | G119: =1000000*C119/R119 -> 26124.621 | H119: =1000000*B119/S119 -> 14342.226 | I119: =1000000*C119/S119 -> 35655.276 | J119: =1000000*D119/R119 -> 19191.75 | K119: =1000000*E119/R119 -> 47711.363 | L119: =1000000*D119/S119 -> 26193.189 | M119: =K119/(1-DataDE1!GL40) -> 65117.188 | N119: =TableDE5a!F119 -> 2.4860351 | O119: =TableDE12!F39 -> 0.76788317 | P119: =L119*O119 -> 20113.309 | Q119: =N119/O119 -> 3.2375173 | R119: =DataDE1!GH40 -> 61380.503 | S119: =R119*(1-DataDE1!GL40) -> 44973.494 | T119: =DataDE1!GI40 -> 26968 | U119: 248.6
A120: 1980 | B120: =TableDE8!B38 -> 685.85 | C120: =N120*B120 -> 1734.9564 | D120: =B120*(TableDE15a!$C$149/TableDE15a!$C119) -> 1187.9255 | E120: =D120*N120 -> 3005.0286 | F120: =1000000*B120/R120 -> 11143.219 | G120: =1000000*C120/R120 -> 28188.377 | H120: =1000000*B120/S120 -> 15140.243 | I120: =1000000*C120/S120 -> 38299.425 | J120: =1000000*D120/R120 -> 19300.596 | K120: =1000000*E120/R120 -> 48823.637 | L120: =1000000*D120/S120 -> 26223.636 | M120: =K120/(1-DataDE1!GL41) -> 66336.463 | N120: =TableDE5a!F120 -> 2.529644 | O120: =TableDE12!F40 -> 0.76572137 | P120: =L120*O120 -> 20079.998 | Q120: =N120/O120 -> 3.303609 | R120: =DataDE1!GH41 -> 61548.643 | S120: =R120*(1-DataDE1!GL41) -> 45299.802 | T120: =DataDE1!GI41 -> 27420 | U120: 248.6
A121: 1981 | B121: =TableDE8!B39 -> 712.68 | C121: =N121*B121 -> 1867.3159 | D121: =B121*(TableDE15a!$C$149/TableDE15a!$C120) -> 1184.7959 | E121: =D121*N121 -> 3104.3221 | F121: =1000000*B121/R121 -> 11553.479 | G121: =1000000*C121/R121 -> 30271.643 | H121: =1000000*B121/S121 -> 15579.125 | I121: =1000000*C121/S121 -> 40819.367 | J121: =1000000*D121/R121 -> 19207.098 | K121: =1000000*E121/R121 -> 50325.137 | L121: =1000000*D121/S121 -> 25899.539 | M121: =K121/(1-DataDE1!GL42) -> 67860.218 | N121: =TableDE5a!F121 -> 2.6201323 | O121: =TableDE12!F41 -> 0.77760005 | P121: =L121*O121 -> 20139.483 | Q121: =N121/O121 -> 3.3695115 | R121: =DataDE1!GH42 -> 61685.317 | S121: =R121*(1-DataDE1!GL42) -> 45745.831 | T121: =DataDE1!GI42 -> 27453 | U121: 248.6
A122: 1982 | B122: =TableDE8!B40 -> 738.71 | C122: =N122*B122 -> 2014.789 | D122: =B122*(TableDE15a!$C$149/TableDE15a!$C121) -> 1174.3236 | E122: =D122*N122 -> 3202.8999 | F122: =1000000*B122/R122 -> 11986.326 | G122: =1000000*C122/R122 -> 32692.013 | H122: =1000000*B122/S122 -> 16041.656 | I122: =1000000*C122/S122 -> 43752.695 | J122: =1000000*D122/R122 -> 19054.601 | K122: =1000000*E122/R122 -> 51970.329 | L122: =1000000*D122/S122 -> 25501.34 | M122: =K122/(1-DataDE1!GL43) -> 69553.438 | N122: =TableDE5a!F122 -> 2.7274424 | O122: =TableDE12!F42 -> 0.77873591 | P122: =L122*O122 -> 19858.809 | Q122: =N122/O122 -> 3.5023972 | R122: =DataDE1!GH43 -> 61629.395 | S122: =R122*(1-DataDE1!GL43) -> 46049.484 | T122: =DataDE1!GI43 -> 27241 | U122: 248.6
... A128: 1988 | B128: =TableDE8!B46 -> 973.9 | C128: =N128*B128 -> 2953.814 | D128: =B128*(TableDE15a!$C$149/TableDE15a!$C127) -> 1362.8992 | E128: =D128*N128 -> 4133.6388 | F128: =1000000*B128/R128 -> 15841.802 | G128: =1000000*C128/R128 -> 48047.784 | H128: =1000000*B128/S128 -> 20289.194 | I128: =1000000*C128/S128 -> 61536.609 | J128: =1000000*D128/R128 -> 22169.402 | K128: =1000000*E128/R128 -> 67239.233 | L128: =1000000*D128/S128 -> 28393.189 | M128: =K128/(1-DataDE1!GL49) -> 86115.82 | N128: =TableDE5a!F128 -> 3.0329746 | O128: =TableDE12!F48 -> 0.77966937 | P128: =L128*O128 -> 22137.3 | Q128: =N128/O128 -> 3.8900779 | R128: =DataDE1!GH49 -> 61476.591 | S128: =R128*(1-DataDE1!GL49) -> 48000.922 | T128: =DataDE1!GI49 -> 28937 | U128: 248.6
A129: 1989 | B129: =TableDE8!B47 -> 1043.5 | C129: =N129*B129 -> 3142.9583 | D129: =B129*(TableDE15a!$C$149/TableDE15a!$C128) -> 1419.5332 | E129: =D129*N129 -> 4275.5474 | F129: =1000000*B129/R129 -> 16777.318 | G129: =1000000*C129/R129 -> 50532.258 | H129: =1000000*B129/S129 -> 21334.331 | I129: =1000000*C129/S129 -> 64257.704 | J129: =1000000*D129/R129 -> 22823.153 | K129: =1000000*E129/R129 -> 68741.944 | L129: =1000000*D129/S129 -> 29022.32 | M129: =K129/(1-DataDE1!GL50) -> 87413.458 | N129: =TableDE5a!F129 -> 3.011939 | O129: =TableDE12!F49 -> 0.76938189 | P129: =L129*O129 -> 22329.248 | Q129: =N129/O129 -> 3.9147516 | R129: =DataDE1!GH50 -> 62197.069 | S129: =R129*(1-DataDE1!GL50) -> 48911.775 | T129: =DataDE1!GI50 -> 29480 | U129: =U128 -> 248.6
A130: 1990 | B130: =TableDE8!B48 -> 1136.5 | C130: =N130*B130 -> 3333.7803 | D130: =B130*(TableDE15a!$C$149/TableDE15a!$C129) -> 1495.2558 | E130: =D130*N130 -> 4386.1455 | F130: =1000000*B130/R130 -> 17981.928 | G130: =1000000*C130/R130 -> 52747.732 | H130: =1000000*B130/S130 -> 22704.455 | I130: =1000000*C130/S130 -> 66600.672 | J130: =1000000*D130/R130 -> 23658.234 | K130: =1000000*E130/R130 -> 69398.463 | L130: =1000000*D130/S130 -> 29871.507 | M130: =K130/(1-DataDE1!GL51) -> 87624.322 | N130: =TableDE5a!F130 -> 2.9333747 | O130: =TableDE12!F50 -> 0.77598768 | P130: =L130*O130 -> 23179.922 | Q130: =N130/O130 -> 3.780182 | R130: =DataDE1!GH51 -> 63202.344 | S130: =R130*(1-DataDE1!GL51) -> 50056.256 | T130: =DataDE1!GI51 -> 30409 | U130: =U129 -> 248.6
A131: 1991 | B131: =TableDE8!B49 -> 1330.57 | C131: =N131*B131 -> 3817.1586 | D131: =B131*(TableDE15a!$C$149/TableDE15a!$C130) -> 1698.198 | E131: =D131*N131 -> 4871.815 | F131: =1000000*B131/R131 -> 16629.237 | G131: =1000000*C131/R131 -> 47706.196 | H131: =1000000*B131/S131 -> 21237.85 | I131: =1000000*C131/S131 -> 60927.453 | J131: =1000000*D131/R131 -> 21223.788 | K131: =1000000*E131/R131 -> 60887.112 | L131: =1000000*D131/S131 -> 27105.732 | M131: =K131/(1-DataDE1!GL52) -> 77761.318 | N131: =TableDE5a!F131 -> 2.8688146 | O131: =TableDE12!F51 -> 0.77868132 | P131: =L131*O131 -> 21106.727 | Q131: =N131/O131 -> 3.684196 | R131: =DataDE1!GH52 -> 80013.895 | S131: =R131*(1-DataDE1!GL52) -> 62650.88 | T131: =DataDE1!GI52 -> 38712 | U131: 357
A132: 1992 | B132: =TableDE8!B50 -> 1423.96 | C132: =N132*B132 -> 4125.95 | D132: =B132*(TableDE15a!$C$149/TableDE15a!$C131) -> 1724.2721 | E132: =D132*N132 -> 4996.1098 | F132: =1000000*B132/R132 -> 17661.607 | G132: =1000000*C132/R132 -> 51174.829 | H132: =1000000*B132/S132 -> 22541.937 | I132: =1000000*C132/S132 -> 65315.672 | J132: =1000000*D132/R132 -> 21386.428 | K132: =1000000*E132/R132 -> 61967.563 | L132: =1000000*D132/S132 -> 27296.015 | M132: =K132/(1-DataDE1!GL53) -> 79090.699 | N132: =TableDE5a!F132 -> 2.8975182 | O132: =TableDE12!F52 -> 0.77851204 | P132: =L132*O132 -> 21250.276 | Q132: =N132/O132 -> 3.7218669 | R132: =DataDE1!GH53 -> 80624.598 | S132: =R132*(1-DataDE1!GL53) -> 63169.373 | T132: =DataDE1!GI53 -> 38183 | U132: 357
A133: 1993 | B133: =TableDE8!B51 -> 1454.58 | C133: =N133*B133 -> 4417.35 | D133: =B133*(TableDE15a!$C$149/TableDE15a!$C132) -> 1693.8618 | E133: =D133*N133 -> 5144.0144 | F133: =1000000*B133/R133 -> 17923.179 | G133: =1000000*C133/R133 -> 54430.113 | H133: =1000000*B133/S133 -> 22861.198 | I133: =1000000*C133/S133 -> 69426.165 | J133: =1000000*D133/R133 -> 20871.584 | K133: =1000000*E133/R133 -> 63383.994 | L133: =1000000*D133/S133 -> 26621.918 | M133: =K133/(1-DataDE1!GL54) -> 80846.931 | N133: =TableDE5a!F133 -> 3.036856 | O133: =TableDE12!F53 -> 0.78028709 | P133: =L133*O133 -> 20772.739 | Q133: =N133/O133 -> 3.8919726 | R133: =DataDE1!GH54 -> 81156.363 | S133: =R133*(1-DataDE1!GL54) -> 63626.588 | T133: =DataDE1!GI54 -> 37695 | U133: 357
A134: 1994 | B134: =TableDE8!B52 -> 1517.52 | C134: =N134*B134 -> 4661.4 | D134: =B134*(TableDE15a!$C$149/TableDE15a!$C133) -> 1724.1647 | E134: =D134*N134 -> 5296.1552 | F134: =1000000*B134/R134 -> 18633.973 | G134: =1000000*C134/R134 -> 57238.391 | H134: =1000000*B134/S134 -> 23752.675 | I134: =1000000*C134/S134 -> 72961.62 | J134: =1000000*D134/R134 -> 21171.411 | K134: =1000000*E134/R134 -> 65032.695 | L134: =1000000*D134/S134 -> 26987.14 | M134: =K134/(1-DataDE1!GL55) -> 82896.998 | N134: =TableDE5a!F134 -> 3.0717223 | O134: =TableDE12!F54 -> 0.78188755 | P134: =L134*O134 -> 21100.909 | Q134: =N134/O134 -> 3.9285985 | R134: =DataDE1!GH55 -> 81438.348 | S134: =R134*(1-DataDE1!GL55) -> 63888.384 | T134: =DataDE1!GI55 -> 37667 | U134: 357
A135: 1995 | B135: =TableDE8!B53 -> 1569.37 | C135: =N135*B135 -> 4869.4 | D135: =B135*(TableDE15a!$C$149/TableDE15a!$C134) -> 1747.9516 | E135: =D135*N135 -> 5423.4984 | F135: =1000000*B135/R135 -> 19214.097 | G135: =1000000*C135/R135 -> 59616.996 | H135: =1000000*B135/S135 -> 24476.557 | I135: =1000000*C135/S135 -> 75945.217 | J135: =1000000*D135/R135 -> 21400.506 | K135: =1000000*E135/R135 -> 66400.928 | L135: =1000000*D135/S135 -> 27261.791 | M135: =K135/(1-DataDE1!GL56) -> 84587.169 | N135: =TableDE5a!F135 -> 3.1027737 | O135: =TableDE12!F55 -> 0.79204394 | P135: =L135*O135 -> 21592.536 | Q135: =N135/O135 -> 3.9174262 | R135: =DataDE1!GH56 -> 81678.051 | S135: =R135*(1-DataDE1!GL56) -> 64117.27 | T135: =DataDE1!GI56 -> 37802 | U135: 357
A136: 1996 | B136: =TableDE8!B54 -> 1593.78 | C136: =N136*B136 -> 5112.05 | D136: =B136*(TableDE15a!$C$149/TableDE15a!$C135) -> 1763.8897 | E136: =D136*N136 -> 5657.677 | F136: =1000000*B136/R136 -> 19456.55 | G136: =1000000*C136/R136 -> 62406.892 | H136: =1000000*B136/S136 -> 24778.445 | I136: =1000000*C136/S136 -> 79476.873 | J136: =1000000*D136/R136 -> 21533.216 | K136: =1000000*E136/R136 -> 69067.799 | L136: =1000000*D136/S136 -> 27423.135 | M136: =K136/(1-DataDE1!GL57) -> 87959.718 | N136: =TableDE5a!F136 -> 3.2075004 | O136: =TableDE12!F56 -> 0.79312703 | P136: =L136*O136 -> 21750.03 | Q136: =N136/O136 -> 4.0441194 | R136: =DataDE1!GH57 -> 81914.83 | S136: =R136*(1-DataDE1!GL57) -> 64321.227 | T136: =DataDE1!GI57 -> 37772 | U136: 357
A137: 1997 | B137: =TableDE8!B55 -> 1621.1 | C137: =N137*B137 -> 5368.15 | D137: =B137*(TableDE15a!$C$149/TableDE15a!$C136) -> 1789.411 | E137: =D137*N137 -> 5925.4991 | F137: =1000000*B137/R137 -> 19761.133 | G137: =1000000*C137/R137 -> 65437.496 | H137: =1000000*B137/S137 -> 25159.265 | I137: =1000000*C137/S137 -> 83313.004 | J137: =1000000*D137/R137 -> 21812.836 | K137: =1000000*E137/R137 -> 72231.556 | L137: =1000000*D137/S137 -> 27771.431 | M137: =K137/(1-DataDE1!GL58) -> 91962.991 | N137: =TableDE5a!F137 -> 3.3114243 | O137: =TableDE12!F57 -> 0.79088273 | P137: =L137*O137 -> 21963.945 | Q137: =N137/O137 -> 4.1869979 | R137: =DataDE1!GH58 -> 82034.77 | S137: =R137*(1-DataDE1!GL58) -> 64433.519 | T137: =DataDE1!GI58 -> 37716 | U137: 357
A138: 1998 | B138: =TableDE8!B56 -> 1655.4 | C138: =N138*B138 -> 5639.75 | D138: =B138*(TableDE15a!$C$149/TableDE15a!$C137) -> 1816.5584 | E138: =D138*N138 -> 6188.7973 | F138: =1000000*B138/R138 -> 20176.192 | G138: =1000000*C138/R138 -> 68737.877 | H138: =1000000*B138/S138 -> 25680.488 | I138: =1000000*C138/S138 -> 87490.354 | J138: =1000000*D138/R138 -> 22140.408 | K138: =1000000*E138/R138 -> 75429.725 | L138: =1000000*D138/S138 -> 28180.564 | M138: =K138/(1-DataDE1!GL59) -> 96007.814 | N138: =TableDE5a!F138 -> 3.4068805 | O138: =TableDE12!F58 -> 0.78294068 | P138: =L138*O138 -> 22063.71 | Q138: =N138/O138 -> 4.3513903 | R138: =DataDE1!GH59 -> 82047.195 | S138: =R138*(1-DataDE1!GL59) -> 64461.392 | T138: =DataDE1!GI59 -> 38148 | U138: 357
A139: =A138+1 -> 1999 | B139: =TableDE8!B57 -> 1687.07 | C139: =N139*B139 -> 5918.25 | D139: =B139*(TableDE15a!$C$149/TableDE15a!$C138) -> 1847.7644 | E139: =D139*N139 -> 6481.9667 | F139: =1000000*B139/R139 -> 20548.904 | G139: =1000000*C139/R139 -> 72085.658 | H139: =1000000*B139/S139 -> 26122.26 | I139: =1000000*C139/S139 -> 91637.02 | J139: =1000000*D139/R139 -> 22506.199 | K139: =1000000*E139/R139 -> 78951.857 | L139: =1000000*D139/S139 -> 28610.42 | M139: =K139/(1-DataDE1!GL60) -> 100365.5 | N139: =TableDE5a!F139 -> 3.508005 | O139: =TableDE12!F59 -> 0.77067934 | P139: =L139*O139 -> 22049.46 | Q139: =N139/O139 -> 4.5518347 | R139: =DataDE1!GH60 -> 82100.243 | S139: =R139*(1-DataDE1!GL60) -> 64583.615 | T139: =DataDE1!GI60 -> 38721 | U139: 357
A140: =A139+1 -> 2000 | B140: =TableDE8!B58 -> 1724.53 | C140: =N140*B140 -> 6147.5 | D140: =B140*(TableDE15a!$C$149/TableDE15a!$C139) -> 1901.5773 | E140: =D140*N140 -> 6778.6275 | F140: =1000000*B140/R140 -> 20976.748 | G140: =1000000*C140/R140 -> 74776.641 | H140: =1000000*B140/S140 -> 26586.5 | I140: =1000000*C140/S140 -> 94773.943 | J140: =1000000*D140/R140 -> 23130.307 | K140: =1000000*E140/R140 -> 82453.517 | L140: =1000000*D140/S140 -> 29315.979 | M140: =K140/(1-DataDE1!GL61) -> 104503.82 | N140: =TableDE5a!F140 -> 3.5647394 | O140: =TableDE12!F60 -> 0.76771062 | P140: =L140*O140 -> 22506.188 | Q140: =N140/O140 -> 4.6433373 | R140: =DataDE1!GH61 -> 82211.503 | S140: =R140*(1-DataDE1!GL61) -> 64864.875 | T140: =DataDE1!GI61 -> 39382 | U140: 357
A141: =A140+1 -> 2001 | B141: =TableDE8!B59 -> 1767.48 | C141: =N141*B141 -> 6336.15 | D141: =B141*(TableDE15a!$C$149/TableDE15a!$C140) -> 1927.2459 | E141: =D141*N141 -> 6908.8867 | F141: =1000000*B141/R141 -> 21463.046 | G141: =1000000*C141/R141 -> 76941.792 | H141: =1000000*B141/S141 -> 27134.066 | I141: =1000000*C141/S141 -> 97271.544 | J141: =1000000*D141/R141 -> 23403.131 | K141: =1000000*E141/R141 -> 83896.707 | L141: =1000000*D141/S141 -> 29586.765 | M141: =K141/(1-DataDE1!GL62) -> 106064.1 | N141: =TableDE5a!F141 -> 3.5848496 | O141: =TableDE12!F61 -> 0.785197 | P141: =L141*O141 -> 23231.44 | Q141: =N141/O141 -> 4.5655416 | R141: =DataDE1!GH62 -> 82349.915 | S141: =R141*(1-DataDE1!GL62) -> 65138.783 | T141: =DataDE1!GI62 -> 39485 | U141: 357
A142: =A141+1 -> 2002 | B142: =TableDE8!B60 -> 1787.41 | C142: =N142*B142 -> 6488.6 | D142: =B142*(TableDE15a!$C$149/TableDE15a!$C141) -> 1921.4761 | E142: =D142*N142 -> 6975.2825 | F142: =1000000*B142/R142 -> 21668.599 | G142: =1000000*C142/R142 -> 78660.671 | H142: =1000000*B142/S142 -> 27324.841 | I142: =1000000*C142/S142 -> 99193.785 | J142: =1000000*D142/R142 -> 23293.869 | K142: =1000000*E142/R142 -> 84560.677 | L142: =1000000*D142/S142 -> 29374.362 | M142: =K142/(1-DataDE1!GL63) -> 106633.89 | N142: =TableDE5a!F142 -> 3.6301688 | O142: =TableDE12!F62 -> 0.79106081 | P142: =L142*O142 -> 23236.907 | Q142: =N142/O142 -> 4.5889883 | R142: =DataDE1!GH63 -> 82488.49 | S142: =R142*(1-DataDE1!GL63) -> 65413.373 | T142: =DataDE1!GI63 -> 39257 | U142: =U141 -> 357
A143: =A142+1 -> 2003 | B143: =TableDE8!B61 -> 1811.5 | C143: =N143*B143 -> 6712.45 | D143: =B143*(TableDE15a!$C$149/TableDE15a!$C142) -> 1926.2396 | E143: =D143*N143 -> 7137.6136 | F143: =1000000*B143/R143 -> 21948.484 | G143: =1000000*C143/R143 -> 81329.34 | H143: =1000000*B143/S143 -> 27608.156 | I143: =1000000*C143/S143 -> 102301.06 | J143: =1000000*D143/R143 -> 23338.691 | K143: =1000000*E143/R143 -> 86480.703 | L143: =1000000*D143/S143 -> 29356.844 | M143: =K143/(1-DataDE1!GL64) -> 108780.76 | N143: =TableDE5a!F143 -> 3.7054651 | O143: =TableDE12!F63 -> 0.79465084 | P143: =L143*O143 -> 23328.441 | Q143: =N143/O143 -> 4.6630103 | R143: =DataDE1!GH64 -> 82534.175 | S143: =R143*(1-DataDE1!GL64) -> 65614.67 | T143: =DataDE1!GI64 -> 38918 | U143: =U142 -> 357
A144: =A143+1 -> 2004 | B144: =TableDE8!B62 -> 1891.58 | C144: =N144*B144 -> 7042.05 | D144: =B144*(TableDE15a!$C$149/TableDE15a!$C143) -> 1990.08 | E144: =D144*N144 -> 7408.7497 | F144: =1000000*B144/R144 -> 22923.724 | G144: =1000000*C144/R144 -> 85341.362 | H144: =1000000*B144/S144 -> 28762.515 | I144: =1000000*C144/S144 -> 107078.25 | J144: =1000000*D144/R144 -> 24117.428 | K144: =1000000*E144/R144 -> 89785.331 | L144: =1000000*D144/S144 -> 30260.262 | M144: =K144/(1-DataDE1!GL65) -> 112654.12 | N144: =TableDE5a!F144 -> 3.7228402 | O144: =TableDE12!F64 -> 0.80320156 | P144: =L144*O144 -> 24305.089 | Q144: =N144/O144 -> 4.6350012 | R144: =DataDE1!GH65 -> 82516.26 | S144: =R144*(1-DataDE1!GL65) -> 65765.459 | T144: =DataDE1!GI65 -> 39034 | U144: =U143 -> 357
A145: =A144+1 -> 2005 | B145: =TableDE8!B63 -> 1921.63 | C145: =N145*B145 -> 7373.2 | D145: =B145*(TableDE15a!$C$149/TableDE15a!$C144) -> 2009.2732 | E145: =D145*N145 -> 7709.4827 | F145: =1000000*B145/R145 -> 23301.121 | G145: =1000000*C145/R145 -> 89405.259 | H145: =1000000*B145/S145 -> 29126.402 | I145: =1000000*C145/S145 -> 111756.57 | J145: =1000000*D145/R145 -> 24363.857 | K145: =1000000*E145/R145 -> 93482.924 | L145: =1000000*D145/S145 -> 30454.821 | M145: =K145/(1-DataDE1!GL66) -> 116853.66 | N145: =TableDE5a!F145 -> 3.8369509 | O145: =TableDE12!F65 -> 0.80027893 | P145: =L145*O145 -> 24372.352 | Q145: =N145/O145 -> 4.794517 | R145: =DataDE1!GH66 -> 82469.422 | S145: =R145*(1-DataDE1!GL66) -> 65975.538 | T145: =DataDE1!GI66 -> 38976 | U145: =U144 -> 357
...

Sheet TableDE2
B1: Back to index
A3: Table DE.2: National income and private wealth in Germany, 1870-2010 (decennial averages)
B5: [1] | C5: [2] | D5: [3] | E5: [4] | F5: [5] | G5: [6] | H5: [7] | I5: [8] | J5: [9] | K5: [10] | L5: [11] | M5: [12] | N5: [13] | O5: [14] | P5: [15] | Q5: [16] | R5: [17] | S5: [18] | T5: [19]
B6: Boundaries: 1870-1944: German Empire (including Alsace-Lorraine from 1871 on, excluding territories lost in the wake of World War 1 from 1919-1923 on, including Saarland from 1935 on, and including annexed territories in 1938-1944); 1945-1949: territory occupied by the Allied powers and USSR; 1950-1990: West Germany (including Saarland & West Berlin); 1991-onwards: reunified Germany.
B7: (current billions euros 1950-2010; current billions marks 1850-1949) | D7: (2010 billions euros) | F7: (current euros 1950-2010; current marks 1850-1949) | J7: (2010 euros) | N7: Ratio (private wealth)/ (national income) βt = Wt/Yt | O7: memo: Ratio (dispos. income)/ (national income) | P7: memo: Per adult dispos. income (2010 €) | Q7: memo: Ratio (private wealth)/ (dispos. income) | R7: Population (thousands) | S7: Adult population (20-yr+) | T7: Employed population
B8: National income Yt | C8: Private wealth Wt | D8: National income Yt | E8: Private wealth Wt | F8: Per capita national income | G8: Per capita private wealth | H8: Per adult national income yt | I8: Per adult private wealth wt | J8: Per capita national income | K8: Per capita private wealth | L8: Per adult national income yt | M8: Per adult private wealth wt
R9: Nt | S9: Nt20+ | T9: Lt
A10: 1870 | B10: =AVERAGE(TableDE1!B10:B19) -> 16.913 | C10: =AVERAGE(TableDE1!C10:C19) -> 108.36457 | D10: =AVERAGE(TableDE1!D10:D19) -> 113.48918 | E10: =AVERAGE(TableDE1!E10:E19) -> 728.3898 | F10: =AVERAGE(TableDE1!F10:F19) -> 399.46028 | G10: =AVERAGE(TableDE1!G10:G19) -> 2561.403 | H10: =AVERAGE(TableDE1!H10:H19) -> 699.15322 | I10: =AVERAGE(TableDE1!I10:I19) -> 4483.7612 | ... T10: =AVERAGE(TableDE1!T10:T19) -> 18382.55
A11: =A10+1 -> 1871 | B11: =#REF! -> #REF! | C11: =#REF! -> #REF! | F11: =1000000*B11/R11 -> #REF! | G11: =1000000*C11/R11 -> #REF! | H11: =1000000*B11/S11 -> #REF! | I11: =1000000*C11/S11 -> #REF! | J11: =1000000*D11/R11 -> #DIV/0! | K11: =1000000*E11/R11 -> #DIV/0! | L11: =1000000*D11/S11 -> #DIV/0! | M11: =1000000*E11/S11 -> #DIV/0! | N11: =AVERAGE(TableDE1!N11:N20) -> 6.3812506 | O11: =AVERAGE(TableDE1!O11:O20) -> 0.95712718 | P11: =AVERAGE(TableDE1!P11:P20) -> 4508.0953 | Q11: =AVERAGE(TableDE1!Q11:Q20) -> 6.6675932 | R11: 0 | S11: 0 | T11: 0
A12: =A11+1 -> 1872 | B12: =#REF! -> #REF! | C12: =#REF! -> #REF! | F12: =1000000*B12/R12 -> #REF! | G12: =1000000*C12/R12 -> #REF! | H12: =1000000*B12/S12 -> #REF! | I12: =1000000*C12/S12 -> #REF! | J12: =1000000*D12/R12 -> #DIV/0! | K12: =1000000*E12/R12 -> #DIV/0! | L12: =1000000*D12/S12 -> #DIV/0! | M12: =1000000*E12/S12 -> #DIV/0! | N12: =AVERAGE(TableDE1!N12:N21) -> 6.3331177 | O12: =AVERAGE(TableDE1!O12:O21) -> 0.95628731 | P12: =AVERAGE(TableDE1!P12:P21) -> 4538.4644 | Q12: =AVERAGE(TableDE1!Q12:Q21) -> 6.6232348 | R12: 0 | S12: 0 | T12: 0
A13: =A12+1 -> 1873 | B13: =#REF! -> #REF! | C13: =#REF! -> #REF! | F13: =1000000*B13/R13 -> #REF! | G13: =1000000*C13/R13 -> #REF! | H13: =1000000*B13/S13 -> #REF! | I13: =1000000*C13/S13 -> #REF! | J13: =1000000*D13/R13 -> #DIV/0! | K13: =1000000*E13/R13 -> #DIV/0! | L13: =1000000*D13/S13 -> #DIV/0! | M13: =1000000*E13/S13 -> #DIV/0! | N13: =AVERAGE(TableDE1!N13:N22) -> 6.3531009 | O13: =AVERAGE(TableDE1!O13:O22) -> 0.95478818 | P13: =AVERAGE(TableDE1!P13:P22) -> 4524.2722 | Q13: =AVERAGE(TableDE1!Q13:Q22) -> 6.6546465 | R13: 0 | S13: 0 | T13: 0
A14: =A13+1 -> 1874 | B14: =#REF! -> #REF! | C14: =#REF! -> #REF! | F14: =1000000*B14/R14 -> #REF! | G14: =1000000*C14/R14 -> #REF! | H14: =1000000*B14/S14 -> #REF! | I14: =1000000*C14/S14 -> #REF! | J14: =1000000*D14/R14 -> #DIV/0! | K14: =1000000*E14/R14 -> #DIV/0! | L14: =1000000*D14/S14 -> #DIV/0! | M14: =1000000*E14/S14 -> #DIV/0! | N14: =AVERAGE(TableDE1!N14:N23) -> 6.3607618 | O14: =AVERAGE(TableDE1!O14:O23) -> 0.95422474 | P14: =AVERAGE(TableDE1!P14:P23) -> 4531.5132 | Q14: =AVERAGE(TableDE1!Q14:Q23) -> 6.666609 | R14: 0 | S14: 0 | T14: 0
A15: =A14+1 -> 1875 | B15: =#REF! -> #REF! | C15: =#REF! -> #REF! | F15: =1000000*B15/R15 -> #REF! | G15: =1000000*C15/R15 -> #REF! | H15: =1000000*B15/S15 -> #REF! | I15: =1000000*C15/S15 -> #REF! | J15: =1000000*D15/R15 -> #DIV/0! | K15: =1000000*E15/R15 -> #DIV/0! | L15: =1000000*D15/S15 -> #DIV/0! | M15: =1000000*E15/S15 -> #DIV/0! | N15: =AVERAGE(TableDE1!N15:N24) -> 6.3875289 | O15: =AVERAGE(TableDE1!O15:O24) -> 0.95340156 | P15: =AVERAGE(TableDE1!P15:P24) -> 4521.7391 | Q15: =AVERAGE(TableDE1!Q15:Q24) -> 6.7000831 | R15: 0 | S15: 0 | T15: 0
A16: =A15+1 -> 1876 | B16: =#REF! -> #REF! | C16: =#REF! -> #REF! | F16: =1000000*B16/R16 -> #REF! | G16: =1000000*C16/R16 -> #REF! | H16: =1000000*B16/S16 -> #REF! | I16: =1000000*C16/S16 -> #REF! | J16: =1000000*D16/R16 -> #DIV/0! | K16: =1000000*E16/R16 -> #DIV/0! | L16: =1000000*D16/S16 -> #DIV/0! | M16: =1000000*E16/S16 -> #DIV/0! | N16: =AVERAGE(TableDE1!N16:N25) -> 6.3875192 | O16: =AVERAGE(TableDE1!O16:O25) -> 0.95292093 | P16: =AVERAGE(TableDE1!P16:P25) -> 4538.652 | Q16: =AVERAGE(TableDE1!Q16:Q25) -> 6.7034239 | R16: 0 | S16: 0 | T16: 0
A17: =A16+1 -> 1877 | B17: =#REF! -> #REF! | C17: =#REF! -> #REF! | F17: =1000000*B17/R17 -> #REF! | G17: =1000000*C17/R17 -> #REF! | H17: =1000000*B17/S17 -> #REF! | I17: =1000000*C17/S17 -> #REF! | J17: =1000000*D17/R17 -> #DIV/0! | K17: =1000000*E17/R17 -> #DIV/0! | L17: =1000000*D17/S17 -> #DIV/0! | M17: =1000000*E17/S17 -> #DIV/0! | N17: =AVERAGE(TableDE1!N17:N26) -> 6.4020054 | O17: =AVERAGE(TableDE1!O17:O26) -> 0.95189054 | P17: =AVERAGE(TableDE1!P17:P26) -> 4568.5792 | Q17: =AVERAGE(TableDE1!Q17:Q26) -> 6.7259428 | R17: 0 | S17: 0 | T17: 0
A18: =A17+1 -> 1878 | B18: =#REF! -> #REF! | C18: =#REF! -> #REF! | F18: =1000000*B18/R18 -> #REF! | G18: =1000000*C18/R18 -> #REF! | H18: =1000000*B18/S18 -> #REF! | I18: =1000000*C18/S18 -> #REF! | J18: =1000000*D18/R18 -> #DIV/0! | K18: =1000000*E18/R18 -> #DIV/0! | L18: =1000000*D18/S18 -> #DIV/0! | M18: =1000000*E18/S18 -> #DIV/0! | N18: =AVERAGE(TableDE1!N18:N27) -> 6.4260041 | O18: =AVERAGE(TableDE1!O18:O27) -> 0.95130919 | P18: =AVERAGE(TableDE1!P18:P27) -> 4611.1004 | Q18: =AVERAGE(TableDE1!Q18:Q27) -> 6.75526 | R18: 0 | S18: 0 | T18: 0
A19: =A18+1 -> 1879 | B19: =#REF! -> #REF! | C19: =#REF! -> #REF! | F19: =1000000*B19/R19 -> #REF! | G19: =1000000*C19/R19 -> #REF! | H19: =1000000*B19/S19 -> #REF! | I19: =1000000*C19/S19 -> #REF! | J19: =1000000*D19/R19 -> #DIV/0! | K19: =1000000*E19/R19 -> #DIV/0! | L19: =1000000*D19/S19 -> #DIV/0! | M19: =1000000*E19/S19 -> #DIV/0! | N19: =AVERAGE(TableDE1!N19:N28) -> 6.4595382 | O19: =AVERAGE(TableDE1!O19:O28) -> 0.95054313 | P19: =AVERAGE(TableDE1!P19:P28) -> 4655.9889 | Q19: =AVERAGE(TableDE1!Q19:Q28) -> 6.7957666 | R19: 0 | S19: 0 | T19: 0
A20: 1880 | B20: =AVERAGE(TableDE1!B20:B29) -> 18.8293 | C20: =AVERAGE(TableDE1!C20:C29) -> 121.30621 | D20: =AVERAGE(TableDE1!D20:D29) -> 135.25176 | E20: =AVERAGE(TableDE1!E20:E29) -> 871.45998 | F20: =AVERAGE(TableDE1!F20:F29) -> 402.72702 | G20: =AVERAGE(TableDE1!G20:G29) -> 2594.4591 | H20: =AVERAGE(TableDE1!H20:H29) -> 694.32218 | I20: =AVERAGE(TableDE1!I20:I29) -> 4472.981 | ... T20: =AVERAGE(TableDE1!T20:T29) -> 20647
A21: =A20+1 -> 1881 | B21: =#REF! -> #REF! | C21: =#REF! -> #REF! | F21: =1000000*B21/R21 -> #REF! | G21: =1000000*C21/R21 -> #REF! | H21: =1000000*B21/S21 -> #REF! | I21: =1000000*C21/S21 -> #REF! | J21: =1000000*D21/R21 -> #DIV/0! | K21: =1000000*E21/R21 -> #DIV/0! | L21: =1000000*D21/S21 -> #DIV/0! | M21: =1000000*E21/S21 -> #DIV/0! | N21: =AVERAGE(TableDE1!N21:N30) -> 6.4196179 | O21: =AVERAGE(TableDE1!O21:O30) -> 0.94991445 | P21: =AVERAGE(TableDE1!P21:P30) -> 4850.8141 | Q21: =AVERAGE(TableDE1!Q21:Q30) -> 6.7581658 | R21: 0 | S21: 0 | T21: 0
A22: =A21+1 -> 1882 | B22: =#REF! -> #REF! | C22: =#REF! -> #REF! | F22: =1000000*B22/R22 -> #REF! | G22: =1000000*C22/R22 -> #REF! | H22: =1000000*B22/S22 -> #REF! | I22: =1000000*C22/S22 -> #REF! | J22: =1000000*D22/R22 -> #DIV/0! | K22: =1000000*E22/R22 -> #DIV/0! | L22: =1000000*D22/S22 -> #DIV/0! | M22: =1000000*E22/S22 -> #DIV/0! | N22: =AVERAGE(TableDE1!N22:N31) -> 6.4329161 | O22: =AVERAGE(TableDE1!O22:O31) -> 0.94967189 | P22: =AVERAGE(TableDE1!P22:P31) -> 4922.5939 | Q22: =AVERAGE(TableDE1!Q22:Q31) -> 6.7739536 | R22: 0 | S22: 0 | T22: 0
A23: =A22+1 -> 1883 | B23: =#REF! -> #REF! | C23: =#REF! -> #REF! | F23: =1000000*B23/R23 -> #REF! | G23: =1000000*C23/R23 -> #REF! | H23: =1000000*B23/S23 -> #REF! | I23: =1000000*C23/S23 -> #REF! | J23: =1000000*D23/R23 -> #DIV/0! | K23: =1000000*E23/R23 -> #DIV/0! | L23: =1000000*D23/S23 -> #DIV/0! | M23: =1000000*E23/S23 -> #DIV/0! | N23: =AVERAGE(TableDE1!N23:N32) -> 6.3867099 | O23: =AVERAGE(TableDE1!O23:O32) -> 0.94999668 | P23: =AVERAGE(TableDE1!P23:P32) -> 5023.8799 | Q23: =AVERAGE(TableDE1!Q23:Q32) -> 6.7230477 | R23: 0 | S23: 0 | T23: 0
A24: =A23+1 -> 1884 | B24: =#REF! -> #REF! | C24: =#REF! -> #REF! | F24: =1000000*B24/R24 -> #REF! | G24: =1000000*C24/R24 -> #REF! | H24: =1000000*B24/S24 -> #REF! | I24: =1000000*C24/S24 -> #REF! | J24: =1000000*D24/R24 -> #DIV/0! | K24: =1000000*E24/R24 -> #DIV/0! | L24: =1000000*D24/S24 -> #DIV/0! | M24: =1000000*E24/S24 -> #DIV/0! | N24: =AVERAGE(TableDE1!N24:N33) -> 6.3375044 | O24: =AVERAGE(TableDE1!O24:O33) -> 0.94998298 | P24: =AVERAGE(TableDE1!P24:P33) -> 5135.5615 | Q24: =AVERAGE(TableDE1!Q24:Q33) -> 6.671443 | R24: 0 | S24: 0 | T24: 0
A25: =A24+1 -> 1885 | B25: =#REF! -> #REF! | C25: =#REF! -> #REF! | F25: =1000000*B25/R25 -> #REF! | G25: =1000000*C25/R25 -> #REF! | H25: =1000000*B25/S25 -> #REF! | I25: =1000000*C25/S25 -> #REF! | J25: =1000000*D25/R25 -> #DIV/0! | K25: =1000000*E25/R25 -> #DIV/0! | L25: =1000000*D25/S25 -> #DIV/0! | M25: =1000000*E25/S25 -> #DIV/0! | N25: =AVERAGE(TableDE1!N25:N34) -> 6.3091588 | O25: =AVERAGE(TableDE1!O25:O34) -> 0.9494329 | P25: =AVERAGE(TableDE1!P25:P34) -> 5223.7953 | Q25: =AVERAGE(TableDE1!Q25:Q34) -> 6.6453619 | R25: 0 | S25: 0 | T25: 0
A26: =A25+1 -> 1886 | B26: =#REF! -> #REF! | C26: =#REF! -> #REF! | F26: =1000000*B26/R26 -> #REF! | G26: =1000000*C26/R26 -> #REF! | H26: =1000000*B26/S26 -> #REF! | I26: =1000000*C26/S26 -> #REF! | J26: =1000000*D26/R26 -> #DIV/0! | K26: =1000000*E26/R26 -> #DIV/0! | L26: =1000000*D26/S26 -> #DIV/0! | M26: =1000000*E26/S26 -> #DIV/0! | N26: =AVERAGE(TableDE1!N26:N35) -> 6.2526996 | O26: =AVERAGE(TableDE1!O26:O35) -> 0.94899289 | P26: =AVERAGE(TableDE1!P26:P35) -> 5317.499 | Q26: =AVERAGE(TableDE1!Q26:Q35) -> 6.5890428 | R26: 0 | S26: 0 | T26: 0
A27: =A26+1 -> 1887 | B27: =#REF! -> #REF! | C27: =#REF! -> #REF! | F27: =1000000*B27/R27 -> #REF! | G27: =1000000*C27/R27 -> #REF! | H27: =1000000*B27/S27 -> #REF! | I27: =1000000*C27/S27 -> #REF! | J27: =1000000*D27/R27 -> #DIV/0! | K27: =1000000*E27/R27 -> #DIV/0! | L27: =1000000*D27/S27 -> #DIV/0! | M27: =1000000*E27/S27 -> #DIV/0! | N27: =AVERAGE(TableDE1!N27:N36) -> 6.1671227 | O27: =AVERAGE(TableDE1!O27:O36) -> 0.94908377 | P27: =AVERAGE(TableDE1!P27:P36) -> 5430.6987 | Q27: =AVERAGE(TableDE1!Q27:Q36) -> 6.4981721 | R27: 0 | S27: 0 | T27: 0
A28: =A27+1 -> 1888 | B28: =#REF! -> #REF! | C28: =#REF! -> #REF! | F28: =1000000*B28/R28 -> #REF! | G28: =1000000*C28/R28 -> #REF! | H28: =1000000*B28/S28 -> #REF! | I28: =1000000*C28/S28 -> #REF! | J28: =1000000*D28/R28 -> #DIV/0! | K28: =1000000*E28/R28 -> #DIV/0! | L28: =1000000*D28/S28 -> #DIV/0! | M28: =1000000*E28/S28 -> #DIV/0! | N28: =AVERAGE(TableDE1!N28:N37) -> 6.0658991 | O28: =AVERAGE(TableDE1!O28:O37) -> 0.94890736 | P28: =AVERAGE(TableDE1!P28:P37) -> 5555.241 | Q28: =AVERAGE(TableDE1!Q28:Q37) -> 6.3928724 | R28: 0 | S28: 0 | T28: 0
A29: =A28+1 -> 1889 | B29: =#REF! -> #REF! | C29: =#REF! -> #REF! | F29: =1000000*B29/R29 -> #REF! | G29: =1000000*C29/R29 -> #REF! | H29: =1000000*B29/S29 -> #REF! | I29: =1000000*C29/S29 -> #REF! | J29: =1000000*D29/R29 -> #DIV/0! | K29: =1000000*E29/R29 -> #DIV/0! | L29: =1000000*D29/S29 -> #DIV/0! | M29: =1000000*E29/S29 -> #DIV/0! | N29: =AVERAGE(TableDE1!N29:N38) -> 5.9734288 | O29: =AVERAGE(TableDE1!O29:O38) -> 0.94883483 | P29: =AVERAGE(TableDE1!P29:P38) -> 5694.0898 | Q29: =AVERAGE(TableDE1!Q29:Q38) -> 6.2959186 | R29: 0 | S29: 0 | T29: 0
A30: 1890 | B30: =AVERAGE(TableDE1!B30:B39) -> 26.2092 | C30: =AVERAGE(TableDE1!C30:C39) -> 154.5943 | D30: =AVERAGE(TableDE1!D30:D39) -> 185.55855 | E30: =AVERAGE(TableDE1!E30:E39) -> 1094.0361 | F30: =AVERAGE(TableDE1!F30:F39) -> 503.29726 | G30: =AVERAGE(TableDE1!G30:G39) -> 2972.7955 | H30: =AVERAGE(TableDE1!H30:H39) -> 862.92048 | I30: =AVERAGE(TableDE1!I30:I39) -> 5097.5798 | ... T30: =AVERAGE(TableDE1!T30:T39) -> 23464
A31: =A30+1 -> 1891 | B31: =#REF! -> #REF! | C31: =#REF! -> #REF! | F31: =1000000*B31/R31 -> #REF! | G31: =1000000*C31/R31 -> #REF! | H31: =1000000*B31/S31 -> #REF! | I31: =1000000*C31/S31 -> #REF! | J31: =1000000*D31/R31 -> #DIV/0! | K31: =1000000*E31/R31 -> #DIV/0! | L31: =1000000*D31/S31 -> #DIV/0! | M31: =1000000*E31/S31 -> #DIV/0! | N31: =AVERAGE(TableDE1!N31:N40) -> 5.9150984 | O31: =AVERAGE(TableDE1!O31:O40) -> 0.9488329 | P31: =AVERAGE(TableDE1!P31:P40) -> 5871.0184 | Q31: =AVERAGE(TableDE1!Q31:Q40) -> 6.2343412 | R31: 0 | S31: 0 | T31: 0
A32: =A31+1 -> 1892 | B32: =#REF! -> #REF! | C32: =#REF! -> #REF! | F32: =1000000*B32/R32 -> #REF! | G32: =1000000*C32/R32 -> #REF! | H32: =1000000*B32/S32 -> #REF! | I32: =1000000*C32/S32 -> #REF! | J32: =1000000*D32/R32 -> #DIV/0! | K32: =1000000*E32/R32 -> #DIV/0! | L32: =1000000*D32/S32 -> #DIV/0! | M32: =1000000*E32/S32 -> #DIV/0! | N32: =AVERAGE(TableDE1!N32:N41) -> 5.9077794 | O32: =AVERAGE(TableDE1!O32:O41) -> 0.94863969 | P32: =AVERAGE(TableDE1!P32:P41) -> 5958.9239 | Q32: =AVERAGE(TableDE1!Q32:Q41) -> 6.2280064 | R32: 0 | S32: 0 | T32: 0
A33: =A32+1 -> 1893 | B33: =#REF! -> #REF! | C33: =#REF! -> #REF! | F33: =1000000*B33/R33 -> #REF! | G33: =1000000*C33/R33 -> #REF! | H33: =1000000*B33/S33 -> #REF! | I33: =1000000*C33/S33 -> #REF! | J33: =1000000*D33/R33 -> #DIV/0! | K33: =1000000*E33/R33 -> #DIV/0! | L33: =1000000*D33/S33 -> #DIV/0! | M33: =1000000*E33/S33 -> #DIV/0! | N33: =AVERAGE(TableDE1!N33:N42) -> 5.9384874 | O33: =AVERAGE(TableDE1!O33:O42) -> 0.94798776 | P33: =AVERAGE(TableDE1!P33:P42) -> 6020.6833 | Q33: =AVERAGE(TableDE1!Q33:Q42) -> 6.2648819 | R33: 0 | S33: 0 | T33: 0
A34: =A33+1 -> 1894 | B34: =#REF! -> #REF! | C34: =#REF! -> #REF! | F34: =1000000*B34/R34 -> #REF! | G34: =1000000*C34/R34 -> #REF! | H34: =1000000*B34/S34 -> #REF! | I34: =1000000*C34/S34 -> #REF! | J34: =1000000*D34/R34 -> #DIV/0! | K34: =1000000*E34/R34 -> #DIV/0! | L34: =1000000*D34/S34 -> #DIV/0! | M34: =1000000*E34/S34 -> #DIV/0! | N34: =AVERAGE(TableDE1!N34:N43) -> 5.9506844 | O34: =AVERAGE(TableDE1!O34:O43) -> 0.94757875 | P34: =AVERAGE(TableDE1!P34:P43) -> 6083.3375 | Q34: =AVERAGE(TableDE1!Q34:Q43) -> 6.2804358 | R34: 0 | S34: 0 | T34: 0
A35: =A34+1 -> 1895 | B35: =#REF! -> #REF! | C35: =#REF! -> #REF! | F35: =1000000*B35/R35 -> #REF! | G35: =1000000*C35/R35 -> #REF! | H35: =1000000*B35/S35 -> #REF! | I35: =1000000*C35/S35 -> #REF! | J35: =1000000*D35/R35 -> #DIV/0! | K35: =1000000*E35/R35 -> #DIV/0! | L35: =1000000*D35/S35 -> #DIV/0! | M35: =1000000*E35/S35 -> #DIV/0! | N35: =AVERAGE(TableDE1!N35:N44) -> 5.9497777 | O35: =AVERAGE(TableDE1!O35:O44) -> 0.94770547 | P35: =AVERAGE(TableDE1!P35:P44) -> 6175.2501 | Q35: =AVERAGE(TableDE1!Q35:Q44) -> 6.278636 | R35: 0 | S35: 0 | T35: 0
A36: =A35+1 -> 1896 | B36: =#REF! -> #REF! | C36: =#REF! -> #REF! | F36: =1000000*B36/R36 -> #REF! | G36: =1000000*C36/R36 -> #REF! | H36: =1000000*B36/S36 -> #REF! | I36: =1000000*C36/S36 -> #REF! | J36: =1000000*D36/R36 -> #DIV/0! | K36: =1000000*E36/R36 -> #DIV/0! | L36: =1000000*D36/S36 -> #DIV/0! | M36: =1000000*E36/S36 -> #DIV/0! | N36: =AVERAGE(TableDE1!N36:N45) -> 5.9533852 | O36: =AVERAGE(TableDE1!O36:O45) -> 0.94742429 | P36: =AVERAGE(TableDE1!P36:P45) -> 6270.6678 | Q36: =AVERAGE(TableDE1!Q36:Q45) -> 6.2842617 | R36: 0 | S36: 0 | T36: 0
A37: =A36+1 -> 1897 | B37: =#REF! -> #REF! | C37: =#REF! -> #REF! | F37: =1000000*B37/R37 -> #REF! | G37: =1000000*C37/R37 -> #REF! | H37: =1000000*B37/S37 -> #REF! | I37: =1000000*C37/S37 -> #REF! | J37: =1000000*D37/R37 -> #DIV/0! | K37: =1000000*E37/R37 -> #DIV/0! | L37: =1000000*D37/S37 -> #DIV/0! | M37: =1000000*E37/S37 -> #DIV/0! | N37: =AVERAGE(TableDE1!N37:N46) -> 5.9878823 | O37: =AVERAGE(TableDE1!O37:O46) -> 0.94717867 | P37: =AVERAGE(TableDE1!P37:P46) -> 6333.9067 | Q37: =AVERAGE(TableDE1!Q37:Q46) -> 6.3222713 | R37: 0 | S37: 0 | T37: 0
A38: =A37+1 -> 1898 | B38: =#REF! -> #REF! | C38: =#REF! -> #REF! | F38: =1000000*B38/R38 -> #REF! | G38: =1000000*C38/R38 -> #REF! | H38: =1000000*B38/S38 -> #REF! | I38: =1000000*C38/S38 -> #REF! | J38: =1000000*D38/R38 -> #DIV/0! | K38: =1000000*E38/R38 -> #DIV/0! | L38: =1000000*D38/S38 -> #DIV/0! | M38: =1000000*E38/S38 -> #DIV/0! | N38: =AVERAGE(TableDE1!N38:N47) -> 6.0232462 | O38: =AVERAGE(TableDE1!O38:O47) -> 0.94669361 | P38: =AVERAGE(TableDE1!P38:P47) -> 6413.5414 | Q38: =AVERAGE(TableDE1!Q38:Q47) -> 6.3627513 | R38: 0 | S38: 0 | T38: 0
A39: =A38+1 -> 1899 | B39: =#REF! -> #REF! | C39: =#REF! -> #REF! | F39: =1000000*B39/R39 -> #REF! | G39: =1000000*C39/R39 -> #REF! | H39: =1000000*B39/S39 -> #REF! | I39: =1000000*C39/S39 -> #REF! | J39: =1000000*D39/R39 -> #DIV/0! | K39: =1000000*E39/R39 -> #DIV/0! | L39: =1000000*D39/S39 -> #DIV/0! | M39: =1000000*E39/S39 -> #DIV/0! | N39: =AVERAGE(TableDE1!N39:N48) -> 6.0930333 | O39: =AVERAGE(TableDE1!O39:O48) -> 0.94607999 | P39: =AVERAGE(TableDE1!P39:P48) -> 6447.5503 | Q39: =AVERAGE(TableDE1!Q39:Q48) -> 6.4406106 | R39: 0 | S39: 0 | T39: 0
A40: 1900 | B40: =AVERAGE(TableDE1!B40:B49) -> 37.4087 | C40: =AVERAGE(TableDE1!C40:C49) -> 228.2181 | D40: =AVERAGE(TableDE1!D40:D49) -> 238.92006 | E40: =AVERAGE(TableDE1!E40:E49) -> 1458.2072 | F40: =AVERAGE(TableDE1!F40:F49) -> 622.63904 | G40: =AVERAGE(TableDE1!G40:G49) -> 3800.3762 | H40: =AVERAGE(TableDE1!H40:H49) -> 1077.5525 | I40: =AVERAGE(TableDE1!I40:I49) -> 6576.2982 | ... T40: =AVERAGE(TableDE1!T40:T49) -> 27045
A41: =A40+1 -> 1901 | B41: =#REF! -> #REF! | C41: =#REF! -> #REF! | E41: =C41*(TableDE15a!$B$149/AVERAGE(TableDE15a!$B$39:$B$48))/1.95583 -> #REF! | F41: =1000000*B41/R41 -> #REF! | G41: =1000000*C41/R41 -> #REF! | H41: =1000000*B41/S41 -> #REF! | I41: =1000000*C41/S41 -> #REF! | J41: =1000000*D41/R41 -> #REF! | K41: =1000000*E41/R41 -> #REF! | L41: =1000000*D41/S41 -> #REF! | M41: =1000000*E41/S41 -> #REF! | N41: =AVERAGE(TableDE1!N41:N50) -> 6.1061585 | O41: =AVERAGE(TableDE1!O41:O50) -> 0.94354143 | P41: =AVERAGE(TableDE1!P41:P50) -> 6575.5125 | Q41: =AVERAGE(TableDE1!Q41:Q50) -> 6.4718311 | R41: =AVERAGE(#REF!) -> #REF! | S41: =AVERAGE(#REF!) -> #REF! | T41: =AVERAGE(#REF!) -> #REF!
A42: =A41+1 -> 1902 | B42: =#REF! -> #REF! | C42: =#REF! -> #REF! | E42: =C42*(TableDE15a!$B$149/AVERAGE(TableDE15a!$B$39:$B$48))/1.95583 -> #REF! | F42: =1000000*B42/R42 -> #REF! | G42: =1000000*C42/R42 -> #REF! | H42: =1000000*B42/S42 -> #REF! | I42: =1000000*C42/S42 -> #REF! | J42: =1000000*D42/R42 -> #REF! | K42: =1000000*E42/R42 -> #REF! | L42: =1000000*D42/S42 -> #REF! | M42: =1000000*E42/S42 -> #REF! | N42: =AVERAGE(TableDE1!N42:N51) -> 6.0633699 | O42: =AVERAGE(TableDE1!O42:O51) -> 0.94197872 | P42: =AVERAGE(TableDE1!P42:P51) -> 6679.2307 | Q42: =AVERAGE(TableDE1!Q42:Q51) -> 6.437295 | R42: =AVERAGE(#REF!) -> #REF! | S42: =AVERAGE(#REF!) -> #REF! | T42: =AVERAGE(#REF!) -> #REF!
A43: =A42+1 -> 1903 | B43: =#REF! -> #REF! | C43: =#REF! -> #REF! | E43: =C43*(TableDE15a!$B$149/AVERAGE(TableDE15a!$B$39:$B$48))/1.95583 -> #REF! | F43: =1000000*B43/R43 -> #REF! | G43: =1000000*C43/R43 -> #REF! | H43: =1000000*B43/S43 -> #REF! | I43: =1000000*C43/S43 -> #REF! | J43: =1000000*D43/R43 -> #REF! | K43: =1000000*E43/R43 -> #REF! | L43: =1000000*D43/S43 -> #REF! | M43: =1000000*E43/S43 -> #REF! | N43: =AVERAGE(TableDE1!N43:N52) -> 6.0270973 | O43: =AVERAGE(TableDE1!O43:O52) -> 0.94046374 | P43: =AVERAGE(TableDE1!P43:P52) -> 6806.2025 | Q43: =AVERAGE(TableDE1!Q43:Q52) -> 6.4092153 | R43: =AVERAGE(#REF!) -> #REF! | S43: =AVERAGE(#REF!) -> #REF! | T43: =AVERAGE(#REF!) -> #REF!
A44: =A43+1 -> 1904 | B44: =#REF! -> #REF! | C44: =#REF! -> #REF! | E44: =C44*(TableDE15a!$B$149/AVERAGE(TableDE15a!$B$39:$B$48))/1.95583 -> #REF! | F44: =1000000*B44/R44 -> #REF! | G44: =1000000*C44/R44 -> #REF! | H44: =1000000*B44/S44 -> #REF! | I44: =1000000*C44/S44 -> #REF! | J44: =1000000*D44/R44 -> #REF! | K44: =1000000*E44/R44 -> #REF! | L44: =1000000*D44/S44 -> #REF! | M44: =1000000*E44/S44 -> #REF! | N44: =AVERAGE(TableDE1!N44:N53) -> 6.046459 | O44: =AVERAGE(TableDE1!O44:O53) -> 0.938446 | P44: =AVERAGE(TableDE1!P44:P53) -> 6892.5338 | Q44: =AVERAGE(TableDE1!Q44:Q53) -> 6.4439534 | R44: =AVERAGE(#REF!) -> #REF! | S44: =AVERAGE(#REF!) -> #REF! | T44: =AVERAGE(#REF!) -> #REF!
A45: =A44+1 -> 1905 | B45: =#REF! -> #REF! | C45: =#REF! -> #REF! | E45: =C45*(TableDE15a!$B$149/AVERAGE(TableDE15a!$B$39:$B$48))/1.95583 -> #REF! | F45: =1000000*B45/R45 -> #REF! | G45: =1000000*C45/R45 -> #REF! | H45: =1000000*B45/S45 -> #REF! | I45: =1000000*C45/S45 -> #REF! | J45: =1000000*D45/R45 -> #REF! | K45: =1000000*E45/R45 -> #REF! | L45: =1000000*D45/S45 -> #REF! | M45: =1000000*E45/S45 -> #REF! | N45: =AVERAGE(TableDE1!N45:N54) -> 6.0442447 | O45: =AVERAGE(TableDE1!O45:O54) -> 0.9372556 | P45: =AVERAGE(TableDE1!P45:P54) -> 6928.9475 | Q45: =AVERAGE(TableDE1!Q45:Q54) -> 6.459005 | R45: =AVERAGE(#REF!) -> #REF! | S45: =AVERAGE(#REF!) -> #REF! | T45: =AVERAGE(#REF!) -> #REF!
A46: =A45+1 -> 1906 | B46: =#REF! -> #REF! | C46: =#REF! -> #REF! | E46: =C46*(TableDE15a!$B$149/AVERAGE(TableDE15a!$B$39:$B$48))/1.95583 -> #REF! | F46: =1000000*B46/R46 -> #REF! | G46: =1000000*C46/R46 -> #REF! | H46: =1000000*B46/S46 -> #REF! | I46: =1000000*C46/S46 -> #REF! | J46: =1000000*D46/R46 -> #REF! | K46: =1000000*E46/R46 -> #REF! | L46: =1000000*D46/S46 -> #REF! | M46: =1000000*E46/S46 -> #REF! | N46: =AVERAGE(TableDE1!N46:N55) -> 6.0287681 | O46: =AVERAGE(TableDE1!O46:O55) -> 0.93598554 | P46: =AVERAGE(TableDE1!P46:P55) -> 6948.1992 | Q46: =AVERAGE(TableDE1!Q46:Q55) -> 6.4936263 | R46: =AVERAGE(#REF!) -> #REF! | S46: =AVERAGE(#REF!) -> #REF! | T46: =AVERAGE(#REF!) -> #REF!
A47: =A46+1 -> 1907 | B47: =#REF! -> #REF! | C47: =#REF! -> #REF! | E47: =C47*(TableDE15a!$B$149/AVERAGE(TableDE15a!$B$39:$B$48))/1.95583 -> #REF! | F47: =1000000*B47/R47 -> #REF! | G47: =1000000*C47/R47 -> #REF! | H47: =1000000*B47/S47 -> #REF! | I47: =1000000*C47/S47 -> #REF! | J47: =1000000*D47/R47 -> #REF! | K47: =1000000*E47/R47 -> #REF! | L47: =1000000*D47/S47 -> #REF! | M47: =1000000*E47/S47 -> #REF! | N47: =AVERAGE(TableDE1!N47:N56) -> 5.9662315 | O47: =AVERAGE(TableDE1!O47:O56) -> 0.93453124 | P47: =AVERAGE(TableDE1!P47:P56) -> 6990.6655 | Q47: =AVERAGE(TableDE1!Q47:Q56) -> 6.5141945 | R47: =AVERAGE(#REF!) -> #REF! | S47: =AVERAGE(#REF!) -> #REF! | T47: =AVERAGE(#REF!) -> #REF!
A48: =A47+1 -> 1908 | B48: =#REF! -> #REF! | C48: =#REF! -> #REF! | E48: =C48*(TableDE15a!$B$149/AVERAGE(TableDE15a!$B$39:$B$48))/1.95583 -> #REF! | F48: =1000000*B48/R48 -> #REF! | G48: =1000000*C48/R48 -> #REF! | H48: =1000000*B48/S48 -> #REF! | I48: =1000000*C48/S48 -> #REF! | J48: =1000000*D48/R48 -> #REF! | K48: =1000000*E48/R48 -> #REF! | L48: =1000000*D48/S48 -> #REF! | M48: =1000000*E48/S48 -> #REF! | N48: =AVERAGE(TableDE1!N48:N57) -> 5.8730048 | O48: =AVERAGE(TableDE1!O48:O57) -> 0.93283099 | P48: =AVERAGE(TableDE1!P48:P57) -> 6997.0167 | Q48: =AVERAGE(TableDE1!Q48:Q57) -> 6.54322 | R48: =AVERAGE(#REF!) -> #REF! | S48: =AVERAGE(#REF!) -> #REF! | T48: =AVERAGE(#REF!) -> #REF!
A49: =A48+1 -> 1909 | B49: =#REF! -> #REF! | C49: =#REF! -> #REF! | E49: =C49*(TableDE15a!$B$149/AVERAGE(TableDE15a!$B$39:$B$48))/1.95583 -> #REF! | F49: =1000000*B49/R49 -> #REF! | G49: =1000000*C49/R49 -> #REF! | H49: =1000000*B49/S49 -> #REF! | I49: =1000000*C49/S49 -> #REF! | J49: =1000000*D49/R49 -> #REF! | K49: =1000000*E49/R49 -> #REF! | L49: =1000000*D49/S49 -> #REF! | M49: =1000000*E49/S49 -> #REF! | N49: =AVERAGE(TableDE1!N49:N58) -> 5.7210522 | O49: =AVERAGE(TableDE1!O49:O58) -> 0.9308951 | P49: =AVERAGE(TableDE1!P49:P58) -> 7030.5093 | Q49: =AVERAGE(TableDE1!Q49:Q58) -> 6.5240903 | R49: =AVERAGE(#REF!) -> #REF! | S49: =AVERAGE(#REF!) -> #REF! | T49: =AVERAGE(#REF!) -> #REF!
A50: 1910 | B50: =AVERAGE(TableDE1!B50:B59) -> 74.451508 | C50: =AVERAGE(TableDE1!C50:C59) -> 394.02196 | D50: =AVERAGE(TableDE1!D50:D59) -> 256.23961 | E50: =AVERAGE(TableDE1!E50:E59) -> 1441.1949 | F50: =AVERAGE(TableDE1!F50:F59) -> 1127.4511 | G50: =AVERAGE(TableDE1!G50:G59) -> 5957.1897 | H50: =AVERAGE(TableDE1!H50:H59) -> 1926.0504 | I50: =AVERAGE(TableDE1!I50:I59) -> 10205.009 | ... N50: =AVERAGE(TableDE1!N50:N59) -> 5.5599133 | R50: =AVERAGE(TableDE1!R50:R59) -> 66351.5 | S50: =AVERAGE(TableDE1!S50:S59) -> 38488.173
A51: =A50+1 -> 1911 | C51: =#REF! -> #REF! | J51: =1000000*D51/R51 -> #REF! | K51: =1000000*E51/R51 -> #REF! | L51: =1000000*D51/S51 -> #REF! | M51: =1000000*E51/S51 -> #REF! | N51: =AVERAGE(TableDE1!N51:N60) -> 5.2855351 | R51: =AVERAGE(#REF!) -> #REF! | S51: =AVERAGE(#REF!) -> #REF! | T51: =AVERAGE(#REF!) -> #REF!
A52: =A51+1 -> 1912 | C52: =#REF! -> #REF! | J52: =1000000*D52/R52 -> #REF! | K52: =1000000*E52/R52 -> #REF! | L52: =1000000*D52/S52 -> #REF! | M52: =1000000*E52/S52 -> #REF! | N52: =AVERAGE(TableDE1!N52:N61) -> 4.9662598 | R52: =AVERAGE(#REF!) -> #REF! | S52: =AVERAGE(#REF!) -> #REF! | T52: =AVERAGE(#REF!) -> #REF!
A53: =A52+1 -> 1913 | C53: =#REF! -> #REF! | J53: =1000000*D53/R53 -> #REF! | K53: =1000000*E53/R53 -> #REF! | L53: =1000000*D53/S53 -> #REF! | M53: =1000000*E53/S53 -> #REF! | N53: =AVERAGE(TableDE1!N53:N62) -> 4.6050589 | R53: =AVERAGE(#REF!) -> #REF! | S53: =AVERAGE(#REF!) -> #REF! | T53: =AVERAGE(#REF!) -> #REF!
A54: =A53+1 -> 1914 | C54: =#REF! -> #REF! | J54: =1000000*D54/R54 -> #REF! | K54: =1000000*E54/R54 -> #REF! | L54: =1000000*D54/S54 -> #REF! | M54: =1000000*E54/S54 -> #REF! | N54: =AVERAGE(TableDE1!N54:N63) -> 4.2222398 | R54: =AVERAGE(#REF!) -> #REF! | S54: =AVERAGE(#REF!) -> #REF! | T54: =AVERAGE(#REF!) -> #REF!
A55: =A54+1 -> 1915 | C55: =#REF! -> #REF! | J55: =1000000*D55/R55 -> #REF! | K55: =1000000*E55/R55 -> #REF! | L55: =1000000*D55/S55 -> #REF! | M55: =1000000*E55/S55 -> #REF! | N55: =AVERAGE(TableDE1!N55:N64) -> 3.8469878 | R55: =AVERAGE(#REF!) -> #REF! | S55: =AVERAGE(#REF!) -> #REF! | T55: =AVERAGE(#REF!) -> #REF!
A56: =A55+1 -> 1916 | C56: =#REF! -> #REF! | J56: =1000000*D56/R56 -> #REF! | K56: =1000000*E56/R56 -> #REF! | L56: =1000000*D56/S56 -> #REF! | M56: =1000000*E56/S56 -> #REF! | N56: =AVERAGE(TableDE1!N56:N65) -> 3.5068753 | R56: =AVERAGE(#REF!) -> #REF! | S56: =AVERAGE(#REF!) -> #REF! | T56: =AVERAGE(#REF!) -> #REF!
A57: =A56+1 -> 1917 | C57: =#REF! -> #REF! | J57: =1000000*D57/R57 -> #REF! | K57: =1000000*E57/R57 -> #REF! | L57: =1000000*D57/S57 -> #REF! | M57: =1000000*E57/S57 -> #REF! | N57: =AVERAGE(TableDE1!N57:N66) -> 3.2358031 | R57: =AVERAGE(#REF!) -> #REF! | S57: =AVERAGE(#REF!) -> #REF! | T57: =AVERAGE(#REF!) -> #REF!
A58: =A57+1 -> 1918 | C58: =#REF! -> #REF! | J58: =1000000*D58/R58 -> #REF! | K58: =1000000*E58/R58 -> #REF! | L58: =1000000*D58/S58 -> #REF! | M58: =1000000*E58/S58 -> #REF! | N58: =AVERAGE(TableDE1!N58:N67) -> 3.0048164 | R58: =AVERAGE(#REF!) -> #REF! | S58: =AVERAGE(#REF!) -> #REF! | T58: =AVERAGE(#REF!) -> #REF!
A59: =A58+1 -> 1919 | C59: =#REF! -> #REF! | J59: =1000000*D59/R59 -> #REF! | K59: =1000000*E59/R59 -> #REF! | L59: =1000000*D59/S59 -> #REF! | M59: =1000000*E59/S59 -> #REF! | N59: =AVERAGE(TableDE1!N59:N68) -> 2.8109917 | R59: =AVERAGE(#REF!) -> #REF! | S59: =AVERAGE(#REF!) -> #REF! | T59: =AVERAGE(#REF!) -> #REF!
A60: 1920 | B60: =AVERAGE(TableDE1!B60:B69) -> 2.6454682e+11 | C60: =AVERAGE(TableDE1!C60:C69) -> 6.3580651e+11 | D60: =AVERAGE(TableDE1!D60:D69) -> 263.01308 | E60: =AVERAGE(TableDE1!E60:E69) -> 704.64674 | F60: =AVERAGE(TableDE1!F60:F69) -> 4.2863804e+12 | G60: =AVERAGE(TableDE1!G60:G69) -> 1.03018e+13 | H60: =AVERAGE(TableDE1!H60:H69) -> 6.8568263e+12 | I60: =AVERAGE(TableDE1!I60:I69) -> 1.6479558e+13 | ... N60: =AVERAGE(TableDE1!N60:N69) -> 2.6739964 | R60: =AVERAGE(TableDE1!R60:R69) -> 62409.1 | S60: =AVERAGE(TableDE1!S60:S69) -> 39633.569
A61: =A60+1 -> 1921 | J61: =1000000*D61/R61 -> #REF! | K61: =1000000*E61/R61 -> #REF! | L61: =1000000*D61/S61 -> #REF! | M61: =1000000*E61/S61 -> #REF! | N61: =AVERAGE(TableDE1!N61:N70) -> 2.6608272 | P61: =O61*L61 -> #REF! | Q61: =N61/O61 -> #DIV/0! | R61: =AVERAGE(#REF!) -> #REF! | S61: =AVERAGE(#REF!) -> #REF! | T61: =AVERAGE(#REF!) -> #REF!
A62: =A61+1 -> 1922 | J62: =1000000*D62/R62 -> #REF! | K62: =1000000*E62/R62 -> #REF! | L62: =1000000*D62/S62 -> #REF! | M62: =1000000*E62/S62 -> #REF! | N62: =AVERAGE(TableDE1!N62:N71) -> 2.7119664 | P62: =O62*L62 -> #REF! | Q62: =N62/O62 -> #DIV/0! | R62: =AVERAGE(#REF!) -> #REF! | S62: =AVERAGE(#REF!) -> #REF! | T62: =AVERAGE(#REF!) -> #REF!
A63: =A62+1 -> 1923 | J63: =1000000*D63/R63 -> #REF! | K63: =1000000*E63/R63 -> #REF! | L63: =1000000*D63/S63 -> #REF! | M63: =1000000*E63/S63 -> #REF! | N63: =AVERAGE(TableDE1!N63:N72) -> 2.823979 | P63: =O63*L63 -> #REF! | Q63: =N63/O63 -> #DIV/0! | R63: =AVERAGE(#REF!) -> #REF! | S63: =AVERAGE(#REF!) -> #REF! | T63: =AVERAGE(#REF!) -> #REF!
A64: =A63+1 -> 1924 | J64: =1000000*D64/R64 -> #REF! | K64: =1000000*E64/R64 -> #REF! | L64: =1000000*D64/S64 -> #REF! | M64: =1000000*E64/S64 -> #REF! | N64: =AVERAGE(TableDE1!N64:N73) -> 2.9149083 | P64: =O64*L64 -> #REF! | Q64: =N64/O64 -> #DIV/0! | R64: =AVERAGE(#REF!) -> #REF! | S64: =AVERAGE(#REF!) -> #REF! | T64: =AVERAGE(#REF!) -> #REF!
A65: =A64+1 -> 1925 | J65: =1000000*D65/R65 -> #REF! | K65: =1000000*E65/R65 -> #REF! | L65: =1000000*D65/S65 -> #REF! | M65: =1000000*E65/S65 -> #REF! | N65: =AVERAGE(TableDE1!N65:N74) -> 2.9984747 | P65: =O65*L65 -> #REF! | Q65: =N65/O65 -> #DIV/0! | R65: =AVERAGE(#REF!) -> #REF! | S65: =AVERAGE(#REF!) -> #REF! | T65: =AVERAGE(#REF!) -> #REF!
A66: =A65+1 -> 1926 | J66: =1000000*D66/R66 -> #REF! | K66: =1000000*E66/R66 -> #REF! | L66: =1000000*D66/S66 -> #REF! | M66: =1000000*E66/S66 -> #REF! | N66: =AVERAGE(TableDE1!N66:N75) -> 3.0588642 | P66: =O66*L66 -> #REF! | Q66: =N66/O66 -> #DIV/0! | R66: =AVERAGE(#REF!) -> #REF! | S66: =AVERAGE(#REF!) -> #REF! | T66: =AVERAGE(#REF!) -> #REF!
A67: =A66+1 -> 1927 | J67: =1000000*D67/R67 -> #REF! | K67: =1000000*E67/R67 -> #REF! | L67: =1000000*D67/S67 -> #REF! | M67: =1000000*E67/S67 -> #REF! | N67: =AVERAGE(TableDE1!N67:N76) -> 3.0688869 | P67: =O67*L67 -> #REF! | Q67: =N67/O67 -> #DIV/0! | R67: =AVERAGE(#REF!) -> #REF! | S67: =AVERAGE(#REF!) -> #REF! | T67: =AVERAGE(#REF!) -> #REF!
A68: =A67+1 -> 1928 | J68: =1000000*D68/R68 -> #REF! | K68: =1000000*E68/R68 -> #REF! | L68: =1000000*D68/S68 -> #REF! | M68: =1000000*E68/S68 -> #REF! | N68: =AVERAGE(TableDE1!N68:N77) -> 3.0611913 | P68: =O68*L68 -> #REF! | Q68: =N68/O68 -> #DIV/0! | R68: =AVERAGE(#REF!) -> #REF! | S68: =AVERAGE(#REF!) -> #REF! | T68: =AVERAGE(#REF!) -> #REF!
A69: =A68+1 -> 1929 | J69: =1000000*D69/R69 -> #REF! | K69: =1000000*E69/R69 -> #REF! | L69: =1000000*D69/S69 -> #REF! | M69: =1000000*E69/S69 -> #REF! | N69: =AVERAGE(TableDE1!N69:N78) -> 3.0460354 | P69: =O69*L69 -> #REF! | Q69: =N69/O69 -> #DIV/0! | R69: =AVERAGE(#REF!) -> #REF! | S69: =AVERAGE(#REF!) -> #REF! | T69: =AVERAGE(#REF!) -> #REF!
A70: 1930 | B70: =AVERAGE(TableDE1!B70:B79) -> 71.441816 | C70: =AVERAGE(TableDE1!C70:C79) -> 212.26466 | D70: =AVERAGE(TableDE1!D70:D79) -> 324.19649 | E70: =AVERAGE(TableDE1!E70:E79) -> 957.93766 | F70: =AVERAGE(TableDE1!F70:F79) -> 1026.6562 | G70: =AVERAGE(TableDE1!G70:G79) -> 3066.1548 | H70: =AVERAGE(TableDE1!H70:H79) -> 1493.9621 | I70: =AVERAGE(TableDE1!I70:I79) -> 4464.649 | ... O70: =AVERAGE(TableDE1!O70:O79) -> 0.86267761 | P70: =O70*L70 -> 5811.6827 | Q70: =N70/O70 -> 3.5042653 | R70: =AVERAGE(TableDE1!R70:R79) -> 68866.3 | S70: =AVERAGE(TableDE1!S70:S79) -> 47348.372
A71: =A70+1 -> 1931 | J71: =1000000*D71/R71 -> #REF! | K71: =1000000*E71/R71 -> #REF! | L71: =1000000*D71/S71 -> #REF! | M71: =1000000*E71/S71 -> #REF! | N71: =AVERAGE(TableDE1!N71:N80) -> 2.989778 | O71: =AVERAGE(TableDE1!O71:O80) -> 0.86002906 | P71: =O71*L71 -> #REF! | Q71: =N71/O71 -> 3.4763685 | R71: =AVERAGE(#REF!) -> #REF! | S71: =AVERAGE(#REF!) -> #REF! | T71: =AVERAGE(#REF!) -> #REF!
A72: =A71+1 -> 1932 | J72: =1000000*D72/R72 -> #REF! | K72: =1000000*E72/R72 -> #REF! | L72: =1000000*D72/S72 -> #REF! | M72: =1000000*E72/S72 -> #REF! | N72: =AVERAGE(TableDE1!N72:N81) -> 2.9163437 | O72: =AVERAGE(TableDE1!O72:O81) -> 0.85479842 | P72: =O72*L72 -> #REF! | Q72: =N72/O72 -> 3.4117327 | R72: =AVERAGE(#REF!) -> #REF! | S72: =AVERAGE(#REF!) -> #REF! | T72: =AVERAGE(#REF!) -> #REF!
A73: =A72+1 -> 1933 | J73: =1000000*D73/R73 -> #REF! | K73: =1000000*E73/R73 -> #REF! | L73: =1000000*D73/S73 -> #REF! | M73: =1000000*E73/S73 -> #REF! | N73: =AVERAGE(TableDE1!N73:N82) -> 2.8373816 | O73: =AVERAGE(TableDE1!O73:O82) -> 0.84642557 | P73: =O73*L73 -> #REF! | Q73: =N73/O73 -> 3.3521926 | R73: =AVERAGE(#REF!) -> #REF! | S73: =AVERAGE(#REF!) -> #REF! | T73: =AVERAGE(#REF!) -> #REF!
A74: =A73+1 -> 1934 | J74: =1000000*D74/R74 -> #REF! | K74: =1000000*E74/R74 -> #REF! | L74: =1000000*D74/S74 -> #REF! | M74: =1000000*E74/S74 -> #REF! | N74: =AVERAGE(TableDE1!N74:N83) -> 2.7848233 | O74: =AVERAGE(TableDE1!O74:O83) -> 0.8376069 | P74: =O74*L74 -> #REF! | Q74: =N74/O74 -> 3.3247378 | R74: =AVERAGE(#REF!) -> #REF! | S74: =AVERAGE(#REF!) -> #REF! | T74: =AVERAGE(#REF!) -> #REF!
A75: =A74+1 -> 1935 | J75: =1000000*D75/R75 -> #REF! | K75: =1000000*E75/R75 -> #REF! | L75: =1000000*D75/S75 -> #REF! | M75: =1000000*E75/S75 -> #REF! | N75: =AVERAGE(TableDE1!N75:N84) -> 2.7761532 | O75: =AVERAGE(TableDE1!O75:O84) -> 0.8292337 | P75: =O75*L75 -> #REF! | Q75: =N75/O75 -> 3.3478538 | R75: =AVERAGE(#REF!) -> #REF! | S75: =AVERAGE(#REF!) -> #REF! | T75: =AVERAGE(#REF!) -> #REF!
A76: =A75+1 -> 1936 | J76: =1000000*D76/R76 -> #REF! | K76: =1000000*E76/R76 -> #REF! | L76: =1000000*D76/S76 -> #REF! | M76: =1000000*E76/S76 -> #REF! | N76: =AVERAGE(TableDE1!N76:N85) -> 2.7461423 | O76: =AVERAGE(TableDE1!O76:O85) -> 0.81960611 | P76: =O76*L76 -> #REF! | Q76: =N76/O76 -> 3.3505634 | R76: =AVERAGE(#REF!) -> #REF! | S76: =AVERAGE(#REF!) -> #REF! | T76: =AVERAGE(#REF!) -> #REF!
A77: =A76+1 -> 1937 | J77: =1000000*D77/R77 -> #REF! | K77: =1000000*E77/R77 -> #REF! | L77: =1000000*D77/S77 -> #REF! | M77: =1000000*E77/S77 -> #REF! | N77: =AVERAGE(TableDE1!N77:N86) -> 2.7040685 | O77: =AVERAGE(TableDE1!O77:O86) -> 0.81030879 | P77: =O77*L77 -> #REF! | Q77: =N77/O77 -> 3.3370839 | R77: =AVERAGE(#REF!) -> #REF! | S77: =AVERAGE(#REF!) -> #REF! | T77: =AVERAGE(#REF!) -> #REF!
A78: =A77+1 -> 1938 | J78: =1000000*D78/R78 -> #REF! | K78: =1000000*E78/R78 -> #REF! | L78: =1000000*D78/S78 -> #REF! | M78: =1000000*E78/S78 -> #REF! | N78: =AVERAGE(TableDE1!N78:N87) -> 2.6514655 | O78: =AVERAGE(TableDE1!O78:O87) -> 0.80421324 | P78: =O78*L78 -> #REF! | Q78: =N78/O78 -> 3.2969683 | R78: =AVERAGE(#REF!) -> #REF! | S78: =AVERAGE(#REF!) -> #REF! | T78: =AVERAGE(#REF!) -> #REF!
A79: =A78+1 -> 1939 | J79: =1000000*D79/R79 -> #REF! | K79: =1000000*E79/R79 -> #REF! | L79: =1000000*D79/S79 -> #REF! | M79: =1000000*E79/S79 -> #REF! | N79: =AVERAGE(TableDE1!N79:N88) -> 2.5854867 | O79: =AVERAGE(TableDE1!O79:O88) -> 0.80421324 | P79: =O79*L79 -> #REF! | Q79: =N79/O79 -> 3.2149268 | R79: =AVERAGE(#REF!) -> #REF! | S79: =AVERAGE(#REF!) -> #REF! | T79: =AVERAGE(#REF!) -> #REF!
A80: 1940 | B80: =AVERAGE(TableDE1!B80:B89) -> 112.08349 | C80: =AVERAGE(TableDE1!C80:C89) -> 288.3179 | D80: =AVERAGE(TableDE1!D80:D89) -> 474.75358 | E80: =AVERAGE(TableDE1!E80:E89) -> 1250.2895 | F80: =AVERAGE(TableDE1!F80:F89) -> 1308.1464 | G80: =AVERAGE(TableDE1!G80:G89) -> 3288.1169 | H80: =AVERAGE(TableDE1!H80:H89) -> 1889.393 | I80: =AVERAGE(TableDE1!I80:I89) -> 4749.4147 | ... N80: =AVERAGE(TableDE1!N80:N89) -> 2.4869449 | R80: =AVERAGE(TableDE1!R80:R89) -> 82485.942 | S80: =AVERAGE(TableDE1!S80:S89) -> 57108.183
A81: =A80+1 -> 1941 | N81: =AVERAGE(TableDE1!N81:N90) -> 2.3807925 | R81: =AVERAGE(TableDE1!R90:R90) -> 50747.57 | S81: =AVERAGE(TableDE1!S90:S90) -> 35269.561 | T81: =AVERAGE(TableDE1!T90:T90) -> 20726.759
A82: =A81+1 -> 1942 | N82: =AVERAGE(TableDE1!N82:N91) -> 2.2902033 | R82: =AVERAGE(TableDE1!R90:R91) -> 50972.01 | S82: =AVERAGE(TableDE1!S90:S91) -> 35479.303 | T82: =AVERAGE(TableDE1!T90:T91) -> 21002.657
A83: =A82+1 -> 1943 | N83: =AVERAGE(TableDE1!N83:N92) -> 2.1898487 | R83: =AVERAGE(TableDE1!R90:R92) -> 51197.773 | S83: =AVERAGE(TableDE1!S90:S92) -> 35690.599 | T83: =AVERAGE(TableDE1!T90:T92) -> 21246.781
A84: =A83+1 -> 1944 | N84: =AVERAGE(TableDE1!N84:N93) -> 2.0792422 | R84: =AVERAGE(TableDE1!R90:R93) -> 51438.03 | S84: =AVERAGE(TableDE1!S90:S93) -> 35912.691 | T84: =AVERAGE(TableDE1!T90:T93) -> 21515.001
A85: =A84+1 -> 1945 | N85: =AVERAGE(TableDE1!N85:N94) -> 1.9532478 | R85: =AVERAGE(TableDE1!R90:R94) -> 51690.134 | S85: =AVERAGE(TableDE1!S90:S94) -> 36143.785 | T85: =AVERAGE(TableDE1!T90:T94) -> 21802.39
A86: =A85+1 -> 1946 | N86: =AVERAGE(TableDE1!N86:N95) -> 1.852961 | R86: =AVERAGE(TableDE1!R90:R95) -> 51946.862 | S86: =AVERAGE(TableDE1!S90:S95) -> 36378.84 | T86: =AVERAGE(TableDE1!T90:T95) -> 22140.316
A87: =A86+1 -> 1947 | N87: =AVERAGE(TableDE1!N87:N96) -> 1.7719757 | R87: =AVERAGE(TableDE1!R90:R96) -> 52158.546 | S87: =AVERAGE(TableDE1!S90:S96) -> 36582.736 | T87: =AVERAGE(TableDE1!T90:T96) -> 22480.643
A88: =A87+1 -> 1948 | N88: =AVERAGE(TableDE1!N88:N97) -> 1.7113414 | R88: =AVERAGE(TableDE1!R90:R97) -> 52351.478 | S88: =AVERAGE(TableDE1!S90:S97) -> 36773.933 | T88: =AVERAGE(TableDE1!T90:T97) -> 22805.922
A89: =A88+1 -> 1949 | N89: =AVERAGE(TableDE1!N89:N98) -> 1.6736983 | R89: =AVERAGE(TableDE1!R90:R98) -> 52578.18 | S89: =AVERAGE(TableDE1!S90:S98) -> 36989.727 | T89: =AVERAGE(TableDE1!T90:T98) -> 23083.864
A90: 1950 | B90: =AVERAGE(TableDE1!B90:B99) -> 90.401834 | C90: =AVERAGE(TableDE1!C90:C99) -> 148.24824 | D90: =AVERAGE(TableDE1!D90:D99) -> 417.57289 | E90: =AVERAGE(TableDE1!E90:E99) -> 686.10636 | F90: =AVERAGE(TableDE1!F90:F99) -> 1700.8926 | G90: =AVERAGE(TableDE1!G90:G99) -> 2791.1369 | H90: =AVERAGE(TableDE1!H90:H99) -> 2409.4358 | I90: =AVERAGE(TableDE1!I90:I99) -> 3954.8367 | ... T90: =AVERAGE(TableDE1!T90:T99) -> 23335.45
A91: =A90+1 -> 1951 | N91: =AVERAGE(TableDE1!N91:N100) -> 1.6477296 | R91: =AVERAGE(TableDE1!R91:R100) -> 53305.19 | S91: =AVERAGE(TableDE1!S91:S100) -> 37670.914 | T91: =AVERAGE(TableDE1!T91:T100) -> 23868.076
A92: =A91+1 -> 1952 | N92: =AVERAGE(TableDE1!N92:N101) -> 1.6602239 | R92: =AVERAGE(TableDE1!R92:R101) -> 53812.917 | S92: =AVERAGE(TableDE1!S92:S101) -> 38123.892 | T92: =AVERAGE(TableDE1!T92:T101) -> 24382.303
A93: =A92+1 -> 1953 | N93: =AVERAGE(TableDE1!N93:N102) -> 1.6833971 | R93: =AVERAGE(TableDE1!R93:R102) -> 54339.807 | S93: =AVERAGE(TableDE1!S93:S102) -> 38573.118 | T93: =AVERAGE(TableDE1!T93:T102) -> 24860.601
A94: =A93+1 -> 1954 | N94: =AVERAGE(TableDE1!N94:N103) -> 1.7185141 | R94: =AVERAGE(TableDE1!R94:R103) -> 54879.515 | S94: =AVERAGE(TableDE1!S94:S103) -> 39013.775 | T94: =AVERAGE(TableDE1!T94:T103) -> 25287.174
A95: =A94+1 -> 1955 | N95: =AVERAGE(TableDE1!N95:N104) -> 1.7542182 | R95: =AVERAGE(TableDE1!R95:R104) -> 55432.258 | S95: =AVERAGE(TableDE1!S95:S104) -> 39445.662 | T95: =AVERAGE(TableDE1!T95:T104) -> 25653.329
A96: =A95+1 -> 1956 | N96: =AVERAGE(TableDE1!N96:N105) -> 1.8020429 | R96: =AVERAGE(TableDE1!R96:R105) -> 56003.41 | S96: =AVERAGE(TableDE1!S96:S105) -> 39872.186 | T96: =AVERAGE(TableDE1!T96:T105) -> 25947.183
A97: =A96+1 -> 1957 | N97: =AVERAGE(TableDE1!N97:N106) -> 1.8635767 | R97: =AVERAGE(TableDE1!R97:R106) -> 56615.021 | S97: =AVERAGE(TableDE1!S97:S106) -> 40308.535 | T97: =AVERAGE(TableDE1!T97:T106) -> 26163.749
A98: =A97+1 -> 1958 | N98: =AVERAGE(TableDE1!N98:N107) -> 1.9459591 | R98: =AVERAGE(TableDE1!R98:R107) -> 57231.892 | S98: =AVERAGE(TableDE1!S98:S107) -> 40729.564 | T98: =AVERAGE(TableDE1!T98:T107) -> 26237.282
A99: =A98+1 -> 1959 | N99: =AVERAGE(TableDE1!N99:N108) -> 2.0249823 | R99: =AVERAGE(TableDE1!R99:R108) -> 57813.287 | S99: =AVERAGE(TableDE1!S99:S108) -> 41106.074 | T99: =AVERAGE(TableDE1!T99:T108) -> 26290.831
A100: 1960 | B100: =AVERAGE(TableDE1!B100:B109) -> 209.10227 | C100: =AVERAGE(TableDE1!C100:C109) -> 446.01463 | D100: =AVERAGE(TableDE1!D100:D109) -> 725.89372 | E100: =AVERAGE(TableDE1!E100:E109) -> 1535.168 | F100: =AVERAGE(TableDE1!F100:F109) -> 3563.5624 | G100: =AVERAGE(TableDE1!G100:G109) -> 7580.9317 | H100: =AVERAGE(TableDE1!H100:H109) -> 5022.6166 | I100: =AVERAGE(TableDE1!I100:I109) -> 10690.179 | ... T100: =AVERAGE(TableDE1!T100:T109) -> 26355.971
A101: =A100+1 -> 1961 | N101: =AVERAGE(TableDE1!N101:N110) -> 2.1460792 | R101: =AVERAGE(TableDE1!R101:R110) -> 58946.371 | S101: =AVERAGE(TableDE1!S101:S110) -> 41778.312 | T101: =AVERAGE(TableDE1!T101:T110) -> 26409.569
A102: =A101+1 -> 1962 | N102: =AVERAGE(TableDE1!N102:N111) -> 2.1809836 | R102: =AVERAGE(TableDE1!R102:R111) -> 59444.182 | S102: =AVERAGE(TableDE1!S102:S111) -> 42082.646 | T102: =AVERAGE(TableDE1!T102:T111) -> 26438.487
...

Sheet TableDE3
B1: Back to index
A3: Table DE.3: Economic growth, population growth and price deflators in Germany (changing boundaries), 1870-2010
B5: [1] | C5: [2] | D5: [3] | E5: [4] | F5: [5] | G5: [6] | H5: [7] | I5: [8] | J5: [9] | K5: [10] | L5: [11]
B6: Boundaries: 1870-1944: German Empire (including Alsace-Lorraine from 1871 on, excluding territories lost in the wake of World War 1 from 1919-1923 on, including Saarland from 1935 on, and including annexed territories in 1938-1944); 1945-1949: territory occupied by the Allied powers and USSR; 1950-1990: West Germany (including Saarland & West Berlin); 1991-onwards: reunified Germany.
B7: Real growth rate of national income (GDP deflator) | C7: Real growth rate of private wealth (GDP deflator) | D7: Real growth rate of per-capita national income (GDP deflator) | E7: Real growth rate of per-capita national income (CPI) | F7: Real growth rate of per-employed national income (GDP deflator) | G7: Population growth rate | H7: Adult population growth rate (20-yr+) | I7: Employed population growth rate | J7: GDP price inflation | K7: Consumer price inflation | L7: Personal consumption expenditure inflation
A8: 1870-2010 | B8: =(((1+B11)^40)*((1+B14)^100))^(1/140)-1 -> 0.022530911 | C8: =(((1+C11)^40)*((1+C14)^100))^(1/140)-1 -> 0.018623324 | D8: =(1+B8)/(1+G8)-1 -> 0.017180119 | E8: =(1+D8)*(1+J8)/(1+K8)-1 -> 0.017261465 | F8: =(1+D8)*(1+G8)/(1+I8)-1 -> 0.016220097 | G8: =(((1+G11)^40)*((1+G14)^100))^(1/140)-1 -> 0.0052604175 | H8: =(((1+H11)^40)*((1+H14)^100))^(1/140)-1 -> 0.0078972157 | I8: =(((1+I11)^40)*((1+I14)^100))^(1/140)-1 -> 0.0062100854 | J8: =(((1+J11)^40)*((1+J14)^100))^(1/140)-1 -> 0.019236402 | K8: =(((1+K11)^40)*((1+K14)^100))^(1/140)-1 -> 0.019154897
A11: 1870-1910 | B11: =(TableDE1!D50/TableDE1!D10)^(1/40)-1 -> 0.026119956 | C11: =(TableDE1!E50/TableDE1!E10)^(1/40)-1 -> 0.022379243 | D11: =(1+B11)/(1+G11)-1 -> 0.013417583 | E11: =(1+D11)*(1+J11)/(1+K11)-1 -> 0.0101636 | F11: =(1+D11)*(1+G11)/(1+I11)-1 -> 0.012213933 | G11: =(TableDE1!R50/TableDE1!R10)^(1/40)-1 -> 0.012534195 | H11: =(TableDE1!S50/TableDE1!S10)^(1/40)-1 -> 0.012668325 | I11: =(TableDE1!T50/TableDE1!T10)^(1/40)-1 -> 0.013738226 | J11: =(TableDE15a!C49/TableDE15a!C9)^(1/40)-1 -> 0.0058343466 | K11: =(TableDE15a!B49/TableDE15a!B9)^(1/40)-1 -> 0.0090743844
A14: 1910-2010 | B14: =(((1+B17)^40)*((1+B20)^60))^(1/100)-1 -> 0.02109881 | C14: =(((1+C17)^40)*((1+C20)^60))^(1/100)-1 -> 0.017124823 | D14: =(1+B14)/(1+G14)-1 -> 0.018689041 | E14: =(1+D14)*(1+J14)/(1+K14)-1 -> 0.020114557 | F14: =(1+D14)*(1+G14)/(1+I14)-1 -> 0.017826999 | G14: =(((1+G17)^40)*((1+G20)^60))^(1/100)-1 -> 0.0023655585 | H14: =(((1+H17)^40)*((1+H20)^60))^(1/100)-1 -> 0.005995072 | I14: =(((1+I17)^40)*((1+I20)^60))^(1/100)-1 -> 0.0032145059 | J14: =(TableDE15a!C149/TableDE15a!C49)^(1/100)-1 -> 0.024647092 | K14: =(TableDE15a!B149/TableDE15a!B49)^(1/100)-1 -> 0.023215243
A17: 1910-1950 | B17: =(TableDE1!D90/TableDE1!D50)^(1/40)-1 -> 0.0012573723 | C17: =(TableDE1!E90/TableDE1!E50)^(1/40)-1 -> -0.028607721 | D17: =(1+B17)/(1+G17)-1 -> 0.0073045109 | E17: =(1+D17)*(1+J17)/(1+K17)-1 -> 0.0078224941 | F17: =(1+D17)*(1+G17)/(1+I17)-1 -> 0.010063107 | G17: =(TableDE1!R90/TableDE1!R50)^(1/40)-1 -> -0.0060032875 | H17: =(TableDE1!S90/TableDE1!S50)^(1/40)-1 -> -0.00098270663 | I17: =(TableDE1!T90/TableDE1!T50)^(1/40)-1 -> -0.0087180046 | J17: =(TableDE15a!C89/TableDE15a!C49)^(1/40)-1 -> 0.018367226 | K17: =(TableDE15a!B89/TableDE15a!B49)^(1/40)-1 -> 0.017843823
A20: 1950-2010 | B20: =(TableDE1!D150/TableDE1!D90)^(1/60)-1 -> 0.034544395 | C20: =(TableDE1!E150/TableDE1!E90)^(1/60)-1 -> 0.048803169 | D20: =(1+B20)/(1+G20)-1 -> 0.026350121 | E20: =(1+D20)*(1+J20)/(1+K20)-1 -> 0.028392442 | F20: =(1+D20)*(1+G20)/(1+I20)-1 -> 0.023036053 | G20: =(TableDE1!R150/TableDE1!R90)^(1/60)-1 -> 0.0079838975 | H20: =(TableDE1!S150/TableDE1!S90)^(1/60)-1 -> 0.01067398 | I20: =(TableDE1!T150/TableDE1!T90)^(1/60)-1 -> 0.011249205 | J20: =(TableDE15a!C149/TableDE15a!C89)^(1/60)-1 -> 0.028855168 | K20: =(TableDE15a!B149/TableDE15a!B89)^(1/60)-1 -> 0.026811928 | L20: =(TableDE15a!D149/TableDE15a!D89)^(1/60)-1 -> 0.025784365
A23: 1950-1980 | B23: =(TableDE1!D120/TableDE1!D90)^(1/30)-1 -> 0.049389004 | C23: =(TableDE1!E120/TableDE1!E90)^(1/30)-1 -> 0.061145219 | D23: =(1+B23)/(1+G23)-1 -> 0.042660853 | E23: =(1+D23)*(1+J23)/(1+K23)-1 -> 0.05033955 | F23: =(1+D23)*(1+G23)/(1+I23)-1 -> 0.03964557 | G23: =(TableDE1!R120/TableDE1!R90)^(1/30)-1 -> 0.0064528662 | H23: =(TableDE1!S120/TableDE1!S90)^(1/30)-1 -> 0.0083776424 | I23: =(TableDE1!T120/TableDE1!T90)^(1/30)-1 -> 0.0093718805 | J23: =(TableDE15a!C119/TableDE15a!C89)^(1/30)-1 -> 0.039337231 | K23: =(TableDE15a!B119/TableDE15a!B89)^(1/30)-1 -> 0.031738968 | L23: =(TableDE15a!D119/TableDE15a!D89)^(1/30)-1 -> 0.032030226
A26: 1980-2010 | B26: =(TableDE1!D150/TableDE1!D120)^(1/30)-1 -> 0.019909778 | C26: =(TableDE1!E150/TableDE1!E120)^(1/30)-1 -> 0.036604668 | D26: =(1+B26)/(1+G26)-1 -> 0.010294544 | E26: =(1+D26)*(1+J26)/(1+K26)-1 -> 0.0069039252 | F26: =(1+D26)*(1+G26)/(1+I26)-1 -> 0.0066918918 | G26: =(TableDE1!R150/TableDE1!R120)^(1/30)-1 -> 0.0095172577 | H26: =(TableDE1!S150/TableDE1!S120)^(1/30)-1 -> 0.012975546 | I26: =(TableDE1!T150/TableDE1!T120)^(1/30)-1 -> 0.013130021 | J26: =(TableDE15a!C149/TableDE15a!C119)^(1/30)-1 -> 0.01847882 | K26: =(TableDE15a!B149/TableDE15a!B119)^(1/30)-1 -> 0.021908416 | L26: =(TableDE15a!D149/TableDE15a!D119)^(1/30)-1 -> 0.019576305
A29: 1950-1970 | B29: =(TableDE1!D110/TableDE1!D90)^(1/20)-1 -> 0.061011767 | C29: =(TableDE1!E110/TableDE1!E90)^(1/20)-1 -> 0.072596948 | D29: =(1+B29)/(1+G29)-1 -> 0.05121042 | E29: =(1+D29)*(1+J29)/(1+K29)-1 -> 0.062702641 | F29: =(1+D29)*(1+G29)/(1+I29)-1 -> 0.047880286 | G29: =(TableDE1!R110/TableDE1!R90)^(1/20)-1 -> 0.0093238681 | H29: =(TableDE1!S110/TableDE1!S90)^(1/20)-1 -> 0.0099016213 | I29: =(TableDE1!T110/TableDE1!T90)^(1/20)-1 -> 0.01253147 | J29: =(TableDE15a!C109/TableDE15a!C89)^(1/20)-1 -> 0.033573108 | K29: =(TableDE15a!B109/TableDE15a!B89)^(1/20)-1 -> 0.022395898 | L29: =(TableDE15a!D109/TableDE15a!D89)^(1/20)-1 -> 0.023001325
A32: 1970-2010 | B32: =(TableDE1!D150/TableDE1!D110)^(1/40)-1 -> 0.021559338 | C32: =(TableDE1!E150/TableDE1!E110)^(1/40)-1 -> 0.037104952 | D32: =(1+B32)/(1+G32)-1 -> 0.014141321 | E32: =(1+D32)*(1+J32)/(1+K32)-1 -> 0.011655005 | F32: =(1+D32)*(1+G32)/(1+I32)-1 -> 0.010835704 | G32: =(TableDE1!R150/TableDE1!R110)^(1/40)-1 -> 0.0073145794 | H32: =(TableDE1!S150/TableDE1!S110)^(1/40)-1 -> 0.01106038 | I32: =(TableDE1!T150/TableDE1!T110)^(1/40)-1 -> 0.010608681 | J32: =(TableDE15a!C149/TableDE15a!C109)^(1/40)-1 -> 0.02650428 | K32: =(TableDE15a!B149/TableDE15a!B109)^(1/40)-1 -> 0.02902709 | L32: =(TableDE15a!D149/TableDE15a!D109)^(1/40)-1 -> 0.027178723
A35: 1970-1990 | B35: =(TableDE1!D130/TableDE1!D110)^(1/20)-1 -> 0.024898549 | C35: =(TableDE1!E130/TableDE1!E110)^(1/20)-1 -> 0.038573882 | D35: =(1+B35)/(1+G35)-1 -> 0.023164645 | E35: =(1+D35)*(1+J35)/(1+K35)-1 -> 0.024255107 | F35: =(1+D35)*(1+G35)/(1+I35)-1 -> 0.018042412 | G35: =(TableDE1!R130/TableDE1!R110)^(1/20)-1 -> 0.0016946474 | H35: =(TableDE1!S130/TableDE1!S110)^(1/20)-1 -> 0.0076828005 | I35: =(TableDE1!T130/TableDE1!T110)^(1/20)-1 -> 0.0067346273 | J35: =(TableDE15a!C129/TableDE15a!C109)^(1/20)-1 -> 0.039355757 | K35: =(TableDE15a!B129/TableDE15a!B109)^(1/20)-1 -> 0.038249219 | L35: =(TableDE15a!D129/TableDE15a!D109)^(1/20)-1 -> 0.037798927
A38: 1990-2010 | B38: =(TableDE1!D150/TableDE1!D130)^(1/20)-1 -> 0.018231007 | C38: =(TableDE1!E150/TableDE1!E130)^(1/20)-1 -> 0.0356381 | D38: =(1+B38)/(1+G38)-1 -> 0.0051975734 | E38: =(1+D38)*(1+J38)/(1+K38)-1 -> -0.00079009304 | F38: =(1+D38)*(1+G38)/(1+I38)-1 -> 0.0036800123 | G38: =(TableDE1!R150/TableDE1!R130)^(1/20)-1 -> 0.012966042 | H38: =(TableDE1!S150/TableDE1!S130)^(1/20)-1 -> 0.014449281 | I38: =(TableDE1!T150/TableDE1!T130)^(1/20)-1 -> 0.014497643 | J38: =(TableDE15a!C149/TableDE15a!C129)^(1/20)-1 -> 0.01381171 | K38: =(TableDE15a!B149/TableDE15a!B129)^(1/20)-1 -> 0.019886876 | L38: =(TableDE15a!D149/TableDE15a!D129)^(1/20)-1 -> 0.016667199
A41: 1950-1960 | B41: =(TableDE1!D100/TableDE1!D90)^(1/10)-1 -> 0.080816059 | C41: =(TableDE1!E100/TableDE1!E90)^(1/10)-1 -> 0.075442167 | D41: =(1+B41)/(1+G41)-1 -> 0.070976203 | E41: =(1+D41)*(1+J41)/(1+K41)-1 -> 0.082234285 | F41: =(1+D41)*(1+G41)/(1+I41)-1 -> 0.05637746 | G41: =(TableDE1!R100/TableDE1!R90)^(1/10)-1 -> 0.0091877442 | H41: =(TableDE1!S100/TableDE1!S90)^(1/10)-1 -> 0.012196403 | I41: =(TableDE1!T100/TableDE1!T90)^(1/10)-1 -> 0.023134343 | J41: =(TableDE15a!C99/TableDE15a!C89)^(1/10)-1 -> 0.029493921 | K41: =(TableDE15a!B99/TableDE15a!B89)^(1/10)-1 -> 0.018784478 | L41: =(TableDE15a!D99/TableDE15a!D89)^(1/10)-1 -> 0.019120155
A51: 1960-1970 | B51: =(TableDE1!D110/TableDE1!D100)^(1/10)-1 -> 0.041570358 | C51: =(TableDE1!E110/TableDE1!E100)^(1/10)-1 -> 0.069759256 | D51: =(1+B51)/(1+G51)-1 -> 0.03180943 | E51: =(1+D51)*(1+J51)/(1+K51)-1 -> 0.043523495 | F51: =(1+D51)*(1+G51)/(1+I51)-1 -> 0.039451461 | G51: =(TableDE1!R110/TableDE1!R100)^(1/10)-1 -> 0.0094600103 | H51: =(TableDE1!S110/TableDE1!S100)^(1/10)-1 -> 0.0076120425 | I51: =(TableDE1!T110/TableDE1!T100)^(1/10)-1 -> 0.0020384768 | J51: =(TableDE15a!C109/TableDE15a!C99)^(1/10)-1 -> 0.037668458 | K51: =(TableDE15a!B109/TableDE15a!B99)^(1/10)-1 -> 0.026020119 | L51: =(TableDE15a!D109/TableDE15a!D99)^(1/10)-1 -> 0.026897277
A61: 1970-1980 | B61: =(TableDE1!D120/TableDE1!D110)^(1/10)-1 -> 0.026524044 | C61: =(TableDE1!E120/TableDE1!E110)^(1/10)-1 -> 0.038607253 | D61: =(1+B61)/(1+G61)-1 -> 0.025769756 | E61: =(1+D61)*(1+J61)/(1+K61)-1 -> 0.026043177 | F61: =(1+D61)*(1+G61)/(1+I61)-1 -> 0.023369765 | G61: =(TableDE1!R120/TableDE1!R110)^(1/10)-1 -> 0.00073533882 | H61: =(TableDE1!S120/TableDE1!S110)^(1/10)-1 -> 0.0053365804 | I61: =(TableDE1!T120/TableDE1!T110)^(1/10)-1 -> 0.0030822482 | J61: =(TableDE15a!C119/TableDE15a!C109)^(1/10)-1 -> 0.050962095 | K61: =(TableDE15a!B119/TableDE15a!B109)^(1/10)-1 -> 0.050682033 | L61: =(TableDE15a!D119/TableDE15a!D109)^(1/10)-1 -> 0.050327793
A71: 1980-1990 | B71: =(TableDE1!D130/TableDE1!D120)^(1/10)-1 -> 0.023275627 | C71: =(TableDE1!E130/TableDE1!E120)^(1/10)-1 -> 0.038540512 | D71: =(1+B71)/(1+G71)-1 -> 0.020566151 | E71: =(1+D71)*(1+J71)/(1+K71)-1 -> 0.022470152 | F71: =(1+D71)*(1+G71)/(1+I71)-1 -> 0.012742793 | G71: =(TableDE1!R130/TableDE1!R120)^(1/10)-1 -> 0.0026548755 | H71: =(TableDE1!S130/TableDE1!S120)^(1/10)-1 -> 0.010034496 | I71: =(TableDE1!T130/TableDE1!T120)^(1/10)-1 -> 0.010400305 | J71: =(TableDE15a!C129/TableDE15a!C119)^(1/10)-1 -> 0.027877595 | K71: =(TableDE15a!B129/TableDE15a!B119)^(1/10)-1 -> 0.025963525 | L71: =(TableDE15a!D129/TableDE15a!D119)^(1/10)-1 -> 0.025419512
A81: 1990-2000 | B81: =(TableDE1!D140/TableDE1!D130)^(1/10)-1 -> 0.024329897 | C81: =(TableDE1!E140/TableDE1!E130)^(1/10)-1 -> 0.044493816 | D81: =(1+B81)/(1+G81)-1 -> -0.0022541998 | E81: =(1+D81)*(1+J81)/(1+K81)-1 -> -0.0084812357 | F81: =(1+D81)*(1+G81)/(1+I81)-1 -> -0.0018167326 | G81: =(TableDE1!R140/TableDE1!R130)^(1/10)-1 -> 0.026644158 | H81: =(TableDE1!S140/TableDE1!S130)^(1/10)-1 -> 0.026254613 | I81: =(TableDE1!T140/TableDE1!T130)^(1/10)-1 -> 0.026194217 | J81: =(TableDE15a!C139/TableDE15a!C129)^(1/10)-1 -> 0.017818365 | K81: =(TableDE15a!B139/TableDE15a!B129)^(1/10)-1 -> 0.024210571 | L81: =(TableDE15a!D139/TableDE15a!D129)^(1/10)-1 -> 0.019731847
A91: 2000-2010 | B91: =(TableDE1!D150/TableDE1!D140)^(1/10)-1 -> 0.01216843 | C91: =(TableDE1!E150/TableDE1!E140)^(1/10)-1 -> 0.026857466 | D91: =(1+B91)/(1+G91)-1 -> 0.012705001 | E91: =(1+D91)*(1+J91)/(1+K91)-1 -> 0.0069607092 | F91: =(1+D91)*(1+G91)/(1+I91)-1 -> 0.0092070263 | G91: =(TableDE1!R150/TableDE1!R140)^(1/10)-1 -> -0.00052983899 | H91: =(TableDE1!S150/TableDE1!S140)^(1/10)-1 -> 0.0027797503 | I91: =(TableDE1!T150/TableDE1!T140)^(1/10)-1 -> 0.0029343871 | J91: =(TableDE15a!C149/TableDE15a!C139)^(1/10)-1 -> 0.009820826 | K91: =(TableDE15a!B149/TableDE15a!B139)^(1/10)-1 -> 0.015581434 | L91: =(TableDE15a!D149/TableDE15a!D139)^(1/10)-1 -> 0.013611762

Sheet TableDE3b
B1: Back to index
A3: Table DE.3b: Economic and population growth in Germany, 1870-2011: Corrections for frontier changes
B5: [1] | C5: [2] | D5: [3] | E5: [4] | F5: [5] | G5: [6] | H5: [7] | I5: [8] | J5: [9] | K5: [10] | L5: [11] | M5: [12] | N5: [13]
B6: Boundaries: Reunified Germany (pre-1991 evolution based on growth rates in the boundaries of the time, and specific adjustments made for border change)
B7: Population and real income growth | E7: Population and real income levels | J7: Real per capita income growth | M7: Memo: effect of territorial change | R7: Memo
B8: Population growth | C8: Memo: Population growth, Maddison | D8: Real national income growth | E8: Population (thousands) | F8: Adult population (thousands) | G8: Employed population (thousands) | H8: Real national income Yt | I8: Real per capita national income | J8: Real per capita national income growth | K8: Memo: real per capita income growth, Barro-Ursua | L8: Memo: real per capita income growth, Maddison | M8: Real income loss/gain caused by frontier changes (% Yt) | N8: Population loss/gain caused by frontier changes | R8: Income per capita Barro-Ursua | S8: Income per capita Maddison | T8: Population Maddison
D9: 1+gt = Yt/Yt-1 | H9: bn 2010 euros
A10: 1870 | E10: =E11/(1+B11) -> 29360.356 | F10: =E10*TableDE1!S10/TableDE1!R10 -> 16592.916 | G10: =TableDE3b!E10*TableDE1!T10/TableDE1!R10 -> 12756.798 | H10: =H11/(1+D11) -> 70.319313 | I10: =1000000*H10/E10 -> 2395.0429
A11: 1871 | B11: 0.0052 | C11: 0.0057352604 | D11: =(TableDE1!J11/TableDE1!J10)*(1+TableDE3b!B11)-1 -> 0.0014296781 | E11: =E12/(1+B12) -> 29513.03 | F11: =E11*TableDE1!S11/TableDE1!R11 -> 16679.199 | G11: =TableDE3b!E11*TableDE1!T11/TableDE1!R11 -> 12481.215 | H11: =H12/(1+D12) -> 70.419847 | I11: =1000000*H11/E11 -> 2386.0595 | J11: =I11/I10-1 -> -0.0037508177 | K11: 0.0052473986 | L11: -0.012243985 | M11: =(TableDE1!D11/TableDE1!D10)/(1+D11)-1 -> 0.039558736 | N11: =(TableDE1!R11/TableDE1!R10)/(1+B11)-1 -> 0.039558736 | R11: =1+K11 -> 1.0052474 | S11: =1+L11 -> 0.98775601 | T11: =1+C11 -> 1.0057353
A12: 1872 | B12: =TableDE1!R12/TableDE1!R11-1 -> 0.0046347116 | C12: 0.0059560016 | D12: =TableDE1!D12/TableDE1!D11-1 -> 0.10560937 | E12: =E13/(1+B13) -> 29649.815 | F12: =E12*TableDE1!S12/TableDE1!R12 -> 16806.816 | G12: =TableDE3b!E12*TableDE1!T12/TableDE1!R12 -> 12716.268 | H12: =H13/(1+D13) -> 77.856842 | I12: =1000000*H12/E12 -> 2625.8796 | J12: =I12/I11-1 -> 0.10050883 | K12: 0.01691421 | L12: 0.063203979 | M12: =(TableDE1!D12/TableDE1!D11)/(1+D12)-1 -> 0 | N12: =(TableDE1!R12/TableDE1!R11)/(1+B12)-1 -> 0 | R12: =1+K12 -> 1.0169142 | S12: =1+L12 -> 1.063204 | T12: =1+C12 -> 1.005956
A13: 1873 | B13: =TableDE1!R13/TableDE1!R12-1 -> 0.0084253976 | C13: 0.0082134489 | D13: =TableDE1!D13/TableDE1!D12-1 -> 0.023933673 | E13: =E14/(1+B14) -> 29899.626 | F13: =E13*TableDE1!S13/TableDE1!R13 -> 16999.157 | G13: =TableDE3b!E13*TableDE1!T13/TableDE1!R13 -> 12951.321 | H13: =H14/(1+D14) -> 79.720242 | I13: =1000000*H13/E13 -> 2666.2622 | J13: =I13/I12-1 -> 0.015378703 | K13: 0.016381297 | L13: 0.034844015 | M13: =(TableDE1!D13/TableDE1!D12)/(1+D13)-1 -> 0 | N13: =(TableDE1!R13/TableDE1!R12)/(1+B13)-1 -> 0 | R13: =1+K13 -> 1.0163813 | S13: =1+L13 -> 1.034844 | T13: =1+C13 -> 1.0082134
A14: 1874 | B14: =TableDE1!R14/TableDE1!R13-1 -> 0.010859097 | C14: 0.010820401 | D14: =TableDE1!D14/TableDE1!D13-1 -> 0.082865466 | E14: =E15/(1+B15) -> 30224.309 | F14: =E14*TableDE1!S14/TableDE1!R14 -> 17235.04 | G14: =TableDE3b!E14*TableDE1!T14/TableDE1!R14 -> 13186.374 | H14: =H15/(1+D15) -> 86.326297 | I14: =1000000*H14/E14 -> 2856.1876 | J14: =I14/I13-1 -> 0.071232845 | K14: 0.0099106407 | L14: 0.062685295 | M14: =(TableDE1!D14/TableDE1!D13)/(1+D14)-1 -> 0 | N14: =(TableDE1!R14/TableDE1!R13)/(1+B14)-1 -> 0 | R14: =1+K14 -> 1.0099106 | S14: =1+L14 -> 1.0626853 | T14: =1+C14 -> 1.0108204
A15: 1875 | B15: =TableDE1!R15/TableDE1!R14-1 -> 0.0125527 | C15: 0.01105068 | D15: =TableDE1!D15/TableDE1!D14-1 -> -0.012790705 | E15: =E16/(1+B16) -> 30603.706 | F15: =E15*TableDE1!S15/TableDE1!R15 -> 17503.318 | G15: =TableDE3b!E15*TableDE1!T15/TableDE1!R15 -> 13421.428 | H15: =H16/(1+D16) -> 85.222123 | I15: =1000000*H15/E15 -> 2784.6995 | J15: =I15/I14-1 -> -0.025029221 | K15: 0.029034836 | L15: -0.0054654214 | M15: =(TableDE1!D15/TableDE1!D14)/(1+D15)-1 -> 0 | N15: =(TableDE1!R15/TableDE1!R14)/(1+B15)-1 -> 0 | R15: =1+K15 -> 1.0290348 | S15: =1+L15 -> 0.99453458 | T15: =1+C15 -> 1.0110507
A16: 1876 | B16: =TableDE1!R16/TableDE1!R15-1 -> 0.012867561 | C16: 0.014524293 | D16: =TableDE1!D16/TableDE1!D15-1 -> -0.010097832 | E16: =E17/(1+B17) -> 30997.501 | F16: =E16*TableDE1!S16/TableDE1!R16 -> 17781.143 | G16: =TableDE3b!E16*TableDE1!T16/TableDE1!R16 -> 13599.967 | H16: =H17/(1+D17) -> 84.361564 | I16: =1000000*H16/E16 -> 2721.5602 | J16: =I16/I15-1 -> -0.022673638 | K16: -0.00013580353 | L16: -0.019732202 | M16: =(TableDE1!D16/TableDE1!D15)/(1+D16)-1 -> 0 | N16: =(TableDE1!R16/TableDE1!R15)/(1+B16)-1 -> 0 | R16: =1+K16 -> 0.9998642 | S16: =1+L16 -> 0.9802678 | T16: =1+C16 -> 1.0145243
A17: 1877 | B17: =TableDE1!R17/TableDE1!R16-1 -> 0.01279699 | C17: 0.013087176 | D17: =TableDE1!D17/TableDE1!D16-1 -> -0.0058385586 | E17: =E18/(1+B18) -> 31394.175 | F17: =E17*TableDE1!S17/TableDE1!R17 -> 18061.962 | G17: =TableDE3b!E17*TableDE1!T17/TableDE1!R17 -> 13756.189 | H17: =H18/(1+D18) -> 83.869014 | I17: =1000000*H17/E17 -> 2671.4833 | J17: =I17/I16-1 -> -0.018400083 | K17: -0.0039686345 | L17: -0.018371605 | M17: =(TableDE1!D17/TableDE1!D16)/(1+D17)-1 -> 0 | N17: =(TableDE1!R17/TableDE1!R16)/(1+B17)-1 -> 0 | R17: =1+K17 -> 0.99603137 | S17: =1+L17 -> 0.9816284 | T17: =1+C17 -> 1.0130872
A18: 1878 | B18: =TableDE1!R18/TableDE1!R17-1 -> 0.011901486 | C18: 0.012180616 | D18: =TableDE1!D18/TableDE1!D17-1 -> 0.052701779 | E18: =E19/(1+B19) -> 31767.813 | F18: =E18*TableDE1!S18/TableDE1!R18 -> 18330.833 | G18: =TableDE3b!E18*TableDE1!T18/TableDE1!R18 -> 13877.855 | H18: =H19/(1+D19) -> 88.28906 | I18: =1000000*H18/E18 -> 2779.1986 | J18: =I18/I17-1 -> 0.04032042 | K18: 0.031494083 | L18: 0.034619915 | M18: =(TableDE1!D18/TableDE1!D17)/(1+D18)-1 -> 0 | N18: =(TableDE1!R18/TableDE1!R17)/(1+B18)-1 -> 0 | R18: =1+K18 -> 1.0314941 | S18: =1+L18 -> 1.0346199 | T18: =1+C18 -> 1.0121806
A19: 1879 | B19: =TableDE1!R19/TableDE1!R18-1 -> 0.011602874 | C19: 0.01189301 | D19: =TableDE1!D19/TableDE1!D18-1 -> -0.027787197 | E19: =E20/(1+B20) -> 32136.411 | F19: =E19*TableDE1!S19/TableDE1!R19 -> 18598.056 | G19: =TableDE3b!E19*TableDE1!T19/TableDE1!R19 -> 14077.273 | H19: =H20/(1+D20) -> 85.835755 | I19: =1000000*H19/E19 -> 2670.9814 | J19: =I19/I18-1 -> -0.038938275 | K19: 0.011195013 | L19: -0.035345327 | M19: =(TableDE1!D19/TableDE1!D18)/(1+D19)-1 -> 0 | N19: =(TableDE1!R19/TableDE1!R18)/(1+B19)-1 -> 0 | R19: =1+K19 -> 1.011195 | S19: =1+L19 -> 0.96465467 | T19: =1+C19 -> 1.011893
A20: 1880 | B20: =TableDE1!R20/TableDE1!R19-1 -> 0.010170479 | C20: 0.010406021 | D20: =TableDE1!D20/TableDE1!D19-1 -> -0.029031208 | E20: =E21/(1+B21) -> 32463.253 | F20: =E20*TableDE1!S20/TableDE1!R20 -> 18842.294 | G20: =TableDE3b!E20*TableDE1!T20/TableDE1!R20 -> 14137.746 | H20: =H21/(1+D21) -> 83.343839 | I20: =1000000*H20/E20 -> 2567.3286 | J20: =I20/I19-1 -> -0.038807001 | K20: -0.034853599 | L20: -0.018367066 | M20: =(TableDE1!D20/TableDE1!D19)/(1+D20)-1 -> 0 | N20: =(TableDE1!R20/TableDE1!R19)/(1+B20)-1 -> 0 | R20: =1+K20 -> 0.9651464 | S20: =1+L20 -> 0.98163293 | T20: =1+C20 -> 1.010406
A21: 1881 | B21: =TableDE1!R21/TableDE1!R20-1 -> 0.0073847382 | C21: 0.0075172414 | D21: =TableDE1!D21/TableDE1!D20-1 -> 0.042054139 | E21: =E22/(1+B22) -> 32702.986 | F21: =E21*TableDE1!S21/TableDE1!R21 -> 18976.727 | G21: =TableDE3b!E21*TableDE1!T21/TableDE1!R21 -> 14214.777 | H21: =H22/(1+D22) -> 86.848793 | I21: =1000000*H21/E21 -> 2655.6839 | J21: =I21/I20-1 -> 0.034415253 | K21: 0.029591192 | L21: 0.017012407 | M21: =(TableDE1!D21/TableDE1!D20)/(1+D21)-1 -> 0 | N21: =(TableDE1!R21/TableDE1!R20)/(1+B21)-1 -> 0 | R21: =1+K21 -> 1.0295912 | S21: =1+L21 -> 1.0170124 | T21: =1+C21 -> 1.0075172
A22: 1882 | B22: =TableDE1!R22/TableDE1!R21-1 -> 0.006406023 | C22: 0.0065028407 | D22: =TableDE1!D22/TableDE1!D21-1 -> 0.0019336033 | E22: =E23/(1+B23) -> 32912.482 | F22: =E22*TableDE1!S22/TableDE1!R22 -> 19093.549 | G22: =TableDE3b!E22*TableDE1!T22/TableDE1!R22 -> 14368.119 | H22: =H23/(1+D23) -> 87.016724 | I22: =1000000*H22/E22 -> 2643.8821 | J22: =I22/I21-1 -> -0.0044439516 | K22: 0.0088317318 | L22: 0.0094783041 | M22: =(TableDE1!D22/TableDE1!D21)/(1+D22)-1 -> 0 | N22: =(TableDE1!R22/TableDE1!R21)/(1+B22)-1 -> 0 | R22: =1+K22 -> 1.0088317 | S22: =1+L22 -> 1.0094783 | T22: =1+C22 -> 1.0065028
A23: 1883 | B23: =TableDE1!R23/TableDE1!R22-1 -> 0.0064964893 | C23: 0.006619514 | D23: =TableDE1!D23/TableDE1!D22-1 -> 0.058222594 | E23: =E24/(1+B24) -> 33126.298 | F23: =E23*TableDE1!S23/TableDE1!R23 -> 19212.816 | G23: =TableDE3b!E23*TableDE1!T23/TableDE1!R23 -> 14533.701 | H23: =H24/(1+D24) -> 92.083063 | I23: =1000000*H23/E23 -> 2779.7572 | J23: =I23/I22-1 -> 0.051392235 | K23: 0.035485749 | L23: 0.048323764 | M23: =(TableDE1!D23/TableDE1!D22)/(1+D23)-1 -> 0 | N23: =(TableDE1!R23/TableDE1!R22)/(1+B23)-1 -> 0 | R23: =1+K23 -> 1.0354857 | S23: =1+L23 -> 1.0483238 | T23: =1+C23 -> 1.0066195
... A53: 1913 | B53: =TableDE1!R53/TableDE1!R52-1 -> 0.012578236 | C53: 0.0093240455 | D53: =TableDE1!D53/TableDE1!D52-1 -> 0.0080258856 | E53: =E54/(1+B54) -> 48218.654 | F53: =E53*TableDE1!S53/TableDE1!R53 -> 27395.395 | G53: =TableDE3b!E53*TableDE1!T53/TableDE1!R53 -> 22294.414 | H53: =H54/(1+D54) -> 211.04662 | I53: =1000000*H53/E53 -> 4376.8666 | J53: =I53/I52-1 -> -0.0044958012 | K53: 0.034610636 | L53: 0.03527909 | M53: =(TableDE1!D53/TableDE1!D52)/(1+D53)-1 -> 0 | N53: =(TableDE1!R53/TableDE1!R52)/(1+B53)-1 -> 0 | R53: =1+K53 -> 1.0346106 | S53: =1+L53 -> 1.0352791 | T53: =1+C53 -> 1.009324
A54: =A53+1 -> 1914 | B54: =TableDE1!R54/TableDE1!R53-1 -> 0.012123384 | C54: 0.015954994 | D54: =TableDE1!D54/TableDE1!D53-1 -> -0.076707054 | E54: =E55/(1+B55) -> 48803.228 | F54: =E54*TableDE1!S54/TableDE1!R54 -> 28005.585 | H54: =H55/(1+D55) -> 194.85785 | I54: =1000000*H54/E54 -> 3992.7247 | J54: =I54/I53-1 -> -0.087766412 | K54: -0.075954994 | L54: -0.16138017 | M54: =(TableDE1!D54/TableDE1!D53)/(1+D54)-1 -> 0 | N54: =(TableDE1!R54/TableDE1!R53)/(1+B54)-1 -> 0 | R54: =1+K54 -> 0.92404501 | S54: =1+L54 -> 0.83861983 | T54: =1+C54 -> 1.015955
A55: =A54+1 -> 1915 | B55: =TableDE1!R55/TableDE1!R54-1 -> 0.0013718838 | C55: 0.0020273542 | D55: =TableDE1!D55/TableDE1!D54-1 -> -0.081358202 | E55: =E56/(1+B56) -> 48870.18 | F55: =E55*TableDE1!S55/TableDE1!R55 -> 28322.451 | H55: =H56/(1+D56) -> 179.00457 | I55: =1000000*H55/E55 -> 3662.8588 | J55: =I55/I54-1 -> -0.082616745 | K55: -0.12968693 | L55: -0.052390623 | M55: =(TableDE1!D55/TableDE1!D54)/(1+D55)-1 -> 0 | N55: =(TableDE1!R55/TableDE1!R54)/(1+B55)-1 -> 0 | R55: =1+K55 -> 0.87031307 | S55: =1+L55 -> 0.94760938 | T55: =1+C55 -> 1.0020274
A56: =A55+1 -> 1916 | B56: =TableDE1!R56/TableDE1!R55-1 -> -0.0024748464 | C56: -0.0023252303 | D56: =TableDE1!D56/TableDE1!D55-1 -> -0.046332931 | E56: =E57/(1+B57) -> 48749.234 | F56: =E56*TableDE1!S56/TableDE1!R56 -> 28530.115 | H56: =H57/(1+D57) -> 170.71076 | I56: =1000000*H56/E56 -> 3501.8143 | J56: =I56/I55-1 -> -0.043966896 | K56: -0.0098698917 | L56: 0.012242448 | M56: =(TableDE1!D56/TableDE1!D55)/(1+D56)-1 -> 0 | N56: =(TableDE1!R56/TableDE1!R55)/(1+B56)-1 -> 0 | R56: =1+K56 -> 0.99013011 | S56: =1+L56 -> 1.0122424 | T56: =1+C56 -> 0.99767477
A57: =A56+1 -> 1917 | B57: =TableDE1!R57/TableDE1!R56-1 -> -0.0051244185 | C57: -0.0047369696 | D57: =TableDE1!D57/TableDE1!D56-1 -> -0.023997205 | E57: =E58/(1+B58) -> 48499.422 | F57: =E57*TableDE1!S57/TableDE1!R57 -> 28660.248 | H57: =H58/(1+D58) -> 166.61418 | I57: =1000000*H57/E57 -> 3435.3848 | J57: =I57/I56-1 -> -0.018969997 | K57: -0.14341118 | L57: 0.005989331 | M57: =(TableDE1!D57/TableDE1!D56)/(1+D57)-1 -> 0 | N57: =(TableDE1!R57/TableDE1!R56)/(1+B57)-1 -> 0 | R57: =1+K57 -> 0.85658882 | S57: =1+L57 -> 1.0059893 | T57: =1+C57 -> 0.99526303
A58: =A57+1 -> 1918 | B58: =TableDE1!R58/TableDE1!R57-1 -> -0.0082680204 | C58: -0.0079984186 | D58: =TableDE1!D58/TableDE1!D57-1 -> -0.026757349 | E58: =E59/(1+B59) -> 48098.428 | F58: =E58*TableDE1!S58/TableDE1!R58 -> 28697.333 | H58: =H59/(1+D59) -> 162.15603 | I58: =1000000*H58/E58 -> 3371.3373 | J58: =I58/I57-1 -> -0.018643474 | K58: -0.018758931 | L58: 0.010527611 | M58: =(TableDE1!D58/TableDE1!D57)/(1+D58)-1 -> 0 | N58: =(TableDE1!R58/TableDE1!R57)/(1+B58)-1 -> 0 | R58: =1+K58 -> 0.98124107 | S58: =1+L58 -> 1.0105276 | T58: =1+C58 -> 0.99200158
A59: =A58+1 -> 1919 | B59: 0.00575 | C59: =37966/37749-1 -> 0.0057484966 | D59: =(TableDE1!J59/TableDE1!J58)*(1+B59)-1 -> -0.04988727 | E59: =E60/(1+B60) -> 48374.994 | F59: =E59*TableDE1!S59/TableDE1!R59 -> 29137.968 | H59: =H60/(1+D60) -> 154.06651 | I59: =1000000*H59/E59 -> 3184.8377 | J59: =I59/I58-1 -> -0.055319184 | K59: -0.038769861 | L59: -0.13304212 | M59: =(TableDE1!D59/TableDE1!D58)/(1+D59)-1 -> -0.063965367 | N59: =(TableDE1!R59/TableDE1!R58)/(1+B59)-1 -> -0.063965367 | R59: =1+K59 -> 0.96123014 | S59: =1+L59 -> 0.86695788 | T59: =1+C59 -> 1.0057485
A60: =A59+1 -> 1920 | B60: 0.00574 | C60: 0.0057310849 | D60: =(TableDE1!J60/TableDE1!J59)*(1+B60)-1 -> 0.15866219 | E60: =E61/(1+B61) -> 48652.667 | F60: =E60*TableDE1!S60/TableDE1!R60 -> 29582.427 | H60: =H61/(1+D61) -> 178.51103 | I60: =1000000*H60/E60 -> 3669.0905 | J60: =I60/I59-1 -> 0.15204943 | K60: 0.11322053 | L60: 0.080936505 | M60: =(TableDE1!D60/TableDE1!D59)/(1+D60)-1 -> -0.034272784 | N60: =(TableDE1!R60/TableDE1!R59)/(1+B60)-1 -> -0.034272784 | R60: =1+K60 -> 1.1132205 | S60: =1+L60 -> 1.0809365 | T60: =1+C60 -> 1.0057311
A61: =A60+1 -> 1921 | B61: 0.01116 | C61: 0.011150524 | D61: =(TableDE1!J61/TableDE1!J60)*(1+B61)-1 -> 0.060336597 | E61: =E62/(1+B62) -> 49195.63 | F61: =E61*TableDE1!S61/TableDE1!R61 -> 30192.867 | H61: =H62/(1+D62) -> 189.28178 | I61: =1000000*H61/E61 -> 3847.5324 | J61: =I61/I60-1 -> 0.048633843 | K61: 0.048932636 | L61: 0.10095548 | M61: =(TableDE1!D61/TableDE1!D60)/(1+D61)-1 -> -0.00023901535 | N61: =(TableDE1!R61/TableDE1!R60)/(1+B61)-1 -> -0.00023901535 | R61: =1+K61 -> 1.0489326 | S61: =1+L61 -> 1.1009555 | T61: =1+C61 -> 1.0111505
A62: =A61+1 -> 1922 | B62: 0.0084 | C62: 0.0053107693 | D62: =(TableDE1!J62/TableDE1!J61)*(1+B62)-1 -> 0.076368725 | E62: =E63/(1+B63) -> 49608.874 | F62: =E62*TableDE1!S62/TableDE1!R62 -> 30729.142 | H62: =H63/(1+D63) -> 203.73699 | I62: =1000000*H62/E62 -> 4106.8659 | J62: =I62/I61-1 -> 0.067402544 | K62: 0.054417718 | L62: 0.082252575 | M62: =(TableDE1!D62/TableDE1!D61)/(1+D62)-1 -> -0.015459608 | N62: =(TableDE1!R62/TableDE1!R61)/(1+B62)-1 -> -0.015459608 | R62: =1+K62 -> 1.0544177 | S62: =1+L62 -> 1.0822526 | T62: =1+C62 -> 1.0053108
A63: =A62+1 -> 1923 | B63: 0.00657 | C63: 0.0065751212 | D63: =(TableDE1!J63/TableDE1!J62)*(1+B63)-1 -> -0.13035634 | E63: =E64/(1+B64) -> 49934.804 | F63: =E63*TableDE1!S63/TableDE1!R63 -> 31215.544 | H63: =H64/(1+D64) -> 177.17858 | I63: =1000000*H63/E63 -> 3548.1982 | J63: =I63/I62-1 -> -0.13603261 | K63: -0.13690083 | L63: -0.17454497 | M63: =(TableDE1!D63/TableDE1!D62)/(1+D63)-1 -> 3.5219329e-05 | N63: =(TableDE1!R63/TableDE1!R62)/(1+B63)-1 -> 3.5219329e-05 | R63: =1+K63 -> 0.86309917 | S63: =1+L63 -> 0.82545503 | T63: =1+C63 -> 1.0065751
A64: =A63+1 -> 1924 | B64: =TableDE1!R64/TableDE1!R63-1 -> 0.0063028614 | C64: 0.0062593288 | D64: =TableDE1!D64/TableDE1!D63-1 -> 0.11417695 | E64: =E65/(1+B65) -> 50249.536 | F64: =E64*TableDE1!S64/TableDE1!R64 -> 31698.597 | H64: =H65/(1+D65) -> 197.40829 | I64: =1000000*H64/E64 -> 3928.5595 | J64: =I64/I63-1 -> 0.10719843 | K64: 0.10791762 | L64: 0.16338888 | M64: =(TableDE1!D64/TableDE1!D63)/(1+D64)-1 -> 0 | N64: =(TableDE1!R64/TableDE1!R63)/(1+B64)-1 -> 0 | R64: =1+K64 -> 1.1079176 | S64: =1+L64 -> 1.1633889 | T64: =1+C64 -> 1.0062593
A65: =A64+1 -> 1925 | B65: =TableDE1!R65/TableDE1!R64-1 -> 0.0048786771 | C65: 0.0074804217 | D65: =TableDE1!D65/TableDE1!D64-1 -> 0.087780693 | E65: =E66/(1+B66) -> 50494.687 | F65: =E65*TableDE1!S65/TableDE1!R65 -> 32140.946 | G65: =TableDE3b!E65*TableDE1!T65/TableDE1!R65 -> 25108.182 | H65: =H66/(1+D66) -> 214.73693 | I65: =1000000*H65/E65 -> 4252.6638 | J65: =I65/I64-1 -> 0.082499527 | K65: 0.065159266 | L65: 0.10405343 | M65: =(TableDE1!D65/TableDE1!D64)/(1+D65)-1 -> 0 | N65: =(TableDE1!R65/TableDE1!R64)/(1+B65)-1 -> 0 | R65: =1+K65 -> 1.0651593 | S65: =1+L65 -> 1.1040534 | T65: =1+C65 -> 1.0074804
A66: =A65+1 -> 1926 | B66: =TableDE1!R66/TableDE1!R65-1 -> 0.0073225445 | C66: 0.007345724 | D66: =TableDE1!D66/TableDE1!D65-1 -> 0.0071741376 | E66: =E67/(1+B67) -> 50864.437 | F66: =E66*TableDE1!S66/TableDE1!R66 -> 32723.479 | G66: =TableDE3b!E66*TableDE1!T66/TableDE1!R66 -> 24152.658 | H66: =H67/(1+D67) -> 216.27748 | I66: =1000000*H66/E66 -> 4252.0373 | J66: =I66/I65-1 -> -0.00014732803 | K66: 0.0055721791 | L66: 0.020658093 | M66: =(TableDE1!D66/TableDE1!D65)/(1+D66)-1 -> 0 | N66: =(TableDE1!R66/TableDE1!R65)/(1+B66)-1 -> 0 | R66: =1+K66 -> 1.0055722 | S66: =1+L66 -> 1.0206581 | T66: =1+C66 -> 1.0073457
A67: =A66+1 -> 1927 | B67: =TableDE1!R67/TableDE1!R66-1 -> 0.0061399462 | C67: 0.0061763319 | D67: =TableDE1!D67/TableDE1!D66-1 -> 0.10165309 | E67: =E68/(1+B68) -> 51176.742 | F67: =E67*TableDE1!S67/TableDE1!R67 -> 33273.71 | G67: =TableDE3b!E67*TableDE1!T67/TableDE1!R67 -> 25860.626 | H67: =H68/(1+D68) -> 238.26276 | I67: =1000000*H67/E67 -> 4655.6844 | J67: =I67/I66-1 -> 0.09493028 | K67: 0.096005181 | L67: 0.093341768 | M67: =(TableDE1!D67/TableDE1!D66)/(1+D67)-1 -> 0 | N67: =(TableDE1!R67/TableDE1!R66)/(1+B67)-1 -> 0 | R67: =1+K67 -> 1.0960052 | S67: =1+L67 -> 1.0933418 | T67: =1+C67 -> 1.0061763
A68: =A67+1 -> 1928 | B68: =TableDE1!R68/TableDE1!R67-1 -> 0.0057704773 | C68: 0.0057791731 | D68: =TableDE1!D68/TableDE1!D67-1 -> 0.033265191 | E68: =E69/(1+B69) -> 51472.056 | F68: =E68*TableDE1!S68/TableDE1!R68 -> 33817.042 | G68: =TableDE3b!E68*TableDE1!T68/TableDE1!R68 -> 26320.184 | H68: =H69/(1+D69) -> 246.18861 | I68: =1000000*H68/E68 -> 4782.9567 | J68: =I68/I67-1 -> 0.027336967 | K68: 0.026629793 | L68: 0.037780058 | M68: =(TableDE1!D68/TableDE1!D67)/(1+D68)-1 -> 0 | N68: =(TableDE1!R68/TableDE1!R67)/(1+B68)-1 -> 0 | R68: =1+K68 -> 1.0266298 | S68: =1+L68 -> 1.0377801 | T68: =1+C68 -> 1.0057792
A69: =A68+1 -> 1929 | B69: =TableDE1!R69/TableDE1!R68-1 -> 0.0053443994 | C69: 0.0053732549 | D69: =TableDE1!D69/TableDE1!D68-1 -> -0.020622404 | E69: =E70/(1+B70) -> 51747.143 | F69: =E69*TableDE1!S69/TableDE1!R69 -> 34350.978 | G69: =TableDE3b!E69*TableDE1!T69/TableDE1!R69 -> 26105.778 | H69: =H70/(1+D70) -> 241.11161 | I69: =1000000*H69/E69 -> 4659.4188 | J69: =I69/I68-1 -> -0.025828764 | K69: -0.020665717 | L69: -0.0094346923 | M69: =(TableDE1!D69/TableDE1!D68)/(1+D69)-1 -> 0 | N69: =(TableDE1!R69/TableDE1!R68)/(1+B69)-1 -> 0 | R69: =1+K69 -> 0.97933428 | S69: =1+L69 -> 0.99056531 | T69: =1+C69 -> 1.0053733
A70: =A69+1 -> 1930 | B70: =TableDE1!R70/TableDE1!R69-1 -> 0.0052690828 | C70: 0.0053290907 | D70: =TableDE1!D70/TableDE1!D69-1 -> -0.076843125 | E70: =E71/(1+B71) -> 52019.803 | F70: =E70*TableDE1!S70/TableDE1!R70 -> 34887.041 | G70: =TableDE3b!E70*TableDE1!T70/TableDE1!R70 -> 24663.188 | H70: =H71/(1+D71) -> 222.58384 | I70: =1000000*H70/E70 -> 4278.829 | J70: =I70/I69-1 -> -0.08168182 | K70: -0.072050371 | L70: -0.019264646 | M70: =(TableDE1!D70/TableDE1!D69)/(1+D70)-1 -> 0 | N70: =(TableDE1!R70/TableDE1!R69)/(1+B70)-1 -> 0 | R70: =1+K70 -> 0.92794963 | S70: =1+L70 -> 0.98073535 | T70: =1+C70 -> 1.0053291
A71: =A70+1 -> 1931 | B71: =TableDE1!R71/TableDE1!R70-1 -> 0.0052259118 | C71: 0.0052086534 | D71: =TableDE1!D71/TableDE1!D70-1 -> -0.13132942 | E71: =E72/(1+B72) -> 52291.654 | F71: =E71*TableDE1!S71/TableDE1!R71 -> 35426.279 | G71: =TableDE3b!E71*TableDE1!T71/TableDE1!R71 -> 22747.286 | H71: =H72/(1+D72) -> 193.35204 | I71: =1000000*H71/E71 -> 3697.5697 | J71: =I71/I70-1 -> -0.13584542 | K71: -0.13274624 | L71: -0.081000392 | M71: =(TableDE1!D71/TableDE1!D70)/(1+D71)-1 -> 0 | N71: =(TableDE1!R71/TableDE1!R70)/(1+B71)-1 -> 0 | R71: =1+K71 -> 0.86725376 | S71: =1+L71 -> 0.91899961 | T71: =1+C71 -> 1.0052087
A72: =A71+1 -> 1932 | B72: =TableDE1!R72/TableDE1!R71-1 -> 0.0043477588 | C72: 0.0044785473 | D72: =TableDE1!D72/TableDE1!D71-1 -> -0.087655855 | E72: =E73/(1+B73) -> 52519.006 | F72: =E72*TableDE1!S72/TableDE1!R72 -> 35938.776 | G72: =TableDE3b!E72*TableDE1!T72/TableDE1!R72 -> 21127.508 | H72: =H73/(1+D73) -> 176.4036 | I72: =1000000*H72/E72 -> 3358.8526 | J72: =I72/I71-1 -> -0.091605335 | K72: -0.086356277 | L72: -0.079374329 | M72: =(TableDE1!D72/TableDE1!D71)/(1+D72)-1 -> 0 | N72: =(TableDE1!R72/TableDE1!R71)/(1+B72)-1 -> 0 | R72: =1+K72 -> 0.91364372 | S72: =1+L72 -> 0.92062567 | T72: =1+C72 -> 1.0044785
A73: =A72+1 -> 1933 | B73: =TableDE1!R73/TableDE1!R72-1 -> 0.0048219127 | C73: 0.0047324852 | D73: =TableDE1!D73/TableDE1!D72-1 -> 0.077785493 | E73: =E74/(1+B74) -> 52772.248 | F73: =E73*TableDE1!S73/TableDE1!R73 -> 36472.271 | G73: =TableDE3b!E73*TableDE1!T73/TableDE1!R73 -> 21591.92 | H73: =H74/(1+D74) -> 190.12524 | I73: =1000000*H73/E73 -> 3602.7504 | J73: =I73/I72-1 -> 0.072613445 | K73: 0.072486512 | L73: 0.057742083 | M73: =(TableDE1!D73/TableDE1!D72)/(1+D73)-1 -> 0 | N73: =(TableDE1!R73/TableDE1!R72)/(1+B73)-1 -> 0 | R73: =1+K73 -> 1.0724865 | S73: =1+L73 -> 1.0577421 | T73: =1+C73 -> 1.0047325
A74: =A73+1 -> 1934 | B74: =TableDE1!R74/TableDE1!R73-1 -> 0.0002759678 | C74: 0.005785512 | D74: =TableDE1!D74/TableDE1!D73-1 -> 0.12812545 | E74: =E75/(1+B75) -> 52786.811 | F74: =E74*TableDE1!S74/TableDE1!R74 -> 36488.141 | G74: =TableDE3b!E74*TableDE1!T74/TableDE1!R74 -> 23310.406 | H74: =H75/(1+D75) -> 214.48512 | I74: =1000000*H74/E74 -> 4063.2331 | J74: =I74/I73-1 -> 0.12781421 | K74: 0.096264138 | L74: 0.085051253 | M74: =(TableDE1!D74/TableDE1!D73)/(1+D74)-1 -> 0 | N74: =(TableDE1!R74/TableDE1!R73)/(1+B74)-1 -> 0 | R74: =1+K74 -> 1.0962641 | S74: =1+L74 -> 1.0850513 | T74: =1+C74 -> 1.0057855
A75: =A74+1 -> 1935 | B75: 0.007 | C75: 0.0069568884 | D75: =(TableDE1!J75/TableDE1!J74)*(1+TableDE3b!B75)-1 -> 0.10384787 | E75: =E76/(1+B76) -> 53156.319 | F75: =E75*TableDE1!S75/TableDE1!R75 -> 36749.403 | G75: =TableDE3b!E75*TableDE1!T75/TableDE1!R75 -> 23915.614 | H75: =H76/(1+D76) -> 236.75894 | I75: =1000000*H75/E75 -> 4454.0132 | J75: =I75/I74-1 -> 0.096174651 | K75: 0.11527886 | L75: 0.067803632 | M75: =(TableDE1!D75/TableDE1!D74)/(1+D75)-1 -> 0.017828072 | N75: =(TableDE1!R75/TableDE1!R74)/(1+B75)-1 -> 0.017828072 | R75: =1+K75 -> 1.1152789 | S75: =1+L75 -> 1.0678036 | T75: =1+C75 -> 1.0069569
A76: =A75+1 -> 1936 | B76: =DataDE1c!BI99/DataDE1c!BI98-1 -> 0.0071480911 | C76: 0.0071480911 | D76: =TableDE1!D76/TableDE1!D75-1 -> 0.11875142 | E76: =E77/(1+B77) -> 53536.285 | F76: =E76*TableDE1!S76/TableDE1!R76 -> 37017.979 | G76: =TableDE3b!E76*TableDE1!T76/TableDE1!R76 -> 24967.278 | H76: =H77/(1+D77) -> 264.8744 | I76: =1000000*H76/E76 -> 4947.5679 | J76: =I76/I75-1 -> 0.11081124 | K76: 0.10721612 | L76: 0.080326195 | M76: =(TableDE1!D76/TableDE1!D75)/(1+D76)-1 -> 0 | N76: =(TableDE1!R76/TableDE1!R75)/(1+B76)-1 -> 0 | R76: =1+K76 -> 1.1072161 | S76: =1+L76 -> 1.0803262 | T76: =1+C76 -> 1.0071481
A77: =A76+1 -> 1937 | B77: =DataDE1c!BI100/DataDE1c!BI99-1 -> 0.0071567507 | C77: 0.0071567507 | D77: =TableDE1!D77/TableDE1!D76-1 -> 0.11651103 | E77: =E78/(1+B78) -> 53919.431 | F77: =E77*TableDE1!S77/TableDE1!R77 -> 37288.836 | G77: =TableDE3b!E77*TableDE1!T77/TableDE1!R77 -> 26024.506 | H77: =H78/(1+D78) -> 295.73519 | I77: =1000000*H77/E77 -> 5484.761 | J77: =I77/I76-1 -> 0.10857721 | K77: 0.10393517 | L77: 0.052616211 | M77: =(TableDE1!D77/TableDE1!D76)/(1+D77)-1 -> 0 | N77: =(TableDE1!R77/TableDE1!R76)/(1+B77)-1 -> 0 | R77: =1+K77 -> 1.1039352 | S77: =1+L77 -> 1.0526162 | T77: =1+C77 -> 1.0071568
A78: =A77+1 -> 1938 | B78: =DataDE1c!BI101/DataDE1c!BI100-1 -> 0.010717813 | C78: 0.010717813 | D78: =(TableDE1!J78/TableDE1!J77)*(1+TableDE3b!B78)-1 -> 0.090889094 | E78: =E79/(1+B79) -> 54497.329 | F78: =E78*TableDE1!S78/TableDE1!R78 -> 37694.484 | H78: =H79/(1+D79) -> 322.6143 | I78: =1000000*H78/E78 -> 5919.8185 | J78: =I78/I77-1 -> 0.079321131 | K78: 0.083867422 | L78: 0.065886643 | M78: =(TableDE1!D78/TableDE1!D77)/(1+D78)-1 -> 0.099740366 | N78: =(TableDE1!R78/TableDE1!R77)/(1+B78)-1 -> 0.099740366 | R78: =1+K78 -> 1.0838674 | S78: =1+L78 -> 1.0658866 | T78: =1+C78 -> 1.0107178
A79: =A78+1 -> 1939 | B79: =DataDE1c!BI102/DataDE1c!BI101-1 -> 0.010618746 | C79: 0.010618746 | D79: =(TableDE1!J79/TableDE1!J78)*(1+TableDE3b!B79)-1 -> 0.042336922 | E79: =E80/(1+B80) -> 55076.023 | F79: =E79*TableDE1!S79/TableDE1!R79 -> 38100.809 | H79: =H80/(1+D80) -> 336.27279 | I79: =1000000*H79/E79 -> 6105.6114 | J79: =I79/I78-1 -> 0.031384907 | K79: 0.17706768 | L79: 0.082635233 | M79: =(TableDE1!D79/TableDE1!D78)/(1+D79)-1 -> 0.14060191 | N79: =(TableDE1!R79/TableDE1!R78)/(1+B79)-1 -> 0.14060191 | R79: =1+K79 -> 1.1770677 | S79: =1+L79 -> 1.0826352 | T79: =1+C79 -> 1.0106187
A80: =A79+1 -> 1940 | B80: 0.0079236787 | C80: 0.0079236787 | D80: =(TableDE1!J80/TableDE1!J79)*(1+TableDE3b!B80)-1 -> 0.036090816 | E80: =E81/(1+B81) -> 55512.427 | F80: =E80*TableDE1!S80/TableDE1!R80 -> 38408.812 | H80: =H81/(1+D81) -> 348.40915 | I80: =1000000*H80/E80 -> 6276.237 | J80: =I80/I79-1 -> 0.027945705 | K80: 0.15258209 | L80: -0.00069138186 | M80: =(TableDE1!D80/TableDE1!D79)/(1+D80)-1 -> 0.12071366 | N80: =(TableDE1!R80/TableDE1!R79)/(1+B80)-1 -> 0.12071366 | R80: =1+K80 -> 1.1525821 | S80: =1+L80 -> 0.99930862 | T80: =1+C80 -> 1.0079237
A81: =A80+1 -> 1941 | B81: =TableDE1!R81/TableDE1!R80-1 -> 0.0062950098 | C81: 0.0058566621 | D81: =TableDE1!D81/TableDE1!D80-1 -> 0.1424208 | E81: =E82/(1+B82) -> 55861.879 | F81: =E81*TableDE1!S81/TableDE1!R81 -> 38656.739 | H81: =H82/(1+D82) -> 398.02986 | I81: =1000000*H81/E81 -> 7125.2502 | J81: =I81/I80-1 -> 0.13527423 | K81: 0.13615063 | L81: 0.057129748 | M81: =(TableDE1!D81/TableDE1!D80)/(1+D81)-1 -> 0 | N81: =(TableDE1!R81/TableDE1!R80)/(1+B81)-1 -> 0 | R81: =1+K81 -> 1.1361506 | S81: =1+L81 -> 1.0571297 | T81: =1+C81 -> 1.0058567
A82: =A81+1 -> 1942 | B82: =TableDE1!R82/TableDE1!R81-1 -> 0.0021155773 | C82: 0.0083992939 | D82: =TableDE1!D82/TableDE1!D81-1 -> 0.056508469 | E82: =E83/(1+B83) -> 55980.059 | F82: =E82*TableDE1!S82/TableDE1!R82 -> 38744.676 | H82: =H83/(1+D83) -> 420.52192 | I82: =1000000*H82/E82 -> 7511.995 | J82: =I82/I81-1 -> 0.054278063 | K82: 0.047950635 | L82: 0.0050388185 | M82: =(TableDE1!D82/TableDE1!D81)/(1+D82)-1 -> 0 | N82: =(TableDE1!R82/TableDE1!R81)/(1+B82)-1 -> 0 | R82: =1+K82 -> 1.0479506 | S82: =1+L82 -> 1.0050388 | T82: =1+C82 -> 1.0083993
A83: =A82+1 -> 1943 | B83: =TableDE1!R83/TableDE1!R82-1 -> 0 | C83: -0.0059717085 | D83: =TableDE1!D83/TableDE1!D82-1 -> 0.063865572 | E83: =E84/(1+B84) -> 55980.059 | F83: =E83*TableDE1!S83/TableDE1!R83 -> 38750.832 | H83: =H84/(1+D84) -> 447.37879 | I83: =1000000*H83/E83 -> 7991.7528 | J83: =I83/I82-1 -> 0.063865572 | K83: 0.069628828 | L83: 0.026084089 | M83: =(TableDE1!D83/TableDE1!D82)/(1+D83)-1 -> 0 | N83: =(TableDE1!R83/TableDE1!R82)/(1+B83)-1 -> 0 | R83: =1+K83 -> 1.0696288 | S83: =1+L83 -> 1.0260841 | T83: =1+C83 -> 0.99402829
A84: =A83+1 -> 1944 | B84: =TableDE1!R84/TableDE1!R83-1 -> 0 | C84: -0.0077544702 | D84: =TableDE1!D84/TableDE1!D83-1 -> -0.084887432 | E84: =E85/(1+B85) -> 55980.059 | F84: =E84*TableDE1!S84/TableDE1!R84 -> 38756.988 | H84: =H85/(1+D85) -> 409.40196 | I84: =1000000*H84/E84 -> 7313.3535 | J84: =I84/I83-1 -> -0.084887432 | K84: -0.077040916 | L84: 0.032956011 | M84: =(TableDE1!D84/TableDE1!D83)/(1+D84)-1 -> 0 | N84: =(TableDE1!R84/TableDE1!R83)/(1+B84)-1 -> 0 | R84: =1+K84 -> 0.92295908 | S84: =1+L84 -> 1.032956 | T84: =1+C84 -> 0.99224553
A85: =A84+1 -> 1945 | B85: 0.027186195 | C85: =45000/43809-1 -> 0.027186195 | D85: =(TableDE1!J85/TableDE1!J84)*(1+TableDE3b!B85)-1 -> -0.5505659 | E85: =E86/(1+B86) -> 57501.943 | F85: =E85*TableDE1!S85/TableDE1!R85 -> 39816.966 | H85: =H86/(1+D86) -> 183.9992 | I85: =1000000*H85/E85 -> 3199.8779 | J85: =I85/I84-1 -> -0.56246092 | K85: -0.66064904 | L85: -0.25797647 | M85: =(TableDE1!D85/TableDE1!D84)/(1+D85)-1 -> -0.3785917 | N85: =(TableDE1!R85/TableDE1!R84)/(1+B85)-1 -> -0.3785917 | R85: =1+K85 -> 0.33935096 | S85: =1+L85 -> 0.74202353 | T85: =1+C85 -> 1.0271862
A86: =A85+1 -> 1946 | B86: =TableDE1!R86/TableDE1!R85-1 -> 0.026444444 | C86: =46190/45000-1 -> 0.026444444 | D86: =TableDE1!D86/TableDE1!D85-1 -> -0.13573378 | E86: =E87/(1+B87) -> 59022.55 | F86: =E86*TableDE1!S86/TableDE1!R86 -> 40876.394 | H86: =H87/(1+D87) -> 159.02429 | I86: =1000000*H86/E86 -> 2694.2972 | J86: =I86/I85-1 -> -0.158 | K86: -0.15836703 | L86: -0.50892685 | M86: =(TableDE1!D86/TableDE1!D85)/(1+D86)-1 -> 0 | N86: =(TableDE1!R86/TableDE1!R85)/(1+B86)-1 -> 0 | R86: =1+K86 -> 0.84163297 | S86: =1+L86 -> 0.49107315 | T86: =1+C86 -> 1.0264444
A87: =A86+1 -> 1947 | B87: =TableDE1!R87/TableDE1!R86-1 -> 0.020253 | C87: 0.02189307 | D87: =TableDE1!D87/TableDE1!D86-1 -> 0.18406839 | E87: =E88/(1+B88) -> 60217.934 | F87: =E87*TableDE1!S87/TableDE1!R87 -> 41710.886 | H87: =H88/(1+D88) -> 188.29564 | I87: =1000000*H87/E87 -> 3126.903 | J87: =I87/I86-1 -> 0.1605635 | K87: 0.16220846 | L87: 0.098900797 | M87: =(TableDE1!D87/TableDE1!D86)/(1+D87)-1 -> 0 | N87: =(TableDE1!R87/TableDE1!R86)/(1+B87)-1 -> 0 | R87: =1+K87 -> 1.1622085 | S87: =1+L87 -> 1.0989008 | T87: =1+C87 -> 1.0218931
A88: =A87+1 -> 1948 | B88: =TableDE1!R88/TableDE1!R87-1 -> 0.026808368 | C88: 0.01817109 | D88: =TableDE1!D88/TableDE1!D87-1 -> 0.18802821 | E88: =E89/(1+B89) -> 61832.279 | F88: =E88*TableDE1!S88/TableDE1!R88 -> 42835.886 | H88: =H89/(1+D89) -> 223.70053 | I88: =1000000*H88/E88 -> 3617.8601 | J88: =I88/I87-1 -> 0.15701064 | K88: 0.16982387 | L88: 0.16322304 | M88: =(TableDE1!D88/TableDE1!D87)/(1+D88)-1 -> 0 | N88: =(TableDE1!R88/TableDE1!R87)/(1+B88)-1 -> 0 | R88: =1+K88 -> 1.1698239 | S88: =1+L88 -> 1.163223 | T88: =1+C88 -> 1.0181711
A89: 1949 | B89: =TableDE1!R89/TableDE1!R88-1 -> 0.011220414 | C89: 0.010342522 | D89: =TableDE1!D89/TableDE1!D88-1 -> 0.20142275 | E89: =E90/(1+B90) -> 62526.062 | F89: =E89*TableDE1!S89/TableDE1!R89 -> 43323.398 | H89: =H90/(1+D90) -> 268.75891 | I89: =1000000*H89/E89 -> 4298.3501 | J89: =I89/I88-1 -> 0.18809187 | K89: 0.19105667 | L89: 0.15835971 | M89: =(TableDE1!D89/TableDE1!D88)/(1+D89)-1 -> 0 | N89: =(TableDE1!R89/TableDE1!R88)/(1+B89)-1 -> 0 | R89: =1+K89 -> 1.1910567 | S89: =1+L89 -> 1.1583597 | T89: =1+C89 -> 1.0103425
A90: 1950 | B90: =47081/46169-1 -> 0.019753514 | C90: 0.0056415114 | D90: =48140/42808-1 -> 0.12455616 | E90: =E91/(1+B91) -> 63761.172 | F90: =E90*TableDE1!S90/TableDE1!R90 -> 44314.014 | G90: =TableDE3b!E90*TableDE1!T90/TableDE1!R90 -> 26041.886 | H90: =H91/(1+D91) -> 302.23448 | I90: =1000000*H90/E90 -> 4740.1024 | J90: =I90/I89-1 -> 0.10277252 | K90: 0.073354908 | L90: 0.18230919 | M90: =(TableDE1!D90/TableDE1!D89)/(1+D90)-1 -> -0.16560019 | N90: =(TableDE1!R90/TableDE1!R89)/(1+B90)-1 -> -0.27576407 | R90: =1+K90 -> 1.0733549 | S90: =1+L90 -> 1.1823092 | T90: =1+C90 -> 1.0056415
A91: =A90+1 -> 1951 | B91: =TableDE1!R91/TableDE1!R90-1 -> 0.0088453399 | C91: 0.0073318485 | D91: =TableDE1!D91/TableDE1!D90-1 -> 0.097608465 | E91: =E92/(1+B92) -> 64325.161 | F91: =E91*TableDE1!S91/TableDE1!R91 -> 44841.07 | G91: =TableDE3b!E91*TableDE1!T91/TableDE1!R91 -> 26735.183 | H91: =H92/(1+D92) -> 331.73513 | I91: =1000000*H91/E91 -> 5157.1597 | J91: =I91/I90-1 -> 0.087984869 | K91: 0.086458658 | L91: 0.083724293 | M91: =(TableDE1!D91/TableDE1!D90)/(1+D91)-1 -> 0 | N91: =(TableDE1!R91/TableDE1!R90)/(1+B91)-1 -> 0 | R91: =1+K91 -> 1.0864587 | S91: =1+L91 -> 1.0837243 | T91: =1+C91 -> 1.0073318
A92: =A91+1 -> 1952 | B92: =TableDE1!R92/TableDE1!R91-1 -> 0.0088453399 | C92: 0.0039210822 | D92: =TableDE1!D92/TableDE1!D91-1 -> 0.091808454 | E92: =E93/(1+B93) -> 64894.139 | F92: =E92*TableDE1!S92/TableDE1!R92 -> 45373.982 | G92: =TableDE3b!E92*TableDE1!T92/TableDE1!R92 -> 27308.716 | H92: =H93/(1+D93) -> 362.19122 | I92: =1000000*H92/E92 -> 5581.2624 | J92: =I92/I91-1 -> 0.082235712 | K92: 0.084868527 | L92: 0.08245502 | M92: =(TableDE1!D92/TableDE1!D91)/(1+D92)-1 -> 0 | N92: =(TableDE1!R92/TableDE1!R91)/(1+B92)-1 -> 0 | R92: =1+K92 -> 1.0848685 | S92: =1+L92 -> 1.082455 | T92: =1+C92 -> 1.0039211
A93: =A92+1 -> 1953 | B93: =TableDE1!R93/TableDE1!R92-1 -> 0.0098646061 | C93: 0.0058468209 | D93: =TableDE1!D93/TableDE1!D92-1 -> 0.090761886 | E93: =E94/(1+B94) -> 65534.294 | F93: =E93*TableDE1!S93/TableDE1!R93 -> 45959.201 | G93: =TableDE3b!E93*TableDE1!T93/TableDE1!R93 -> 28043.265 | H93: =H94/(1+D94) -> 395.06438 | I93: =1000000*H93/E93 -> 6028.3609 | J93: =I93/I92-1 -> 0.080107056 | K93: 0.077780371 | L93: 0.077425083 | M93: =(TableDE1!D93/TableDE1!D92)/(1+D93)-1 -> 0 | N93: =(TableDE1!R93/TableDE1!R92)/(1+B93)-1 -> 0 | R93: =1+K93 -> 1.0777804 | S93: =1+L93 -> 1.0774251 | T93: =1+C93 -> 1.0058468
A94: =A93+1 -> 1954 | B94: =TableDE1!R94/TableDE1!R93-1 -> 0.010348206 | C94: 0.0045704949 | D94: =TableDE1!D94/TableDE1!D93-1 -> 0.074345895 | E94: =E95/(1+B95) -> 66212.457 | F94: =E94*TableDE1!S94/TableDE1!R94 -> 46573.842 | G94: =TableDE3b!E94*TableDE1!T94/TableDE1!R94 -> 28837.696 | H94: =H95/(1+D95) -> 424.43579 | I94: =1000000*H94/E94 -> 6410.2106 | J94: =I94/I93-1 -> 0.063342211 | K94: 0.065881805 | L94: 0.069664818 | M94: =(TableDE1!D94/TableDE1!D93)/(1+D94)-1 -> 0 | N94: =(TableDE1!R94/TableDE1!R93)/(1+B94)-1 -> 0 | R94: =1+K94 -> 1.0658818 | S94: =1+L94 -> 1.0696648 | T94: =1+C94 -> 1.0045705
A95: =A94+1 -> 1955 | B95: =TableDE1!R95/TableDE1!R94-1 -> 0.010094206 | C95: 0.0046873599 | D95: =TableDE1!D95/TableDE1!D94-1 -> 0.12272568 | E95: =E96/(1+B96) -> 66880.819 | F95: =E95*TableDE1!S95/TableDE1!R95 -> 47184.418 | G95: =TableDE3b!E95*TableDE1!T95/TableDE1!R95 -> 29940.85 | H95: =H96/(1+D96) -> 476.52496 | I95: =1000000*H95/E95 -> 7124.987 | J95: =I95/I94-1 -> 0.11150591 | K95: 0.10938121 | L95: 0.10485867 | M95: =(TableDE1!D95/TableDE1!D94)/(1+D95)-1 -> 0 | N95: =(TableDE1!R95/TableDE1!R94)/(1+B95)-1 -> 0 | R95: =1+K95 -> 1.1093812 | S95: =1+L95 -> 1.1048587 | T95: =1+C95 -> 1.0046874
A96: =A95+1 -> 1956 | B96: =TableDE1!R96/TableDE1!R95-1 -> 0.0037224899 | C96: 0.0057967441 | D96: =TableDE1!D96/TableDE1!D95-1 -> 0.074495317 | E96: =E97/(1+B97) -> 67129.782 | F96: =E96*TableDE1!S96/TableDE1!R96 -> 47501.034 | G96: =TableDE3b!E96*TableDE1!T96/TableDE1!R96 -> 30811.131 | H96: =H97/(1+D97) -> 512.02384 | I96: =1000000*H96/E96 -> 7627.3723 | J96: =I96/I95-1 -> 0.070510353 | K96: 0.063517642 | L96: 0.065493363 | M96: =(TableDE1!D96/TableDE1!D95)/(1+D96)-1 -> 0 | N96: =(TableDE1!R96/TableDE1!R95)/(1+B96)-1 -> 0 | R96: =1+K96 -> 1.0635176 | S96: =1+L96 -> 1.0654934 | T96: =1+C96 -> 1.0057967
A97: =A96+1 -> 1957 | B97: =TableDE1!R97/TableDE1!R96-1 -> 0.0051161689 | C97: 0.0058999454 | D97: =TableDE1!D97/TableDE1!D96-1 -> 0.056484747 | E97: =E98/(1+B98) -> 67473.229 | F97: =E97*TableDE1!S97/TableDE1!R97 -> 47885.751 | G97: =TableDE3b!E97*TableDE1!T97/TableDE1!R97 -> 31515.073 | H97: =H98/(1+D98) -> 540.94538 | I97: =1000000*H97/E97 -> 8017.1852 | J97: =I97/I96-1 -> 0.051107106 | K97: 0.046036187 | L97: 0.051092357 | M97: =(TableDE1!D97/TableDE1!D96)/(1+D97)-1 -> 0 | N97: =(TableDE1!R97/TableDE1!R96)/(1+B97)-1 -> 0 | R97: =1+K97 -> 1.0460362 | S97: =1+L97 -> 1.0510924 | T97: =1+C97 -> 1.0058999
A98: =A97+1 -> 1958 | B98: =TableDE1!R98/TableDE1!R97-1 -> 0.012844959 | C98: 0.0066052401 | D98: =TableDE1!D98/TableDE1!D97-1 -> 0.039120769 | E98: =E99/(1+B99) -> 68339.92 | F98: =E98*TableDE1!S98/TableDE1!R98 -> 48644.355 | G98: =TableDE3b!E98*TableDE1!T98/TableDE1!R98 -> 31797.183 | H98: =H99/(1+D99) -> 562.10758 | I98: =1000000*H98/E98 -> 8225.1717 | J98: =I98/I97-1 -> 0.025942578 | K98: 0.031238265 | L98: 0.037668378 | M98: =(TableDE1!D98/TableDE1!D97)/(1+D98)-1 -> 0 | N98: =(TableDE1!R98/TableDE1!R97)/(1+B98)-1 -> 0 | R98: =1+K98 -> 1.0312383 | S98: =1+L98 -> 1.0376684 | T98: =1+C98 -> 1.0066052
A99: =A98+1 -> 1959 | B99: =TableDE1!R99/TableDE1!R98-1 -> 0.010963969 | C99: 0.0073534687 | D99: =TableDE1!D99/TableDE1!D98-1 -> 0.076084572 | E99: =E100/(1+B100) -> 69089.197 | F99: =E99*TableDE1!S99/TableDE1!R99 -> 49322.778 | G99: =TableDE3b!E99*TableDE1!T99/TableDE1!R99 -> 32164.457 | H99: =H100/(1+D100) -> 604.87529 | I99: =1000000*H99/E99 -> 8754.9909 | J99: =I99/I98-1 -> 0.064414366 | K99: 0.066399452 | L99: 0.06530187 | M99: =(TableDE1!D99/TableDE1!D98)/(1+D99)-1 -> 0 | N99: =(TableDE1!R99/TableDE1!R98)/(1+B99)-1 -> 0 | R99: =1+K99 -> 1.0663995 | S99: =1+L99 -> 1.0653019 | T99: =1+C99 -> 1.0073535
A100: =A99+1 -> 1960 | B100: =TableDE1!R100/TableDE1!R99-1 -> 0.011266973 | C100: 0.0064850856 | D100: =TableDE1!D100/TableDE1!D99-1 -> 0.086916196 | E100: =E101/(1+B101) -> 69867.623 | F100: =E100*TableDE1!S100/TableDE1!R100 -> 50025.218 | G100: =TableDE3b!E100*TableDE1!T100/TableDE1!R100 -> 32733.998 | H100: =H101/(1+D101) -> 657.44875 | I100: =1000000*H100/E100 -> 9409.9201 | J100: =I100/I99-1 -> 0.074806381 | K100: 0.075774271 | L100: 0.073647419 | M100: =(TableDE1!D100/TableDE1!D99)/(1+D100)-1 -> 0 | N100: =(TableDE1!R100/TableDE1!R99)/(1+B100)-1 -> 0 | R100: =1+K100 -> 1.0757743 | S100: =1+L100 -> 1.0736474 | T100: =1+C100 -> 1.0064851
A101: =A100+1 -> 1961 | B101: =TableDE1!R101/TableDE1!R100-1 -> 0.01197719 | C101: 0.008861359 | D101: =TableDE1!D101/TableDE1!D100-1 -> 0.039883188 | E101: =E102/(1+B102) -> 70704.441 | F101: =E101*TableDE1!S101/TableDE1!R101 -> 50532.464 | G101: =TableDE3b!E101*TableDE1!T101/TableDE1!R101 -> 33196.126 | H101: =H102/(1+D102) -> 683.6699 | I101: =1000000*H101/E101 -> 9669.4054 | J101: =I101/I100-1 -> 0.027575718 | K101: 0.031340296 | L101: 0.032046681 | M101: =(TableDE1!D101/TableDE1!D100)/(1+D101)-1 -> 0 | N101: =(TableDE1!R101/TableDE1!R100)/(1+B101)-1 -> 0 | R101: =1+K101 -> 1.0313403 | S101: =1+L101 -> 1.0320467 | T101: =1+C101 -> 1.0088614
A102: =A101+1 -> 1962 | B102: =TableDE1!R102/TableDE1!R101-1 -> 0.011452468 | C102: 0.008423721 | D102: =TableDE1!D102/TableDE1!D101-1 -> 0.040805407 | E102: =E103/(1+B103) -> 71514.181 | F102: =E102*TableDE1!S102/TableDE1!R102 -> 51018.217 | G102: =TableDE3b!E102*TableDE1!T102/TableDE1!R102 -> 33318.233 | H102: =H103/(1+D103) -> 711.56733 | I102: =1000000*H102/E102 -> 9950.0172 | J102: =I102/I101-1 -> 0.029020583 | K102: 0.033676522 | L102: 0.033948184 | M102: =(TableDE1!D102/TableDE1!D101)/(1+D102)-1 -> 0 | N102: =(TableDE1!R102/TableDE1!R101)/(1+B102)-1 -> 0 | R102: =1+K102 -> 1.0336765 | S102: =1+L102 -> 1.0339482 | T102: =1+C102 -> 1.0084237
... A110: =A109+1 -> 1970 | B110: =TableDE1!R110/TableDE1!R109-1 -> 0.0044233233 | C110: 0.0082868004 | D110: =TableDE1!D110/TableDE1!D109-1 -> 0.047419195 | E110: =E111/(1+B111) -> 76765.69 | F110: =E110*TableDE1!S110/TableDE1!R110 -> 53966.28 | G110: =TableDE3b!E110*TableDE1!T110/TableDE1!R110 -> 33407.428 | H110: =H111/(1+D111) -> 987.97971 | I110: =1000000*H110/E110 -> 12870.069 | J110: =I110/I109-1 -> 0.042806525 | K110: 0.040859831 | L110: 0.03819644 | M110: =(TableDE1!D110/TableDE1!D109)/(1+D110)-1 -> 0 | N110: =(TableDE1!R110/TableDE1!R109)/(1+B110)-1 -> 0 | R110: =1+K110 -> 1.0408598 | S110: =1+L110 -> 1.0381964 | T110: =1+C110 -> 1.0082868
A111: 1971 | B111: =TableDE1!R111/TableDE1!R110-1 -> 0.0025198257 | C111: 0.0073479269 | D111: =TableDE1!D111/TableDE1!D110-1 -> 0.025907802 | E111: =E112/(1+B112) -> 76959.126 | F111: =E111*TableDE1!S111/TableDE1!R111 -> 54356.231 | G111: =TableDE3b!E111*TableDE1!T111/TableDE1!R111 -> 33559.457 | H111: =H112/(1+D112) -> 1013.5761 | I111: =1000000*H111/E111 -> 13170.317 | J111: =I111/I110-1 -> 0.023329191 | K111: 0.019127301 | L111: 0.02192274 | M111: =(TableDE1!D111/TableDE1!D110)/(1+D111)-1 -> 0 | N111: =(TableDE1!R111/TableDE1!R110)/(1+B111)-1 -> 0 | R111: =1+K111 -> 1.0191273 | S111: =1+L111 -> 1.0219227 | T111: =1+C111 -> 1.0073479
A112: 1972 | B112: =TableDE1!R112/TableDE1!R111-1 -> 0.0065974678 | C112: 0.0046248529 | D112: =TableDE1!D112/TableDE1!D111-1 -> 0.039978013 | E112: =E113/(1+B113) -> 77466.862 | F112: =E112*TableDE1!S112/TableDE1!R112 -> 54970.485 | G112: =TableDE3b!E112*TableDE1!T112/TableDE1!R112 -> 33744.153 | H112: =H113/(1+D113) -> 1054.0968 | I112: =1000000*H112/E112 -> 13607.068 | J112: =I112/I111-1 -> 0.033161762 | K112: 0.036360144 | L112: 0.036479965 | M112: =(TableDE1!D112/TableDE1!D111)/(1+D112)-1 -> 0 | N112: =(TableDE1!R112/TableDE1!R111)/(1+B112)-1 -> 0 | R112: =1+K112 -> 1.0363601 | S112: =1+L112 -> 1.03648 | T112: =1+C112 -> 1.0046249
A113: 1973 | B113: =TableDE1!R113/TableDE1!R112-1 -> 0.004856515 | C113: 0.0029616441 | D113: =TableDE1!D113/TableDE1!D112-1 -> 0.04839231 | E113: =E114/(1+B114) -> 77843.081 | F113: =E113*TableDE1!S113/TableDE1!R113 -> 55494.332 | G113: =TableDE3b!E113*TableDE1!T113/TableDE1!R113 -> 34151.239 | H113: =H114/(1+D114) -> 1105.107 | I113: =1000000*H113/E113 -> 14196.599 | J113: =I113/I112-1 -> 0.043325385 | K113: 0.043568142 | L113: 0.042297869 | M113: =(TableDE1!D113/TableDE1!D112)/(1+D113)-1 -> 0 | N113: =(TableDE1!R113/TableDE1!R112)/(1+B113)-1 -> 0 | R113: =1+K113 -> 1.0435681 | S113: =1+L113 -> 1.0422979 | T113: =1+C113 -> 1.0029616
A114: 1974 | B114: =TableDE1!R114/TableDE1!R113-1 -> 0.001469582 | C114: 0.00020160805 | D114: =TableDE1!D114/TableDE1!D113-1 -> 0.0034280216 | E114: =E115/(1+B115) -> 77957.477 | F114: =E114*TableDE1!S114/TableDE1!R114 -> 55833.145 | G114: =TableDE3b!E114*TableDE1!T114/TableDE1!R114 -> 33828.335 | H114: =H115/(1+D115) -> 1108.8954 | I114: =1000000*H114/E114 -> 14224.362 | J114: =I114/I113-1 -> 0.0019555658 | K114: 0.0014091889 | L114: 0.0080698093 | M114: =(TableDE1!D114/TableDE1!D113)/(1+D114)-1 -> 0 | N114: =(TableDE1!R114/TableDE1!R113)/(1+B114)-1 -> 0 | R114: =1+K114 -> 1.0014092 | S114: =1+L114 -> 1.0080698 | T114: =1+C114 -> 1.0002016
A115: 1975 | B115: =TableDE1!R115/TableDE1!R114-1 -> -0.0036806715 | C115: -0.0035940976 | D115: =TableDE1!D115/TableDE1!D114-1 -> -0.012171252 | E115: =E116/(1+B116) -> 77670.542 | F115: =E115*TableDE1!S115/TableDE1!R115 -> 55883.955 | G115: =TableDE3b!E115*TableDE1!T115/TableDE1!R115 -> 32978.983 | H115: =H116/(1+D116) -> 1095.3987 | I115: =1000000*H115/E115 -> 14103.142 | J115: =I115/I114-1 -> -0.0085219468 | K115: -0.010433967 | L115: -0.0018588967 | M115: =(TableDE1!D115/TableDE1!D114)/(1+D115)-1 -> 0 | N115: =(TableDE1!R115/TableDE1!R114)/(1+B115)-1 -> 0 | R115: =1+K115 -> 0.98956603 | S115: =1+L115 -> 0.9981411 | T115: =1+C115 -> 0.9964059
A116: 1976 | B116: =TableDE1!R116/TableDE1!R115-1 -> -0.004444325 | C116: -0.0048723522 | D116: =TableDE1!D116/TableDE1!D115-1 -> 0.052685911 | E116: =E117/(1+B117) -> 77325.348 | F116: =E116*TableDE1!S116/TableDE1!R116 -> 55890.762 | G116: =TableDE3b!E116*TableDE1!T116/TableDE1!R116 -> 32842.031 | H116: =H117/(1+D117) -> 1153.1108 | I116: =1000000*H116/E116 -> 14912.455 | J116: =I116/I115-1 -> 0.057385275 | K116: 0.058567371 | L116: 0.053422513 | M116: =(TableDE1!D116/TableDE1!D115)/(1+D116)-1 -> 0 | N116: =(TableDE1!R116/TableDE1!R115)/(1+B116)-1 -> 0 | R116: =1+K116 -> 1.0585674 | S116: =1+L116 -> 1.0534225 | T116: =1+C116 -> 0.99512765
A117: 1977 | B117: =TableDE1!R117/TableDE1!R116-1 -> -0.00237133 | C117: -0.0017648256 | D117: =TableDE1!D117/TableDE1!D116-1 -> 0.031491443 | E117: =E118/(1+B118) -> 77141.984 | F117: =E117*TableDE1!S117/TableDE1!R117 -> 56012.795 | G117: =TableDE3b!E117*TableDE1!T117/TableDE1!R117 -> 32916.161 | H117: =H118/(1+D118) -> 1189.4239 | I117: =1000000*H117/E117 -> 15418.633 | J117: =I117/I116-1 -> 0.033943264 | K117: 0.030560442 | L117: 0.03059445 | M117: =(TableDE1!D117/TableDE1!D116)/(1+D117)-1 -> 0 | N117: =(TableDE1!R117/TableDE1!R116)/(1+B117)-1 -> 0 | R117: =1+K117 -> 1.0305604 | S117: =1+L117 -> 1.0305945 | T117: =1+C117 -> 0.99823517
A118: 1978 | B118: =TableDE1!R118/TableDE1!R117-1 -> -0.00097995239 | C118: -0.0012115924 | D118: =TableDE1!D118/TableDE1!D117-1 -> 0.032419283 | E118: =E119/(1+B119) -> 77066.389 | F118: =E118*TableDE1!S118/TableDE1!R118 -> 56212.224 | G118: =TableDE3b!E118*TableDE1!T118/TableDE1!R118 -> 33241.578 | H118: =H119/(1+D119) -> 1227.9842 | I118: =1000000*H118/E118 -> 15934.108 | J118: =I118/I117-1 -> 0.033431997 | K118: 0.031302579 | L118: 0.02933142 | M118: =(TableDE1!D118/TableDE1!D117)/(1+D118)-1 -> 0 | N118: =(TableDE1!R118/TableDE1!R117)/(1+B118)-1 -> 0 | R118: =1+K118 -> 1.0313026 | S118: =1+L118 -> 1.0293314 | T118: =1+C118 -> 0.99878841
A119: 1979 | B119: =TableDE1!R119/TableDE1!R118-1 -> 0.00070590926 | C119: 0.00019493743 | D119: =TableDE1!D119/TableDE1!D118-1 -> 0.036578809 | E119: =E120/(1+B120) -> 77120.791 | F119: =E119*TableDE1!S119/TableDE1!R119 -> 56506.403 | G119: =TableDE3b!E119*TableDE1!T119/TableDE1!R119 -> 33883.618 | H119: =H120/(1+D120) -> 1272.9024 | I119: =1000000*H119/E119 -> 16505.308 | J119: =I119/I118-1 -> 0.035847594 | K119: 0.040431461 | L119: 0.039982759 | M119: =(TableDE1!D119/TableDE1!D118)/(1+D119)-1 -> 0 | N119: =(TableDE1!R119/TableDE1!R118)/(1+B119)-1 -> 0 | R119: =1+K119 -> 1.0404315 | S119: =1+L119 -> 1.0399828 | T119: =1+C119 -> 1.0001949
A120: 1980 | B120: =TableDE1!R120/TableDE1!R119-1 -> 0.0027393226 | C120: 0.0027741857 | D120: =TableDE1!D120/TableDE1!D119-1 -> 0.0084263523 | E120: =E121/(1+B121) -> 77332.05 | F120: =E120*TableDE1!S120/TableDE1!R120 -> 56916.389 | G120: =TableDE3b!E120*TableDE1!T120/TableDE1!R120 -> 34451.528 | H120: =H121/(1+D121) -> 1283.6283 | I120: =1000000*H120/E120 -> 16598.917 | J120: =I120/I119-1 -> 0.0056714936 | K120: 0.0074489498 | L120: 0.0086276791 | M120: =(TableDE1!D120/TableDE1!D119)/(1+D120)-1 -> 0 | N120: =(TableDE1!R120/TableDE1!R119)/(1+B120)-1 -> 0 | R120: =1+K120 -> 1.0074489 | S120: =1+L120 -> 1.0086277 | T120: =1+C120 -> 1.0027742
A121: 1981 | B121: =TableDE1!R121/TableDE1!R120-1 -> 0.002220577 | C121: 0.0013273152 | D121: =TableDE1!D121/TableDE1!D120-1 -> -0.0026344805 | E121: =E122/(1+B122) -> 77503.771 | F121: =E121*TableDE1!S121/TableDE1!R121 -> 57476.797 | G121: =TableDE3b!E121*TableDE1!T121/TableDE1!R121 -> 34492.99 | H121: =H122/(1+D122) -> 1280.2466 | I121: =1000000*H121/E121 -> 16518.507 | J121: =I121/I120-1 -> -0.0048443003 | K121: -0.00096252113 | L121: 0.0024491858 | M121: =(TableDE1!D121/TableDE1!D120)/(1+D121)-1 -> 0 | N121: =(TableDE1!R121/TableDE1!R120)/(1+B121)-1 -> 0 | R121: =1+K121 -> 0.99903748 | S121: =1+L121 -> 1.0024492 | T121: =1+C121 -> 1.0013273
A122: 1982 | B122: =TableDE1!R122/TableDE1!R121-1 -> -0.00090656906 | C122: -0.00084901079 | D122: =TableDE1!D122/TableDE1!D121-1 -> -0.0088389615 | E122: =E123/(1+B123) -> 77433.509 | F122: =E122*TableDE1!S122/TableDE1!R122 -> 57858.318 | G122: =TableDE3b!E122*TableDE1!T122/TableDE1!R122 -> 34226.625 | H122: =H123/(1+D123) -> 1268.9306 | I122: =1000000*H122/E122 -> 16387.357 | J122: =I122/I121-1 -> -0.0079395902 | K122: -0.0086357556 | L122: -0.0077009377 | M122: =(TableDE1!D122/TableDE1!D121)/(1+D122)-1 -> 0 | N122: =(TableDE1!R122/TableDE1!R121)/(1+B122)-1 -> 0 | R122: =1+K122 -> 0.99136424 | S122: =1+L122 -> 0.99229906 | T122: =1+C122 -> 0.99915099
... A130: 1990 | B130: =TableDE1!R130/TableDE1!R129-1 -> 0.016162739 | C130: 0.009351908 | D130: =TableDE1!D130/TableDE1!D129-1 -> 0.053343322 | E130: =E131/(1+B131) -> 79409.822 | F130: =E130*TableDE1!S130/TableDE1!R130 -> 62892.579 | G130: =TableDE3b!E130*TableDE1!T130/TableDE1!R130 -> 38207.021 | H130: =H131/(1+D131) -> 1615.7181 | I130: =1000000*H130/E130 -> 20346.577 | J130: =I130/I129-1 -> 0.036589201 | K130: 0.032726415 | L130: -0.038004063 | M130: =(TableDE1!D130/TableDE1!D129)/(1+D130)-1 -> 0 | N130: =(TableDE1!R130/TableDE1!R129)/(1+B130)-1 -> 0 | R130: =1+K130 -> 1.0327264 | S130: =1+L130 -> 0.96199594 | T130: =1+C130 -> 1.0093519
A131: 1991 | B131: 0.0076070421 | C131: 0.0076070421 | D131: =DataDE1!GE52 -> 0.051048427 | E131: =E132/(1+B132) -> 80013.895 | F131: =E131*TableDE1!S131/TableDE1!R131 -> 62650.88 | G131: =TableDE3b!E131*TableDE1!T131/TableDE1!R131 -> 38712 | H131: =H132/(1+D132) -> 1698.198 | I131: =1000000*H131/E131 -> 21223.788 | J131: =I131/I130-1 -> 0.04311342 | K131: 0.041451145 | L131: 0.045243607 | M131: =(TableDE1!D131/TableDE1!D130)/(1+D131)-1 -> 0.080562982 | N131: =(TableDE1!R131/TableDE1!R130)/(1+B131)-1 -> 0.25643792 | R131: =1+K131 -> 1.0414511 | S131: =1+L131 -> 1.0452436 | T131: =1+C131 -> 1.007607
A132: 1992 | B132: =TableDE1!R132/TableDE1!R131-1 -> 0.0076324555 | C132: 0.0076705107 | D132: =TableDE1!D132/TableDE1!D131-1 -> 0.015354022 | E132: =E133/(1+B133) -> 80624.598 | F132: =E132*TableDE1!S132/TableDE1!R132 -> 63169.373 | G132: =TableDE3b!E132*TableDE1!T132/TableDE1!R132 -> 38183 | H132: =H133/(1+D133) -> 1724.2721 | I132: =1000000*H132/E132 -> 21386.428 | J132: =I132/I131-1 -> 0.0076630782 | K132: 0.014588158 | L132: 0.014477112 | M132: =(TableDE1!D132/TableDE1!D131)/(1+D132)-1 -> 0 | N132: =(TableDE1!R132/TableDE1!R131)/(1+B132)-1 -> 0 | R132: =1+K132 -> 1.0145882 | S132: =1+L132 -> 1.0144771 | T132: =1+C132 -> 1.0076705
A133: 1993 | B133: =TableDE1!R133/TableDE1!R132-1 -> 0.0065955616 | C133: 0.0066317969 | D133: =TableDE1!D133/TableDE1!D132-1 -> -0.017636604 | E133: =E134/(1+B134) -> 81156.363 | F133: =E133*TableDE1!S133/TableDE1!R133 -> 63626.588 | G133: =TableDE3b!E133*TableDE1!T133/TableDE1!R133 -> 37695 | H133: =H134/(1+D134) -> 1693.8618 | I133: =1000000*H133/E133 -> 20871.584 | J133: =I133/I132-1 -> -0.024073388 | K133: -0.0146538 | L133: -0.014557259 | M133: =(TableDE1!D133/TableDE1!D132)/(1+D133)-1 -> 0 | N133: =(TableDE1!R133/TableDE1!R132)/(1+B133)-1 -> 0 | R133: =1+K133 -> 0.9853462 | S133: =1+L133 -> 0.98544274 | T133: =1+C133 -> 1.0066318
A134: 1994 | B134: =TableDE1!R134/TableDE1!R133-1 -> 0.0034745951 | C134: 0.0034744744 | D134: =TableDE1!D134/TableDE1!D133-1 -> 0.017889844 | E134: =E135/(1+B135) -> 81438.348 | F134: =E134*TableDE1!S134/TableDE1!R134 -> 63888.384 | G134: =TableDE3b!E134*TableDE1!T134/TableDE1!R134 -> 37667 | H134: =H135/(1+D135) -> 1724.1647 | I134: =1000000*H134/E134 -> 21171.411 | J134: =I134/I133-1 -> 0.014365335 | K134: 0.02309669 | L134: 0.023016719 | M134: =(TableDE1!D134/TableDE1!D133)/(1+D134)-1 -> 0 | N134: =(TableDE1!R134/TableDE1!R133)/(1+B134)-1 -> 0 | R134: =1+K134 -> 1.0230967 | S134: =1+L134 -> 1.0230167 | T134: =1+C134 -> 1.0034745
A135: 1995 | B135: =TableDE1!R135/TableDE1!R134-1 -> 0.0029433677 | C135: 0.0029422153 | D135: =TableDE1!D135/TableDE1!D134-1 -> 0.013796178 | E135: =E136/(1+B136) -> 81678.051 | F135: =E135*TableDE1!S135/TableDE1!R135 -> 64117.27 | G135: =TableDE3b!E135*TableDE1!T135/TableDE1!R135 -> 37802 | H135: =H136/(1+D136) -> 1747.9516 | I135: =1000000*H135/E135 -> 21400.506 | J135: =I135/I134-1 -> 0.010820961 | K135: 0.015963929 | L135: 0.015917098 | M135: =(TableDE1!D135/TableDE1!D134)/(1+D135)-1 -> 0 | N135: =(TableDE1!R135/TableDE1!R134)/(1+B135)-1 -> 0 | R135: =1+K135 -> 1.0159639 | S135: =1+L135 -> 1.0159171 | T135: =1+C135 -> 1.0029422
A136: 1996 | B136: =TableDE1!R136/TableDE1!R135-1 -> 0.0028989367 | C136: 0.002902073 | D136: =TableDE1!D136/TableDE1!D135-1 -> 0.0091181623 | E136: =E137/(1+B137) -> 81914.83 | F136: =E136*TableDE1!S136/TableDE1!R136 -> 64321.227 | G136: =TableDE3b!E136*TableDE1!T136/TableDE1!R136 -> 37772 | H136: =H137/(1+D137) -> 1763.8897 | I136: =1000000*H136/E136 -> 21533.216 | J136: =I136/I135-1 -> 0.0062012486 | K136: 0.0070382849 | L136: 0.0070179184 | M136: =(TableDE1!D136/TableDE1!D135)/(1+D136)-1 -> 0 | N136: =(TableDE1!R136/TableDE1!R135)/(1+B136)-1 -> 0 | R136: =1+K136 -> 1.0070383 | S136: =1+L136 -> 1.0070179 | T136: =1+C136 -> 1.0029021
A137: 1997 | B137: =TableDE1!R137/TableDE1!R136-1 -> 0.0014642037 | C137: 0.0014703263 | D137: =TableDE1!D137/TableDE1!D136-1 -> 0.014468743 | E137: =E138/(1+B138) -> 82034.77 | F137: =E137*TableDE1!S137/TableDE1!R137 -> 64433.519 | G137: =TableDE3b!E137*TableDE1!T137/TableDE1!R137 -> 37716 | H137: =H138/(1+D138) -> 1789.411 | I137: =1000000*H137/E137 -> 21812.836 | J137: =I137/I136-1 -> 0.012985525 | K137: 0.016574293 | L137: 0.016549986 | M137: =(TableDE1!D137/TableDE1!D136)/(1+D137)-1 -> 0 | N137: =(TableDE1!R137/TableDE1!R136)/(1+B137)-1 -> 0 | R137: =1+K137 -> 1.0165743 | S137: =1+L137 -> 1.01655 | T137: =1+C137 -> 1.0014703
A138: 1998 | B138: =TableDE1!R138/TableDE1!R137-1 -> 0.00015145407 | C138: 0.0001536256 | D138: =TableDE1!D138/TableDE1!D137-1 -> 0.015171128 | E138: =E139/(1+B139) -> 82047.195 | F138: =E138*TableDE1!S138/TableDE1!R138 -> 64461.392 | G138: =TableDE3b!E138*TableDE1!T138/TableDE1!R138 -> 38148 | H138: =H139/(1+D139) -> 1816.5584 | I138: =1000000*H138/E138 -> 22140.408 | J138: =I138/I137-1 -> 0.015017399 | K138: 0.020149307 | L138: 0.018090469 | M138: =(TableDE1!D138/TableDE1!D137)/(1+D138)-1 -> 0 | N138: =(TableDE1!R138/TableDE1!R137)/(1+B138)-1 -> 0 | R138: =1+K138 -> 1.0201493 | S138: =1+L138 -> 1.0180905 | T138: =1+C138 -> 1.0001536
A139: =A138+1 -> 1999 | B139: =TableDE1!R139/TableDE1!R138-1 -> 0.00064655471 | C139: 0.00062306403 | D139: =TableDE1!D139/TableDE1!D138-1 -> 0.017178634 | E139: =E140/(1+B140) -> 82100.243 | F139: =E139*TableDE1!S139/TableDE1!R139 -> 64583.615 | G139: =TableDE3b!E139*TableDE1!T139/TableDE1!R139 -> 38721 | H139: =H140/(1+D140) -> 1847.7644 | I139: =1000000*H139/E139 -> 22506.199 | J139: =I139/I138-1 -> 0.016521398 | K139: 0.019486433 | L139: 0.019477797 | M139: =(TableDE1!D139/TableDE1!D138)/(1+D139)-1 -> 0 | N139: =(TableDE1!R139/TableDE1!R138)/(1+B139)-1 -> 0 | R139: =1+K139 -> 1.0194864 | S139: =1+L139 -> 1.0194778 | T139: =1+C139 -> 1.0006231
A140: =A139+1 -> 2000 | B140: =TableDE1!R140/TableDE1!R139-1 -> 0.0013551665 | C140: 0.0013783894 | D140: =TableDE1!D140/TableDE1!D139-1 -> 0.029123265 | E140: =E141/(1+B141) -> 82211.503 | F140: =E140*TableDE1!S140/TableDE1!R140 -> 64864.875 | G140: =TableDE3b!E140*TableDE1!T140/TableDE1!R140 -> 39382 | H140: =H141/(1+D141) -> 1901.5773 | I140: =1000000*H140/E140 -> 23130.307 | J140: =I140/I139-1 -> 0.027730519 | K140: 0.030719866 | L140: 0.030656769 | M140: =(TableDE1!D140/TableDE1!D139)/(1+D140)-1 -> 0 | N140: =(TableDE1!R140/TableDE1!R139)/(1+B140)-1 -> 0 | R140: =1+K140 -> 1.0307199 | S140: =1+L140 -> 1.0306568 | T140: =1+C140 -> 1.0013784
A141: =A140+1 -> 2001 | B141: =TableDE1!R141/TableDE1!R140-1 -> 0.0016836148 | C141: 0.0011271974 | D141: =TableDE1!D141/TableDE1!D140-1 -> 0.013498576 | E141: =E142/(1+B142) -> 82349.915 | F141: =E141*TableDE1!S141/TableDE1!R141 -> 65138.783 | G141: =TableDE3b!E141*TableDE1!T141/TableDE1!R141 -> 39485 | H141: =H142/(1+D142) -> 1927.2459 | I141: =1000000*H141/E141 -> 23403.131 | J141: =I141/I140-1 -> 0.011795103 | K141: 0.011272803 | L141: 0.011253112 | M141: =(TableDE1!D141/TableDE1!D140)/(1+D141)-1 -> 0 | N141: =(TableDE1!R141/TableDE1!R140)/(1+B141)-1 -> 0 | R141: =1+K141 -> 1.0112728 | S141: =1+L141 -> 1.0112531 | T141: =1+C141 -> 1.0011272
A142: =A141+1 -> 2002 | B142: =TableDE1!R142/TableDE1!R141-1 -> 0.0016827583 | C142: 0.00085220625 | D142: =TableDE1!D142/TableDE1!D141-1 -> -0.0029938047 | E142: =E143/(1+B143) -> 82488.49 | F142: =E142*TableDE1!S142/TableDE1!R142 -> 65413.373 | G142: =TableDE3b!E142*TableDE1!T142/TableDE1!R142 -> 39257 | H142: =H143/(1+D143) -> 1921.4761 | I142: =1000000*H142/E142 -> 23293.869 | J142: =I142/I141-1 -> -0.0046687067 | K142: -0.00085220625 | L142: -0.00085148062 | M142: =(TableDE1!D142/TableDE1!D141)/(1+D142)-1 -> 0 | N142: =(TableDE1!R142/TableDE1!R141)/(1+B142)-1 -> 0 | R142: =1+K142 -> 0.99914779 | S142: =1+L142 -> 0.99914852 | T142: =1+C142 -> 1.0008522
A143: =A142+1 -> 2003 | B143: =TableDE1!R143/TableDE1!R142-1 -> 0.00055384091 | C143: 0.00057868381 | D143: =TableDE1!D143/TableDE1!D142-1 -> 0.0024790852 | E143: =E144/(1+B144) -> 82534.175 | F143: =E143*TableDE1!S143/TableDE1!R143 -> 65614.67 | G143: =TableDE3b!E143*TableDE1!T143/TableDE1!R143 -> 38918 | H143: =H144/(1+D144) -> 1926.2396 | I143: =1000000*H143/E143 -> 23338.691 | J143: =I143/I142-1 -> 0.0019241786 | K143: -0.0024554124 | L143: -0.0027588852 | M143: =(TableDE1!D143/TableDE1!D142)/(1+D143)-1 -> 0 | N143: =(TableDE1!R143/TableDE1!R142)/(1+B143)-1 -> 0 | R143: =1+K143 -> 0.99754459 | S143: =1+L143 -> 0.99724111 | T143: =1+C143 -> 1.0005787
A144: =A143+1 -> 2004 | B144: =TableDE1!R144/TableDE1!R143-1 -> -0.00021706766 | C144: 0.00031897493 | D144: =TableDE1!D144/TableDE1!D143-1 -> 0.033142504 | E144: =E145/(1+B145) -> 82516.26 | F144: =E144*TableDE1!S144/TableDE1!R144 -> 65765.459 | G144: =TableDE3b!E144*TableDE1!T144/TableDE1!R144 -> 39034 | H144: =H145/(1+D145) -> 1990.08 | I144: =1000000*H144/E144 -> 24117.428 | J144: =I144/I143-1 -> 0.033366814 | K144: 0.0121501 | L144: 0.010273609 | M144: =(TableDE1!D144/TableDE1!D143)/(1+D144)-1 -> 0 | N144: =(TableDE1!R144/TableDE1!R143)/(1+B144)-1 -> 0 | R144: =1+K144 -> 1.0121501 | S144: =1+L144 -> 1.0102736 | T144: =1+C144 -> 1.000319
A145: =A144+1 -> 2005 | B145: =TableDE1!R145/TableDE1!R144-1 -> -0.00056762146 | C145: 8.2269119e-05 | D145: =TableDE1!D145/TableDE1!D144-1 -> 0.0096444477 | E145: =E146/(1+B146) -> 82469.422 | F145: =E145*TableDE1!S145/TableDE1!R145 -> 65975.538 | G145: =TableDE3b!E145*TableDE1!T145/TableDE1!R145 -> 38976 | H145: =H146/(1+D146) -> 2009.2732 | I145: =1000000*H145/E145 -> 24363.857 | J145: =I145/I144-1 -> 0.010217869 | K145: 0.0090222008 | L145: 0.0069170719 | M145: =(TableDE1!D145/TableDE1!D144)/(1+D145)-1 -> 0 | N145: =(TableDE1!R145/TableDE1!R144)/(1+B145)-1 -> 0 | R145: =1+K145 -> 1.0090222 | S145: =1+L145 -> 1.0069171 | T145: =1+C145 -> 1.0000823
...

Sheet TableDE3c
B1: Back to index
A3: Table DE.3c: Economic growth, population growth and price deflators in Germany (fixed boundaries), 1870-2010
B5: [1] | C5: [2] | D5: [3] | E5: [4] | F5: [5] | G5: [6] | H5: [7] | I5: [8] | J5: [9] | K5: [10] | L5: [11]
B6: Boundaries: Reunified Germany (pre-1991 evolution based on growth rates in the boundaries of the time, and specific adjustments made for border change)
B7: Real growth rate of national income (GDP deflator) | C7: Real growth rate of private wealth (GDP deflator) | D7: Real growth rate of per-capita national income (GDP deflator) | E7: Real growth rate of per-capita national income (CPI) | F7: Real growth rate of per-employed national income (GDP deflator) | G7: Population growth rate | H7: Adult population growth rate (20-yr+) | I7: Employed population growth rate | J7: GDP price inflation | K7: Consumer price inflation | L7: Personal consumption expenditure inflation | O7: Memo: real growth rate of per capita GDP (Barro-Ursua) | P7: Memo: real growth rate of per capita GDP (Maddison) | Q7: Memo: real growth rate of population (Maddison)
A8: 1870-2010 | B8: =(((1+B11)^40)*((1+B14)^100))^(1/140)-1 -> 0.024717261 | C8: =(((1+C11)^40)*((1+C14)^100))^(1/140)-1 -> 0.020801319 | D8: =(1+B8)/(1+G8)-1 -> 0.017246986 | E8: =(1+D8)*(1+J8)/(1+K8)-1 -> 0.017328338 | F8: =(1+D8)*(1+G8)/(1+I8)-1 -> 0.016286902 | G8: =(((1+G11)^40)*((1+G14)^100))^(1/140)-1 -> 0.0073436194 | H8: =(((1+H11)^40)*((1+H14)^100))^(1/140)-1 -> 0.0099858818 | I8: =(((1+I11)^40)*((1+I14)^100))^(1/140)-1 -> 0.0082952553 | J8: =(((1+J11)^40)*((1+J14)^100))^(1/140)-1 -> 0.019236402 | K8: =(((1+K11)^40)*((1+K14)^100))^(1/140)-1 -> 0.019154897 | O8: =PRODUCT(TableDE3b!R11:R150)^(1/140)-1 -> 0.016274347 | P8: =PRODUCT(TableDE3b!S11:S150)^(1/140)-1 -> 0.017401978 | Q8: =PRODUCT(TableDE3b!T11:T150)^(1/140)-1 -> 0.0068098176
A11: 1870-1910 | B11: =(TableDE3b!H50/TableDE3b!H10)^(1/40)-1 -> 0.025125197 | C11: =(TableDE5a!C50/TableDE5a!C10)^(1/40)-1 -> 0.02138811 | D11: =(1+B11)/(1+G11)-1 -> 0.013417583 | E11: =(1+D11)*(1+J11)/(1+K11)-1 -> 0.0101636 | F11: =(1+D11)*(1+G11)/(1+I11)-1 -> 0.012213933 | G11: =(TableDE3b!E50/TableDE3b!E10)^(1/40)-1 -> 0.011552606 | H11: =(TableDE3b!F50/TableDE3b!F10)^(1/40)-1 -> 0.011686606 | I11: =(TableDE3b!G50/TableDE3b!G10)^(1/40)-1 -> 0.012755469 | J11: =(TableDE15a!C49/TableDE15a!C9)^(1/40)-1 -> 0.0058343466 | K11: =(TableDE15a!B49/TableDE15a!B9)^(1/40)-1 -> 0.0090743844 | O11: =PRODUCT(TableDE3b!R11:R50)^(1/40)-1 -> 0.013979505 | P11: =PRODUCT(TableDE3b!S11:S50)^(1/40)-1 -> 0.015087504 | Q11: =PRODUCT(TableDE3b!T11:T50)^(1/40)-1 -> 0.011865455
A14: 1910-2010 | B14: =(((1+B17)^40)*((1+B20)^60))^(1/100)-1 -> 0.024554132 | C14: =(((1+C17)^40)*((1+C20)^60))^(1/100)-1 -> 0.020566697 | D14: =(1+B14)/(1+G14)-1 -> 0.018782796 | E14: =(1+D14)*(1+J14)/(1+K14)-1 -> 0.020208442 | F14: =(1+D14)*(1+G14)/(1+I14)-1 -> 0.017920674 | G14: =(((1+G17)^40)*((1+G20)^60))^(1/100)-1 -> 0.0056649328 | H14: =(((1+H17)^40)*((1+H20)^60))^(1/100)-1 -> 0.0093063931 | I14: =(((1+I17)^40)*((1+I20)^60))^(1/100)-1 -> 0.0065166746 | J14: =(TableDE15a!C149/TableDE15a!C49)^(1/100)-1 -> 0.024647092 | K14: =(TableDE15a!B149/TableDE15a!B49)^(1/100)-1 -> 0.023215243 | O14: =PRODUCT(TableDE3b!R51:R150)^(1/100)-1 -> 0.017193737 | P14: =PRODUCT(TableDE3b!S51:S150)^(1/100)-1 -> 0.018329245 | Q14: =PRODUCT(TableDE3b!T51:T150)^(1/100)-1 -> 0.0047946424
A17: 1910-1950 | B17: =(TableDE3b!H90/TableDE3b!H50)^(1/40)-1 -> 0.011707167 | C17: =(TableDE5a!C90/TableDE5a!C50)^(1/40)-1 -> -0.018469618 | D17: =(1+B17)/(1+G17)-1 -> 0.0037450709 | E17: =(1+D17)*(1+J17)/(1+K17)-1 -> 0.0042612238 | F17: =(1+D17)*(1+G17)/(1+I17)-1 -> 0.0064939193 | G17: =(TableDE3b!E90/TableDE3b!E50)^(1/40)-1 -> 0.0079323891 | H17: =(TableDE3b!F90/TableDE3b!F50)^(1/40)-1 -> 0.013023358 | I17: =(TableDE3b!G90/TableDE3b!G50)^(1/40)-1 -> 0.0051796121 | J17: =(TableDE15a!C89/TableDE15a!C49)^(1/40)-1 -> 0.018367226 | K17: =(TableDE15a!B89/TableDE15a!B49)^(1/40)-1 -> 0.017843823 | O17: =PRODUCT(TableDE3b!R51:R90)^(1/40)-1 -> -0.00056247216 | P17: =PRODUCT(TableDE3b!S51:S90)^(1/40)-1 -> 0.0037019813 | Q17: =PRODUCT(TableDE3b!T51:T90)^(1/40)-1 -> 0.0073799963
A20: 1950-2010 | B20: =(TableDE3b!H150/TableDE3b!H90)^(1/60)-1 -> 0.033209278 | C20: =(TableDE5a!C150/TableDE5a!C90)^(1/60)-1 -> 0.04744965 | D20: =(1+B20)/(1+G20)-1 -> 0.028932899 | E20: =(1+D20)*(1+J20)/(1+K20)-1 -> 0.03098036 | F20: =(1+D20)*(1+G20)/(1+I20)-1 -> 0.025610491 | G20: =(TableDE3b!E150/TableDE3b!E90)^(1/60)-1 -> 0.0041561298 | H20: =(TableDE3b!F150/TableDE3b!F90)^(1/60)-1 -> 0.0068359966 | I20: =(TableDE3b!G150/TableDE3b!G90)^(1/60)-1 -> 0.0074090375 | J20: =(TableDE15a!C149/TableDE15a!C89)^(1/60)-1 -> 0.028855168 | K20: =(TableDE15a!B149/TableDE15a!B89)^(1/60)-1 -> 0.026811928 | L20: =(TableDE15a!D149/TableDE15a!D89)^(1/60)-1 -> 0.025784365 | O20: =PRODUCT(TableDE3b!R91:R150)^(1/60)-1 -> 0.029206121 | P20: =PRODUCT(TableDE3b!S91:S150)^(1/60)-1 -> 0.02819899 | Q20: =PRODUCT(TableDE3b!T91:T150)^(1/60)-1 -> 0.0030747603
A23: 1950-1980 | B23: =(TableDE3b!H120/TableDE3b!H90)^(1/30)-1 -> 0.049389004 | C23: =(TableDE5a!C120/TableDE5a!C90)^(1/30)-1 -> 0.061145219 | D23: =(1+B23)/(1+G23)-1 -> 0.042660853 | E23: =(1+D23)*(1+J23)/(1+K23)-1 -> 0.05033955 | F23: =(1+D23)*(1+G23)/(1+I23)-1 -> 0.03964557 | G23: =(TableDE3b!E120/TableDE3b!E90)^(1/30)-1 -> 0.0064528662 | H23: =(TableDE3b!F120/TableDE3b!F90)^(1/30)-1 -> 0.0083776424 | I23: =(TableDE3b!G120/TableDE3b!G90)^(1/30)-1 -> 0.0093718805 | J23: =(TableDE15a!C119/TableDE15a!C89)^(1/30)-1 -> 0.039337231 | K23: =(TableDE15a!B119/TableDE15a!B89)^(1/30)-1 -> 0.031738968 | L23: =(TableDE15a!D119/TableDE15a!D89)^(1/30)-1 -> 0.032030226 | O23: =PRODUCT(TableDE3b!R91:R120)^(1/30)-1 -> 0.043529085 | P23: =PRODUCT(TableDE3b!S91:S120)^(1/30)-1 -> 0.043976368 | Q23: =PRODUCT(TableDE3b!T91:T120)^(1/30)-1 -> 0.0045275463
A26: 1980-2010 | B26: =(TableDE3b!H150/TableDE3b!H120)^(1/30)-1 -> 0.017279015 | C26: =(TableDE5a!C150/TableDE5a!C120)^(1/30)-1 -> 0.033930843 | D26: =(1+B26)/(1+G26)-1 -> 0.015385692 | E26: =(1+D26)*(1+J26)/(1+K26)-1 -> 0.011977987 | F26: =(1+D26)*(1+G26)/(1+I26)-1 -> 0.011764885 | G26: =(TableDE3b!E150/TableDE3b!E120)^(1/30)-1 -> 0.0018646345 | H26: =(TableDE3b!F150/TableDE3b!F120)^(1/30)-1 -> 0.0052967077 | I26: =(TableDE3b!G150/TableDE3b!G120)^(1/30)-1 -> 0.0054500115 | J26: =(TableDE15a!C149/TableDE15a!C119)^(1/30)-1 -> 0.01847882 | K26: =(TableDE15a!B149/TableDE15a!B119)^(1/30)-1 -> 0.021908416 | L26: =(TableDE15a!D149/TableDE15a!D119)^(1/30)-1 -> 0.019576305 | O26: =PRODUCT(TableDE3b!R121:R150)^(1/30)-1 -> 0.015079747 | P26: =PRODUCT(TableDE3b!S121:S150)^(1/30)-1 -> 0.012660053 | Q26: =PRODUCT(TableDE3b!T121:T150)^(1/30)-1 -> 0.0016240755
A29: 1950-1970 | B29: =(TableDE3b!H110/TableDE3b!H90)^(1/20)-1 -> 0.061011767 | C29: =(TableDE5a!C110/TableDE5a!C90)^(1/20)-1 -> 0.072596948 | D29: =(1+B29)/(1+G29)-1 -> 0.05121042 | E29: =(1+D29)*(1+J29)/(1+K29)-1 -> 0.062702641 | F29: =(1+D29)*(1+G29)/(1+I29)-1 -> 0.047880286 | G29: =(TableDE3b!E110/TableDE3b!E90)^(1/20)-1 -> 0.0093238681 | H29: =(TableDE3b!F110/TableDE3b!F90)^(1/20)-1 -> 0.0099016213 | I29: =(TableDE3b!G110/TableDE3b!G90)^(1/20)-1 -> 0.01253147 | J29: =(TableDE15a!C109/TableDE15a!C89)^(1/20)-1 -> 0.033573108 | K29: =(TableDE15a!B109/TableDE15a!B89)^(1/20)-1 -> 0.022395898 | L29: =(TableDE15a!D109/TableDE15a!D89)^(1/20)-1 -> 0.023001325 | O29: =PRODUCT(TableDE3b!R91:R110)^(1/20)-1 -> 0.05259255 | P29: =PRODUCT(TableDE3b!S91:S110)^(1/20)-1 -> 0.052696552 | Q29: =PRODUCT(TableDE3b!T91:T110)^(1/20)-1 -> 0.0064670217
A32: 1970-2010 | B32: =(TableDE3b!H150/TableDE3b!H110)^(1/40)-1 -> 0.019582437 | C32: =(TableDE5a!C150/TableDE5a!C110)^(1/40)-1 -> 0.035097968 | D32: =(1+B32)/(1+G32)-1 -> 0.017971811 | E32: =(1+D32)*(1+J32)/(1+K32)-1 -> 0.015476105 | F32: =(1+D32)*(1+G32)/(1+I32)-1 -> 0.014653709 | G32: =(TableDE3b!E150/TableDE3b!E110)^(1/40)-1 -> 0.0015821912 | H32: =(TableDE3b!F150/TableDE3b!F110)^(1/40)-1 -> 0.0053066757 | I32: =(TableDE3b!G150/TableDE3b!G110)^(1/40)-1 -> 0.0048575472 | J32: =(TableDE15a!C149/TableDE15a!C109)^(1/40)-1 -> 0.02650428 | K32: =(TableDE15a!B149/TableDE15a!B109)^(1/40)-1 -> 0.02902709 | L32: =(TableDE15a!D149/TableDE15a!D109)^(1/40)-1 -> 0.027178723 | O32: =PRODUCT(TableDE3b!R111:R150)^(1/40)-1 -> 0.017708483 | P32: =PRODUCT(TableDE3b!S111:S150)^(1/40)-1 -> 0.016164829 | Q32: =PRODUCT(TableDE3b!T111:T150)^(1/40)-1 -> 0.0013829196
A35: 1970-1990 | B35: =(TableDE3b!H130/TableDE3b!H110)^(1/20)-1 -> 0.024898549 | C35: =(TableDE5a!C130/TableDE5a!C110)^(1/20)-1 -> 0.038573882 | D35: =(1+B35)/(1+G35)-1 -> 0.023164645 | E35: =(1+D35)*(1+J35)/(1+K35)-1 -> 0.024255107 | F35: =(1+D35)*(1+G35)/(1+I35)-1 -> 0.018042412 | G35: =(TableDE3b!E130/TableDE3b!E110)^(1/20)-1 -> 0.0016946474 | H35: =(TableDE3b!F130/TableDE3b!F110)^(1/20)-1 -> 0.0076828005 | I35: =(TableDE3b!G130/TableDE3b!G110)^(1/20)-1 -> 0.0067346273 | J35: =(TableDE15a!C129/TableDE15a!C109)^(1/20)-1 -> 0.039355757 | K35: =(TableDE15a!B129/TableDE15a!B109)^(1/20)-1 -> 0.038249219 | L35: =(TableDE15a!D129/TableDE15a!D109)^(1/20)-1 -> 0.037798927 | O35: =PRODUCT(TableDE3b!R111:R130)^(1/20)-1 -> 0.022452443 | P35: =PRODUCT(TableDE3b!S111:S130)^(1/20)-1 -> 0.019434819 | Q35: =PRODUCT(TableDE3b!T111:T130)^(1/20)-1 -> 0.0010168368
A38: 1990-2010 | B38: =(TableDE3b!H150/TableDE3b!H130)^(1/20)-1 -> 0.0142939 | C38: =(TableDE5a!C150/TableDE5a!C130)^(1/20)-1 -> 0.031633686 | D38: =(1+B38)/(1+G38)-1 -> 0.012805332 | E38: =(1+D38)*(1+J38)/(1+K38)-1 -> 0.0067723483 | F38: =(1+D38)*(1+G38)/(1+I38)-1 -> 0.011276285 | G38: =(TableDE3b!E150/TableDE3b!E130)^(1/20)-1 -> 0.0014697476 | H38: =(TableDE3b!F150/TableDE3b!F130)^(1/20)-1 -> 0.0029361538 | I38: =(TableDE3b!G150/TableDE3b!G130)^(1/20)-1 -> 0.0029839669 | J38: =(TableDE15a!C149/TableDE15a!C129)^(1/20)-1 -> 0.01381171 | K38: =(TableDE15a!B149/TableDE15a!B129)^(1/20)-1 -> 0.019886876 | L38: =(TableDE15a!D149/TableDE15a!D129)^(1/20)-1 -> 0.016667199 | O38: =PRODUCT(TableDE3b!R131:R150)^(1/20)-1 -> 0.012986534 | P38: =PRODUCT(TableDE3b!S131:S150)^(1/20)-1 -> 0.012905328 | Q38: =PRODUCT(TableDE3b!T131:T150)^(1/20)-1 -> 0.0017491363
A41: 1950-1960 | B41: =(TableDE3b!H100/TableDE3b!H90)^(1/10)-1 -> 0.080816059 | C41: =(TableDE5a!C100/TableDE5a!C90)^(1/10)-1 -> 0.075442167 | D41: =(1+B41)/(1+G41)-1 -> 0.070976203 | E41: =(1+D41)*(1+J41)/(1+K41)-1 -> 0.082234285 | F41: =(1+D41)*(1+G41)/(1+I41)-1 -> 0.05637746 | G41: =(TableDE3b!E100/TableDE3b!E90)^(1/10)-1 -> 0.0091877442 | H41: =(TableDE3b!F100/TableDE3b!F90)^(1/10)-1 -> 0.012196403 | I41: =(TableDE3b!G100/TableDE3b!G90)^(1/10)-1 -> 0.023134343 | J41: =(TableDE15a!C99/TableDE15a!C89)^(1/10)-1 -> 0.029493921 | K41: =(TableDE15a!B99/TableDE15a!B89)^(1/10)-1 -> 0.018784478 | L41: =(TableDE15a!D99/TableDE15a!D89)^(1/10)-1 -> 0.019120155 | O41: =PRODUCT(TableDE3b!R91:R100)^(1/10)-1 -> 0.07053333 | P41: =PRODUCT(TableDE3b!S91:S100)^(1/10)-1 -> 0.070990151 | Q41: =PRODUCT(TableDE3b!T91:T100)^(1/10)-1 -> 0.0058492052
A51: 1960-1970 | B51: =(TableDE3b!H110/TableDE3b!H100)^(1/10)-1 -> 0.041570358 | C51: =(TableDE5a!C110/TableDE5a!C100)^(1/10)-1 -> 0.069759256 | D51: =(1+B51)/(1+G51)-1 -> 0.03180943 | E51: =(1+D51)*(1+J51)/(1+K51)-1 -> 0.043523495 | F51: =(1+D51)*(1+G51)/(1+I51)-1 -> 0.039451461 | G51: =(TableDE3b!E110/TableDE3b!E100)^(1/10)-1 -> 0.0094600103 | H51: =(TableDE3b!F110/TableDE3b!F100)^(1/10)-1 -> 0.0076120425 | I51: =(TableDE3b!G110/TableDE3b!G100)^(1/10)-1 -> 0.0020384768 | J51: =(TableDE15a!C109/TableDE15a!C99)^(1/10)-1 -> 0.037668458 | K51: =(TableDE15a!B109/TableDE15a!B99)^(1/10)-1 -> 0.026020119 | L51: =(TableDE15a!D109/TableDE15a!D99)^(1/10)-1 -> 0.026897277 | O51: =PRODUCT(TableDE3b!R101:R110)^(1/10)-1 -> 0.034952435 | P51: =PRODUCT(TableDE3b!S101:S110)^(1/10)-1 -> 0.034715427 | Q51: =PRODUCT(TableDE3b!T101:T110)^(1/10)-1 -> 0.0070852178
A61: 1970-1980 | B61: =(TableDE3b!H120/TableDE3b!H110)^(1/10)-1 -> 0.026524044 | C61: =(TableDE5a!C120/TableDE5a!C110)^(1/10)-1 -> 0.038607253 | D61: =(1+B61)/(1+G61)-1 -> 0.025769756 | E61: =(1+D61)*(1+J61)/(1+K61)-1 -> 0.026043177 | F61: =(1+D61)*(1+G61)/(1+I61)-1 -> 0.023369765 | G61: =(TableDE3b!E120/TableDE3b!E110)^(1/10)-1 -> 0.00073533882 | H61: =(TableDE3b!F120/TableDE3b!F110)^(1/10)-1 -> 0.0053365804 | I61: =(TableDE3b!G120/TableDE3b!G110)^(1/10)-1 -> 0.0030822482 | J61: =(TableDE15a!C119/TableDE15a!C109)^(1/10)-1 -> 0.050962095 | K61: =(TableDE15a!B119/TableDE15a!B109)^(1/10)-1 -> 0.050682033 | L61: =(TableDE15a!D119/TableDE15a!D109)^(1/10)-1 -> 0.050327793 | O61: =PRODUCT(TableDE3b!R111:R120)^(1/10)-1 -> 0.025635608 | P61: =PRODUCT(TableDE3b!S111:S120)^(1/10)-1 -> 0.026752105 | Q61: =PRODUCT(TableDE3b!T111:T120)^(1/10)-1 -> 0.00065980028
A71: 1980-1990 | B71: =(TableDE3b!H130/TableDE3b!H120)^(1/10)-1 -> 0.023275627 | C71: =(TableDE5a!C130/TableDE5a!C120)^(1/10)-1 -> 0.038540512 | D71: =(1+B71)/(1+G71)-1 -> 0.020566151 | E71: =(1+D71)*(1+J71)/(1+K71)-1 -> 0.022470152 | F71: =(1+D71)*(1+G71)/(1+I71)-1 -> 0.012742793 | G71: =(TableDE3b!E130/TableDE3b!E120)^(1/10)-1 -> 0.0026548755 | H71: =(TableDE3b!F130/TableDE3b!F120)^(1/10)-1 -> 0.010034496 | I71: =(TableDE3b!G130/TableDE3b!G120)^(1/10)-1 -> 0.010400305 | J71: =(TableDE15a!C129/TableDE15a!C119)^(1/10)-1 -> 0.027877595 | K71: =(TableDE15a!B129/TableDE15a!B119)^(1/10)-1 -> 0.025963525 | L71: =(TableDE15a!D129/TableDE15a!D119)^(1/10)-1 -> 0.025419512 | O71: =PRODUCT(TableDE3b!R121:R130)^(1/10)-1 -> 0.019279158 | P71: =PRODUCT(TableDE3b!S121:S130)^(1/10)-1 -> 0.012169681 | Q71: =PRODUCT(TableDE3b!T121:T130)^(1/10)-1 -> 0.0013740008
A81: 1990-2000 | B81: =(TableDE3b!H140/TableDE3b!H130)^(1/10)-1 -> 0.016423833 | C81: =(TableDE5a!C140/TableDE5a!C130)^(1/10)-1 -> 0.036432122 | D81: =(1+B81)/(1+G81)-1 -> 0.012905673 | E81: =(1+D81)*(1+J81)/(1+K81)-1 -> 0.0065840225 | F81: =(1+D81)*(1+G81)/(1+I81)-1 -> 0.013349787 | G81: =(TableDE3b!E140/TableDE3b!E130)^(1/10)-1 -> 0.0034733347 | H81: =(TableDE3b!F140/TableDE3b!F130)^(1/10)-1 -> 0.0030925817 | I81: =(TableDE3b!G140/TableDE3b!G130)^(1/10)-1 -> 0.0030335491 | J81: =(TableDE15a!C139/TableDE15a!C129)^(1/10)-1 -> 0.017818365 | K81: =(TableDE15a!B139/TableDE15a!B129)^(1/10)-1 -> 0.024210571 | L81: =(TableDE15a!D139/TableDE15a!D129)^(1/10)-1 -> 0.019731847 | O81: =PRODUCT(TableDE3b!R131:R140)^(1/10)-1 -> 0.01734521 | P81: =PRODUCT(TableDE3b!S131:S140)^(1/10)-1 -> 0.017484099 | Q81: =PRODUCT(TableDE3b!T131:T140)^(1/10)-1 -> 0.003481726
A91: 2000-2010 | B91: =(TableDE3b!H150/TableDE3b!H140)^(1/10)-1 -> 0.01216843 | C91: =(TableDE5a!C150/TableDE5a!C140)^(1/10)-1 -> 0.026857466 | D91: =(1+B91)/(1+G91)-1 -> 0.012705001 | E91: =(1+D91)*(1+J91)/(1+K91)-1 -> 0.0069607092 | F91: =(1+D91)*(1+G91)/(1+I91)-1 -> 0.0092070263 | G91: =(TableDE3b!E150/TableDE3b!E140)^(1/10)-1 -> -0.00052983899 | H91: =(TableDE3b!F150/TableDE3b!F140)^(1/10)-1 -> 0.0027797503 | I91: =(TableDE3b!G150/TableDE3b!G140)^(1/10)-1 -> 0.0029343871 | J91: =(TableDE15a!C149/TableDE15a!C139)^(1/10)-1 -> 0.009820826 | K91: =(TableDE15a!B149/TableDE15a!B139)^(1/10)-1 -> 0.015581434 | L91: =(TableDE15a!D149/TableDE15a!D139)^(1/10)-1 -> 0.013611762 | O91: =PRODUCT(TableDE3b!R141:R150)^(1/10)-1 -> 0.0086465322 | P91: =PRODUCT(TableDE3b!S141:S150)^(1/10)-1 -> 0.0083471623 | Q91: =PRODUCT(TableDE3b!T141:T150)^(1/10)-1 -> 1.9538036e-05

Sheet TableDE3d
B1: Back to index
A3: Table DE.3d: Summary macro variables, 1870-2011 (annual series)
B5: [1] | C5: [2] | D5: [3] | E5: [4] | F5: [5] | G5: [6] | H5: [7] | I5: [8] | J5: [9] | K5: [10] | L5: [11] | M5: [12] | N5: [13] | O5: [14] | P5: [15]
B6: Boundaries: Reunified Germany (pre-1991 data based on evolution in the boundaries of the time)
B7: Ratio (Private wealth)/ (National income) | C7: Capital share (exc. govt interest) | D7: Labor share | E7: Capital share (inc. govt interest) | F7: Rate of return | G7: Tax rate | H7: Capital tax rate | I7: Labor tax rate | J7: Correct. tax rate | K7: Correct. labor tax rate (exc. replac. taxes) | L7: After-tax capital share | M7: After-tax rate of return | N7: Personal savings rate | O7: Private savings (person. savings + retained earnings) | P7: Rate of war destruction on private wealth
B9: βt = Wt/Yt | C9: αt | D9: 1-αt | E9: αt* | F9: rt = αt*/βt | G9: τt | H9: τKt | I9: τLt | J9: τt* | K9: τLt* | L9: αdt | M9: rdt = αdt /βt = (1-τKt)rt | N9: sot | O9: st | P9: dyt
A10: 1870 | B10: =TableDE1!N10 -> 7.0371635 | C10: =TableDE11b!N9 -> 0.22064603 | D10: =TableDE11b!O9 -> 0.77935397 | E10: =(DataDE1c!X33+DataDE1c!AC33)/DataDE1c!W33 -> 0.23368159 | F10: =E10/B10 -> 0.033206786 | G10: =DataDE1c!AN33/TableDE1!B10 -> 0.051335819 | H10: =G10 -> 0.051335819 | L10: =E10*(1-H10) -> 0.22168535 | M10: =(1-H10)*F10 -> 0.031502089 | O10: =TableDE12c!C10 -> 0.12345847 | P10: =TableDE5a!O10 -> 0
